Workbook

Sheet BIData
A2: =IFERROR(IF(0=LEN(ReferenceData!$A$2),"",ReferenceData!$A$2),"") -> Description | B2: =IFERROR(IF(0=LEN(ReferenceData!$B$2),"",ReferenceData!$B$2),"") -> Ticker | C2: =IFERROR(IF(0=LEN(ReferenceData!$C$2),"",ReferenceData!$C$2),"") -> Field ID | D2: =IFERROR(IF(0=LEN(ReferenceData!$D$2),"",ReferenceData!$D$2),"") -> Field Mnemonic | E2: =IFERROR(IF(0=LEN(ReferenceData!$E$2),"",ReferenceData!$E$2),"") -> Data State | F2: =IFERROR(IF(0=LEN(ReferenceData!$F$2),"",ReferenceData!$F$2),"") -> 2025 Q2 | G2: =IFERROR(IF(0=LEN(ReferenceData!$G$2),"",ReferenceData!$G$2),"") -> 2025 Q1 | H2: =IFERROR(IF(0=LEN(ReferenceData!$H$2),"",ReferenceData!$H$2),"") -> 2024 Q4 | I2: =IFERROR(IF(0=LEN(ReferenceData!$I$2),"",ReferenceData!$I$2),"") -> 2024 Q3 | J2: =IFERROR(IF(0=LEN(ReferenceData!$J$2),"",ReferenceData!$J$2),"") -> 2024 Q2 | K2: =IFERROR(IF(0=LEN(ReferenceData!$K$2),"",ReferenceData!$K$2),"") -> 2024 Q1 | L2: =IFERROR(IF(0=LEN(ReferenceData!$L$2),"",ReferenceData!$L$2),"") -> 2023 Q4 | M2: =IFERROR(IF(0=LEN(ReferenceData!$M$2),"",ReferenceData!$M$2),"") -> 2023 Q3 | N2: =IFERROR(IF(0=LEN(ReferenceData!$N$2),"",ReferenceData!$N$2),"") -> 2023 Q2 | O2: =IFERROR(IF(0=LEN(ReferenceData!$O$2),"",ReferenceData!$O$2),"") -> 2023 Q1 | P2: =IFERROR(IF(0=LEN(ReferenceData!$P$2),"",ReferenceData!$P$2),"") -> 2022 Q4 | Q2: =IFERROR(IF(0=LEN(ReferenceData!$Q$2),"",ReferenceData!$Q$2),"") -> 2022 Q3 | R2: =IFERROR(IF(0=LEN(ReferenceData!$R$2),"",ReferenceData!$R$2),"") -> 2022 Q2 | S2: =IFERROR(IF(0=LEN(ReferenceData!$S$2),"",ReferenceData!$S$2),"") -> 2022 Q1 | T2: =IFERROR(IF(0=LEN(ReferenceData!$T$2),"",ReferenceData!$T$2),"") -> 2021 Q4 | U2: =IFERROR(IF(0=LEN(ReferenceData!$U$2),"",ReferenceData!$U$2),"") -> 2021 Q3 | V2: =IFERROR(IF(0=LEN(ReferenceData!$V$2),"",ReferenceData!$V$2),"") -> 2021 Q2 | W2: =IFERROR(IF(0=LEN(ReferenceData!$W$2),"",ReferenceData!$W$2),"") -> 2021 Q1 | X2: =IFERROR(IF(0=LEN(ReferenceData!$X$2),"",ReferenceData!$X$2),"") -> 2020 Q4 | Y2: =IFERROR(IF(0=LEN(ReferenceData!$Y$2),"",ReferenceData!$Y$2),"") -> 2020 Q3 | Z2: =IFERROR(IF(0=LEN(ReferenceData!$Z$2),"",ReferenceData!$Z$2),"") -> 2020 Q2 | AA2: =IFERROR(IF(0=LEN(ReferenceData!$AA$2),"",ReferenceData!$AA$2),"") -> 2020 Q1 | AB2: =IFERROR(IF(0=LEN(ReferenceData!$AB$2),"",ReferenceData!$AB$2),"") -> 2019 Q4 | AC2: =IFERROR(IF(0=LEN(ReferenceData!$AC$2),"",ReferenceData!$AC$2),"") -> 2019 Q3 | AD2: =IFERROR(IF(0=LEN(ReferenceData!$AD$2),"",ReferenceData!$AD$2),"") -> 2019 Q2 | AE2: =IFERROR(IF(0=LEN(ReferenceData!$AE$2),"",ReferenceData!$AE$2),"") -> 2019 Q1 | AF2: =IFERROR(IF(0=LEN(ReferenceData!$AF$2),"",ReferenceData!$AF$2),"") -> 2018 Q4 | AG2: =IFERROR(IF(0=LEN(ReferenceData!$AG$2),"",ReferenceData!$AG$2),"") -> 2018 Q3 | AH2: =IFERROR(IF(0=LEN(ReferenceData!$AH$2),"",ReferenceData!$AH$2),"") -> 2018 Q2 | AI2: =IFERROR(IF(0=LEN(ReferenceData!$AI$2),"",ReferenceData!$AI$2),"") -> 2018 Q1 | AJ2: =IFERROR(IF(0=LEN(ReferenceData!$AJ$2),"",ReferenceData!$AJ$2),"") -> 2017 Q4 | AK2: =IFERROR(IF(0=LEN(ReferenceData!$AK$2),"",ReferenceData!$AK$2),"") -> 2017 Q3 | AL2: =IFERROR(IF(0=LEN(ReferenceData!$AL$2),"",ReferenceData!$AL$2),"") -> 2017 Q2 | AM2: =IFERROR(IF(0=LEN(ReferenceData!$AM$2),"",ReferenceData!$AM$2),"") -> 2017 Q1 | AN2: =IFERROR(IF(0=LEN(ReferenceData!$AN$2),"",ReferenceData!$AN$2),"") -> 2016 Q4 | AO2: =IFERROR(IF(0=LEN(ReferenceData!$AO$2),"",ReferenceData!$AO$2),"") -> 2016 Q3 | AP2: =IFERROR(IF(0=LEN(ReferenceData!$AP$2),"",ReferenceData!$AP$2),"") -> 2016 Q2 | AQ2: =IFERROR(IF(0=LEN(ReferenceData!$AQ$2),"",ReferenceData!$AQ$2),"") -> 2016 Q1 | AR2: =IFERROR(IF(0=LEN(ReferenceData!$AR$2),"",ReferenceData!$AR$2),"") -> 2015 Q4 | AS2: =IFERROR(IF(0=LEN(ReferenceData!$AS$2),"",ReferenceData!$AS$2),"") -> 2015 Q3 | AT2: =IFERROR(IF(0=LEN(ReferenceData!$AT$2),"",ReferenceData!$AT$2),"") -> 2015 Q2 | AU2: =IFERROR(IF(0=LEN(ReferenceData!$AU$2),"",ReferenceData!$AU$2),"") -> 2015 Q1 | AV2: =IFERROR(IF(0=LEN(ReferenceData!$AV$2),"",ReferenceData!$AV$2),"") -> 2014 Q4 | AW2: =IFERROR(IF(0=LEN(ReferenceData!$AW$2),"",ReferenceData!$AW$2),"") -> 2014 Q3 | AX2: =IFERROR(IF(0=LEN(ReferenceData!$AX$2),"",ReferenceData!$AX$2),"") -> 2014 Q2 | AY2: =IFERROR(IF(0=LEN(ReferenceData!$AY$2),"",ReferenceData!$AY$2),"") -> 2014 Q1 | AZ2: =IFERROR(IF(0=LEN(ReferenceData!$AZ$2),"",ReferenceData!$AZ$2),"") -> 2013 Q4 | BA2: =IFERROR(IF(0=LEN(ReferenceData!$BA$2),"",ReferenceData!$BA$2),"") -> 2013 Q3 | BB2: =IFERROR(IF(0=LEN(ReferenceData!$BB$2),"",ReferenceData!$BB$2),"") -> 2013 Q2 | BC2: =IFERROR(IF(0=LEN(ReferenceData!$BC$2),"",ReferenceData!$BC$2),"") -> 2013 Q1 | BD2: =IFERROR(IF(0=LEN(ReferenceData!$BD$2),"",ReferenceData!$BD$2),"") -> 2012 Q4 | BE2: =IFERROR(IF(0=LEN(ReferenceData!$BE$2),"",ReferenceData!$BE$2),"") -> 2012 Q3 | BF2: =IFERROR(IF(0=LEN(ReferenceData!$BF$2),"",ReferenceData!$BF$2),"") -> 2012 Q2 | BG2: =IFERROR(IF(0=LEN(ReferenceData!$BG$2),"",ReferenceData!$BG$2),"") -> 2012 Q1 | BH2: =IFERROR(IF(0=LEN(ReferenceData!$BH$2),"",ReferenceData!$BH$2),"") -> 2011 Q4 | BI2: =IFERROR(IF(0=LEN(ReferenceData!$BI$2),"",ReferenceData!$BI$2),"") -> 2011 Q3 | BJ2: =IFERROR(IF(0=LEN(ReferenceData!$BJ$2),"",ReferenceData!$BJ$2),"") -> 2011 Q2 | BK2: =IFERROR(IF(0=LEN(ReferenceData!$BK$2),"",ReferenceData!$BK$2),"") -> 2011 Q1 | BL2: =IFERROR(IF(0=LEN(ReferenceData!$BL$2),"",ReferenceData!$BL$2),"") -> 2010 Q4 | BM2: =IFERROR(IF(0=LEN(ReferenceData!$BM$2),"",ReferenceData!$BM$2),"") -> 2010 Q3
A3: =IFERROR(IF(0=LEN(ReferenceData!$A$3),"",ReferenceData!$A$3),"") -> North America (Bil.) - US (USD) | B3: =IFERROR(IF(0=LEN(ReferenceData!$B$3),"",ReferenceData!$B$3),"") -> GDP CUR$ Index | C3: =IFERROR(IF(0=LEN(ReferenceData!$C$3),"",ReferenceData!$C$3),"") -> PR005 | D3: =IFERROR(IF(0=LEN(ReferenceData!$D$3),"",ReferenceData!$D$3),"") -> PX_LAST | E3: =IFERROR(IF(0=LEN(ReferenceData!$E$3),"",ReferenceData!$E$3),"") -> Dynamic | F3: =IFERROR(IF(0=LEN(ReferenceData!$F$3),"",ReferenceData!$F$3),"") -> 30331.117 | G3: =IFERROR(IF(0=LEN(ReferenceData!$G$3),"",ReferenceData!$G$3),"") -> 29962.047 | H3: =IFERROR(IF(0=LEN(ReferenceData!$H$3),"",ReferenceData!$H$3),"") -> 29723.864 | I3: =IFERROR(IF(0=LEN(ReferenceData!$I$3),"",ReferenceData!$I$3),"") -> 29374.914 | J3: =IFERROR(IF(0=LEN(ReferenceData!$J$3),"",ReferenceData!$J$3),"") -> 29016.714 | K3: =IFERROR(IF(0=LEN(ReferenceData!$K$3),"",ReferenceData!$K$3),"") -> 28624.069 | L3: =IFERROR(IF(0=LEN(ReferenceData!$L$3),"",ReferenceData!$L$3),"") -> 28296.967 | M3: =IFERROR(IF(0=LEN(ReferenceData!$M$3),"",ReferenceData!$M$3),"") -> 27967.697 | N3: =IFERROR(IF(0=LEN(ReferenceData!$N$3),"",ReferenceData!$N$3),"") -> 27453.815 | O3: =IFERROR(IF(0=LEN(ReferenceData!$O$3),"",ReferenceData!$O$3),"") -> 27164.359 | P3: =IFERROR(IF(0=LEN(ReferenceData!$P$3),"",ReferenceData!$P$3),"") -> 26734.277 | Q3: =IFERROR(IF(0=LEN(ReferenceData!$Q$3),"",ReferenceData!$Q$3),"") -> 26272.011 | R3: =IFERROR(IF(0=LEN(ReferenceData!$R$3),"",ReferenceData!$R$3),"") -> 25805.791 | S3: =IFERROR(IF(0=LEN(ReferenceData!$S$3),"",ReferenceData!$S$3),"") -> 25215.491 | T3: =IFERROR(IF(0=LEN(ReferenceData!$T$3),"",ReferenceData!$T$3),"") -> 24777.038 | U3: =IFERROR(IF(0=LEN(ReferenceData!$U$3),"",ReferenceData!$U$3),"") -> 23921.991 | V3: =IFERROR(IF(0=LEN(ReferenceData!$V$3),"",ReferenceData!$V$3),"") -> 23368.861 | W3: =IFERROR(IF(0=LEN(ReferenceData!$W$3),"",ReferenceData!$W$3),"") -> 22656.793 | X3: =IFERROR(IF(0=LEN(ReferenceData!$X$3),"",ReferenceData!$X$3),"") -> 22068.767 | Y3: =IFERROR(IF(0=LEN(ReferenceData!$Y$3),"",ReferenceData!$Y$3),"") -> 21684.551 | Z3: =IFERROR(IF(0=LEN(ReferenceData!$Z$3),"",ReferenceData!$Z$3),"") -> 19935.444 | AA3: =IFERROR(IF(0=LEN(ReferenceData!$AA$3),"",ReferenceData!$AA$3),"") -> 21727.657 | AB3: =IFERROR(IF(0=LEN(ReferenceData!$AB$3),"",ReferenceData!$AB$3),"") -> 21933.217 | AC3: =IFERROR(IF(0=LEN(ReferenceData!$AC$3),"",ReferenceData!$AC$3),"") -> 21717.171 | AD3: =IFERROR(IF(0=LEN(ReferenceData!$AD$3),"",ReferenceData!$AD$3),"") -> 21397.938 | AE3: =IFERROR(IF(0=LEN(ReferenceData!$AE$3),"",ReferenceData!$AE$3),"") -> 21111.6 | AF3: =IFERROR(IF(0=LEN(ReferenceData!$AF$3),"",ReferenceData!$AF$3),"") -> 20917.867 | AG3: =IFERROR(IF(0=LEN(ReferenceData!$AG$3),"",ReferenceData!$AG$3),"") -> 20798.73 | AH3: =IFERROR(IF(0=LEN(ReferenceData!$AH$3),"",ReferenceData!$AH$3),"") -> 20580.912 | AI3: =IFERROR(IF(0=LEN(ReferenceData!$AI$3),"",ReferenceData!$AI$3),"") -> 20328.553 | AJ3: =IFERROR(IF(0=LEN(ReferenceData!$AJ$3),"",ReferenceData!$AJ$3),"") -> 20037.088 | AK3: =IFERROR(IF(0=LEN(ReferenceData!$AK$3),"",ReferenceData!$AK$3),"") -> 19692.595 | AL3: =IFERROR(IF(0=LEN(ReferenceData!$AL$3),"",ReferenceData!$AL$3),"") -> 19438.643 | AM3: =IFERROR(IF(0=LEN(ReferenceData!$AM$3),"",ReferenceData!$AM$3),"") -> 19280.084 | AN3: =IFERROR(IF(0=LEN(ReferenceData!$AN$3),"",ReferenceData!$AN$3),"") -> 19089.379 | AO3: =IFERROR(IF(0=LEN(ReferenceData!$AO$3),"",ReferenceData!$AO$3),"") -> 18892.639 | AP3: =IFERROR(IF(0=LEN(ReferenceData!$AP$3),"",ReferenceData!$AP$3),"") -> 18711.702 | AQ3: =IFERROR(IF(0=LEN(ReferenceData!$AQ$3),"",ReferenceData!$AQ$3),"") -> 18525.933 | AR3: =IFERROR(IF(0=LEN(ReferenceData!$AR$3),"",ReferenceData!$AR$3),"") -> 18435.137 | AS3: =IFERROR(IF(0=LEN(ReferenceData!$AS$3),"",ReferenceData!$AS$3),"") -> 18401.626 | AT3: =IFERROR(IF(0=LEN(ReferenceData!$AT$3),"",ReferenceData!$AT$3),"") -> 18279.784 | AU3: =IFERROR(IF(0=LEN(ReferenceData!$AU$3),"",ReferenceData!$AU$3),"") -> 18063.529 | AV3: =IFERROR(IF(0=LEN(ReferenceData!$AV$3),"",ReferenceData!$AV$3),"") -> 17912.079 | AW3: =IFERROR(IF(0=LEN(ReferenceData!$AW$3),"",ReferenceData!$AW$3),"") -> 17804.228 | AX3: =IFERROR(IF(0=LEN(ReferenceData!$AX$3),"",ReferenceData!$AX$3),"") -> 17518.508 | AY3: =IFERROR(IF(0=LEN(ReferenceData!$AY$3),"",ReferenceData!$AY$3),"") -> 17197.738 | AZ3: =IFERROR(IF(0=LEN(ReferenceData!$AZ$3),"",ReferenceData!$AZ$3),"") -> 17192.019 | BA3: =IFERROR(IF(0=LEN(ReferenceData!$BA$3),"",ReferenceData!$BA$3),"") -> 16953.838 | BB3: =IFERROR(IF(0=LEN(ReferenceData!$BB$3),"",ReferenceData!$BB$3),"") -> 16728.687 | BC3: =IFERROR(IF(0=LEN(ReferenceData!$BC$3),"",ReferenceData!$BC$3),"") -> 16648.189 | BD3: =IFERROR(IF(0=LEN(ReferenceData!$BD$3),"",ReferenceData!$BD$3),"") -> 16420.419 | BE3: =IFERROR(IF(0=LEN(ReferenceData!$BE$3),"",ReferenceData!$BE$3),"") -> 16319.54 | BF3: =IFERROR(IF(0=LEN(ReferenceData!$BF$3),"",ReferenceData!$BF$3),"") -> 16207.115 | BG3: =IFERROR(IF(0=LEN(ReferenceData!$BG$3),"",ReferenceData!$BG$3),"") -> 16068.805 | BH3: =IFERROR(IF(0=LEN(ReferenceData!$BH$3),"",ReferenceData!$BH$3),"") -> 15842.259 | BI3: =IFERROR(IF(0=LEN(ReferenceData!$BI$3),"",ReferenceData!$BI$3),"") -> 15647.681 | BJ3: =IFERROR(IF(0=LEN(ReferenceData!$BJ$3),"",ReferenceData!$BJ$3),"") -> 15557.539 | BK3: =IFERROR(IF(0=LEN(ReferenceData!$BK$3),"",ReferenceData!$BK$3),"") -> 15351.448 | BL3: =IFERROR(IF(0=LEN(ReferenceData!$BL$3),"",ReferenceData!$BL$3),"") -> 15309.474 | BM3: =IFERROR(IF(0=LEN(ReferenceData!$BM$3),"",ReferenceData!$BM$3),"") -> 15141.607
A4: =IFERROR(IF(0=LEN(ReferenceData!$A$4),"",ReferenceData!$A$4),"") -> Personal Consumption Expenditures | B4: =IFERROR(IF(0=LEN(ReferenceData!$B$4),"",ReferenceData!$B$4),"") -> GDP$PCE Index | C4: =IFERROR(IF(0=LEN(ReferenceData!$C$4),"",ReferenceData!$C$4),"") -> PR005 | D4: =IFERROR(IF(0=LEN(ReferenceData!$D$4),"",ReferenceData!$D$4),"") -> PX_LAST | E4: =IFERROR(IF(0=LEN(ReferenceData!$E$4),"",ReferenceData!$E$4),"") -> Dynamic | F4: =IFERROR(IF(0=LEN(ReferenceData!$F$4),"",ReferenceData!$F$4),"") -> 20640.878 | G4: =IFERROR(IF(0=LEN(ReferenceData!$G$4),"",ReferenceData!$G$4),"") -> 20461.602 | H4: =IFERROR(IF(0=LEN(ReferenceData!$H$4),"",ReferenceData!$H$4),"") -> 20255.455 | I4: =IFERROR(IF(0=LEN(ReferenceData!$I$4),"",ReferenceData!$I$4),"") -> 19938.425 | J4: =IFERROR(IF(0=LEN(ReferenceData!$J$4),"",ReferenceData!$J$4),"") -> 19682.699 | K4: =IFERROR(IF(0=LEN(ReferenceData!$K$4),"",ReferenceData!$K$4),"") -> 19424.775 | L4: =IFERROR(IF(0=LEN(ReferenceData!$L$4),"",ReferenceData!$L$4),"") -> 19170.154 | M4: =IFERROR(IF(0=LEN(ReferenceData!$M$4),"",ReferenceData!$M$4),"") -> 18928.987 | N4: =IFERROR(IF(0=LEN(ReferenceData!$N$4),"",ReferenceData!$N$4),"") -> 18685.724 | O4: =IFERROR(IF(0=LEN(ReferenceData!$O$4),"",ReferenceData!$O$4),"") -> 18506.211 | P4: =IFERROR(IF(0=LEN(ReferenceData!$P$4),"",ReferenceData!$P$4),"") -> 18108.27 | Q4: =IFERROR(IF(0=LEN(ReferenceData!$Q$4),"",ReferenceData!$Q$4),"") -> 17876.234 | R4: =IFERROR(IF(0=LEN(ReferenceData!$R$4),"",ReferenceData!$R$4),"") -> 17603.753 | S4: =IFERROR(IF(0=LEN(ReferenceData!$S$4),"",ReferenceData!$S$4),"") -> 17175.105 | T4: =IFERROR(IF(0=LEN(ReferenceData!$T$4),"",ReferenceData!$T$4),"") -> 16816.132 | U4: =IFERROR(IF(0=LEN(ReferenceData!$U$4),"",ReferenceData!$U$4),"") -> 16363.876 | V4: =IFERROR(IF(0=LEN(ReferenceData!$V$4),"",ReferenceData!$V$4),"") -> 16016.346 | W4: =IFERROR(IF(0=LEN(ReferenceData!$W$4),"",ReferenceData!$W$4),"") -> 15259.427 | X4: =IFERROR(IF(0=LEN(ReferenceData!$X$4),"",ReferenceData!$X$4),"") -> 14752.732 | Y4: =IFERROR(IF(0=LEN(ReferenceData!$Y$4),"",ReferenceData!$Y$4),"") -> 14478.033 | Z4: =IFERROR(IF(0=LEN(ReferenceData!$Z$4),"",ReferenceData!$Z$4),"") -> 13175.637 | AA4: =IFERROR(IF(0=LEN(ReferenceData!$AA$4),"",ReferenceData!$AA$4),"") -> 14496.227 | AB4: =IFERROR(IF(0=LEN(ReferenceData!$AB$4),"",ReferenceData!$AB$4),"") -> 14701.038 | AC4: =IFERROR(IF(0=LEN(ReferenceData!$AC$4),"",ReferenceData!$AC$4),"") -> 14548.282 | AD4: =IFERROR(IF(0=LEN(ReferenceData!$AD$4),"",ReferenceData!$AD$4),"") -> 14350.662 | AE4: =IFERROR(IF(0=LEN(ReferenceData!$AE$4),"",ReferenceData!$AE$4),"") -> 14150.191 | AF4: =IFERROR(IF(0=LEN(ReferenceData!$AF$4),"",ReferenceData!$AF$4),"") -> 14099.199 | AG4: =IFERROR(IF(0=LEN(ReferenceData!$AG$4),"",ReferenceData!$AG$4),"") -> 14002.199 | AH4: =IFERROR(IF(0=LEN(ReferenceData!$AH$4),"",ReferenceData!$AH$4),"") -> 13891.294 | AI4: =IFERROR(IF(0=LEN(ReferenceData!$AI$4),"",ReferenceData!$AI$4),"") -> 13745.074 | AJ4: =IFERROR(IF(0=LEN(ReferenceData!$AJ$4),"",ReferenceData!$AJ$4),"") -> 13551.401 | AK4: =IFERROR(IF(0=LEN(ReferenceData!$AK$4),"",ReferenceData!$AK$4),"") -> 13325.065 | AL4: =IFERROR(IF(0=LEN(ReferenceData!$AL$4),"",ReferenceData!$AL$4),"") -> 13188.73 | AM4: =IFERROR(IF(0=LEN(ReferenceData!$AM$4),"",ReferenceData!$AM$4),"") -> 13097.306 | AN4: =IFERROR(IF(0=LEN(ReferenceData!$AN$4),"",ReferenceData!$AN$4),"") -> 12921.989 | AO4: =IFERROR(IF(0=LEN(ReferenceData!$AO$4),"",ReferenceData!$AO$4),"") -> 12797.126 | AP4: =IFERROR(IF(0=LEN(ReferenceData!$AP$4),"",ReferenceData!$AP$4),"") -> 12665.124 | AQ4: =IFERROR(IF(0=LEN(ReferenceData!$AQ$4),"",ReferenceData!$AQ$4),"") -> 12523.156 | AR4: =IFERROR(IF(0=LEN(ReferenceData!$AR$4),"",ReferenceData!$AR$4),"") -> 12423.353 | AS4: =IFERROR(IF(0=LEN(ReferenceData!$AS$4),"",ReferenceData!$AS$4),"") -> 12382.494 | AT4: =IFERROR(IF(0=LEN(ReferenceData!$AT$4),"",ReferenceData!$AT$4),"") -> 12264.14 | AU4: =IFERROR(IF(0=LEN(ReferenceData!$AU$4),"",ReferenceData!$AU$4),"") -> 12119.763 | AV4: =IFERROR(IF(0=LEN(ReferenceData!$AV$4),"",ReferenceData!$AV$4),"") -> 12081.561 | AW4: =IFERROR(IF(0=LEN(ReferenceData!$AW$4),"",ReferenceData!$AW$4),"") -> 11959.79 | AX4: =IFERROR(IF(0=LEN(ReferenceData!$AX$4),"",ReferenceData!$AX$4),"") -> 11810.451 | AY4: =IFERROR(IF(0=LEN(ReferenceData!$AY$4),"",ReferenceData!$AY$4),"") -> 11646.001 | AZ4: =IFERROR(IF(0=LEN(ReferenceData!$AZ$4),"",ReferenceData!$AZ$4),"") -> 11551.229 | BA4: =IFERROR(IF(0=LEN(ReferenceData!$BA$4),"",ReferenceData!$BA$4),"") -> 11408.359 | BB4: =IFERROR(IF(0=LEN(ReferenceData!$BB$4),"",ReferenceData!$BB$4),"") -> 11315.681 | BC4: =IFERROR(IF(0=LEN(ReferenceData!$BC$4),"",ReferenceData!$BC$4),"") -> 11277.664 | BD4: =IFERROR(IF(0=LEN(ReferenceData!$BD$4),"",ReferenceData!$BD$4),"") -> 11165.703 | BE4: =IFERROR(IF(0=LEN(ReferenceData!$BE$4),"",ReferenceData!$BE$4),"") -> 11059.393 | BF4: =IFERROR(IF(0=LEN(ReferenceData!$BF$4),"",ReferenceData!$BF$4),"") -> 11005.055 | BG4: =IFERROR(IF(0=LEN(ReferenceData!$BG$4),"",ReferenceData!$BG$4),"") -> 10959.301 | BH4: =IFERROR(IF(0=LEN(ReferenceData!$BH$4),"",ReferenceData!$BH$4),"") -> 10809.186 | BI4: =IFERROR(IF(0=LEN(ReferenceData!$BI$4),"",ReferenceData!$BI$4),"") -> 10755.029 | BJ4: =IFERROR(IF(0=LEN(ReferenceData!$BJ$4),"",ReferenceData!$BJ$4),"") -> 10673.018 | BK4: =IFERROR(IF(0=LEN(ReferenceData!$BK$4),"",ReferenceData!$BK$4),"") -> 10558.195 | BL4: =IFERROR(IF(0=LEN(ReferenceData!$BL$4),"",ReferenceData!$BL$4),"") -> 10430.304 | BM4: =IFERROR(IF(0=LEN(ReferenceData!$BM$4),"",ReferenceData!$BM$4),"") -> 10300.754
A5: =IFERROR(IF(0=LEN(ReferenceData!$A$5),"",ReferenceData!$A$5),"") -> Fixed Investment | B5: =IFERROR(IF(0=LEN(ReferenceData!$B$5),"",ReferenceData!$B$5),"") -> GPDIFXIN Index | C5: =IFERROR(IF(0=LEN(ReferenceData!$C$5),"",ReferenceData!$C$5),"") -> PR005 | D5: =IFERROR(IF(0=LEN(ReferenceData!$D$5),"",ReferenceData!$D$5),"") -> PX_LAST | E5: =IFERROR(IF(0=LEN(ReferenceData!$E$5),"",ReferenceData!$E$5),"") -> Dynamic | F5: =IFERROR(IF(0=LEN(ReferenceData!$F$5),"",ReferenceData!$F$5),"") -> 5402.683 | G5: =IFERROR(IF(0=LEN(ReferenceData!$G$5),"",ReferenceData!$G$5),"") -> 5388.729 | H5: =IFERROR(IF(0=LEN(ReferenceData!$H$5),"",ReferenceData!$H$5),"") -> 5275.129 | I5: =IFERROR(IF(0=LEN(ReferenceData!$I$5),"",ReferenceData!$I$5),"") -> 5269.195 | J5: =IFERROR(IF(0=LEN(ReferenceData!$J$5),"",ReferenceData!$J$5),"") -> 5201.053 | K5: =IFERROR(IF(0=LEN(ReferenceData!$K$5),"",ReferenceData!$K$5),"") -> 5138.499 | L5: =IFERROR(IF(0=LEN(ReferenceData!$L$5),"",ReferenceData!$L$5),"") -> 5046.126 | M5: =IFERROR(IF(0=LEN(ReferenceData!$M$5),"",ReferenceData!$M$5),"") -> 4974.163 | N5: =IFERROR(IF(0=LEN(ReferenceData!$N$5),"",ReferenceData!$N$5),"") -> 4925.655 | O5: =IFERROR(IF(0=LEN(ReferenceData!$O$5),"",ReferenceData!$O$5),"") -> 4826.317 | P5: =IFERROR(IF(0=LEN(ReferenceData!$P$5),"",ReferenceData!$P$5),"") -> 4749.042 | Q5: =IFERROR(IF(0=LEN(ReferenceData!$Q$5),"",ReferenceData!$Q$5),"") -> 4727.803 | R5: =IFERROR(IF(0=LEN(ReferenceData!$R$5),"",ReferenceData!$R$5),"") -> 4669.571 | S5: =IFERROR(IF(0=LEN(ReferenceData!$S$5),"",ReferenceData!$S$5),"") -> 4539.883 | T5: =IFERROR(IF(0=LEN(ReferenceData!$T$5),"",ReferenceData!$T$5),"") -> 4346.39 | U5: =IFERROR(IF(0=LEN(ReferenceData!$U$5),"",ReferenceData!$U$5),"") -> 4231.018 | V5: =IFERROR(IF(0=LEN(ReferenceData!$V$5),"",ReferenceData!$V$5),"") -> 4182.192 | W5: =IFERROR(IF(0=LEN(ReferenceData!$W$5),"",ReferenceData!$W$5),"") -> 4086.717 | X5: =IFERROR(IF(0=LEN(ReferenceData!$X$5),"",ReferenceData!$X$5),"") -> 3968.294 | Y5: =IFERROR(IF(0=LEN(ReferenceData!$Y$5),"",ReferenceData!$Y$5),"") -> 3802.372 | Z5: =IFERROR(IF(0=LEN(ReferenceData!$Z$5),"",ReferenceData!$Z$5),"") -> 3552.634 | AA5: =IFERROR(IF(0=LEN(ReferenceData!$AA$5),"",ReferenceData!$AA$5),"") -> 3841.036 | AB5: =IFERROR(IF(0=LEN(ReferenceData!$AB$5),"",ReferenceData!$AB$5),"") -> 3857.115 | AC5: =IFERROR(IF(0=LEN(ReferenceData!$AC$5),"",ReferenceData!$AC$5),"") -> 3869.365 | AD5: =IFERROR(IF(0=LEN(ReferenceData!$AD$5),"",ReferenceData!$AD$5),"") -> 3820.789 | AE5: =IFERROR(IF(0=LEN(ReferenceData!$AE$5),"",ReferenceData!$AE$5),"") -> 3735.845 | AF5: =IFERROR(IF(0=LEN(ReferenceData!$AF$5),"",ReferenceData!$AF$5),"") -> 3706.704 | AG5: =IFERROR(IF(0=LEN(ReferenceData!$AG$5),"",ReferenceData!$AG$5),"") -> 3690.028 | AH5: =IFERROR(IF(0=LEN(ReferenceData!$AH$5),"",ReferenceData!$AH$5),"") -> 3666.129 | AI5: =IFERROR(IF(0=LEN(ReferenceData!$AI$5),"",ReferenceData!$AI$5),"") -> 3610.589 | AJ5: =IFERROR(IF(0=LEN(ReferenceData!$AJ$5),"",ReferenceData!$AJ$5),"") -> 3530.448 | AK5: =IFERROR(IF(0=LEN(ReferenceData!$AK$5),"",ReferenceData!$AK$5),"") -> 3445.283 | AL5: =IFERROR(IF(0=LEN(ReferenceData!$AL$5),"",ReferenceData!$AL$5),"") -> 3407.44 | AM5: =IFERROR(IF(0=LEN(ReferenceData!$AM$5),"",ReferenceData!$AM$5),"") -> 3356.791 | AN5: =IFERROR(IF(0=LEN(ReferenceData!$AN$5),"",ReferenceData!$AN$5),"") -> 3302.805 | AO5: =IFERROR(IF(0=LEN(ReferenceData!$AO$5),"",ReferenceData!$AO$5),"") -> 3256.247 | AP5: =IFERROR(IF(0=LEN(ReferenceData!$AP$5),"",ReferenceData!$AP$5),"") -> 3215.897 | AQ5: =IFERROR(IF(0=LEN(ReferenceData!$AQ$5),"",ReferenceData!$AQ$5),"") -> 3181.999 | AR5: =IFERROR(IF(0=LEN(ReferenceData!$AR$5),"",ReferenceData!$AR$5),"") -> 3169.729 | AS5: =IFERROR(IF(0=LEN(ReferenceData!$AS$5),"",ReferenceData!$AS$5),"") -> 3176.809 | AT5: =IFERROR(IF(0=LEN(ReferenceData!$AT$5),"",ReferenceData!$AT$5),"") -> 3139.856 | AU5: =IFERROR(IF(0=LEN(ReferenceData!$AU$5),"",ReferenceData!$AU$5),"") -> 3107.041 | AV5: =IFERROR(IF(0=LEN(ReferenceData!$AV$5),"",ReferenceData!$AV$5),"") -> 3086.53 | AW5: =IFERROR(IF(0=LEN(ReferenceData!$AW$5),"",ReferenceData!$AW$5),"") -> 3038.113 | AX5: =IFERROR(IF(0=LEN(ReferenceData!$AX$5),"",ReferenceData!$AX$5),"") -> 2961.343 | AY5: =IFERROR(IF(0=LEN(ReferenceData!$AY$5),"",ReferenceData!$AY$5),"") -> 2870.77 | AZ5: =IFERROR(IF(0=LEN(ReferenceData!$AZ$5),"",ReferenceData!$AZ$5),"") -> 2816.948 | BA5: =IFERROR(IF(0=LEN(ReferenceData!$BA$5),"",ReferenceData!$BA$5),"") -> 2755.705 | BB5: =IFERROR(IF(0=LEN(ReferenceData!$BB$5),"",ReferenceData!$BB$5),"") -> 2697.549 | BC5: =IFERROR(IF(0=LEN(ReferenceData!$BC$5),"",ReferenceData!$BC$5),"") -> 2661.196 | BD5: =IFERROR(IF(0=LEN(ReferenceData!$BD$5),"",ReferenceData!$BD$5),"") -> 2609.548 | BE5: =IFERROR(IF(0=LEN(ReferenceData!$BE$5),"",ReferenceData!$BE$5),"") -> 2559.69 | BF5: =IFERROR(IF(0=LEN(ReferenceData!$BF$5),"",ReferenceData!$BF$5),"") -> 2545.458 | BG5: =IFERROR(IF(0=LEN(ReferenceData!$BG$5),"",ReferenceData!$BG$5),"") -> 2487.473 | BH5: =IFERROR(IF(0=LEN(ReferenceData!$BH$5),"",ReferenceData!$BH$5),"") -> 2400.138 | BI5: =IFERROR(IF(0=LEN(ReferenceData!$BI$5),"",ReferenceData!$BI$5),"") -> 2334.873 | BJ5: =IFERROR(IF(0=LEN(ReferenceData!$BJ$5),"",ReferenceData!$BJ$5),"") -> 2236.305 | BK5: =IFERROR(IF(0=LEN(ReferenceData!$BK$5),"",ReferenceData!$BK$5),"") -> 2173.885 | BL5: =IFERROR(IF(0=LEN(ReferenceData!$BL$5),"",ReferenceData!$BL$5),"") -> 2171.138 | BM5: =IFERROR(IF(0=LEN(ReferenceData!$BM$5),"",ReferenceData!$BM$5),"") -> 2123.598
A6: =IFERROR(IF(0=LEN(ReferenceData!$A$6),"",ReferenceData!$A$6),"") -> Change in Private Inventories | B6: =IFERROR(IF(0=LEN(ReferenceData!$B$6),"",ReferenceData!$B$6),"") -> GDP$PICG Index | C6: =IFERROR(IF(0=LEN(ReferenceData!$C$6),"",ReferenceData!$C$6),"") -> PR005 | D6: =IFERROR(IF(0=LEN(ReferenceData!$D$6),"",ReferenceData!$D$6),"") -> PX_LAST | E6: =IFERROR(IF(0=LEN(ReferenceData!$E$6),"",ReferenceData!$E$6),"") -> Dynamic | F6: =IFERROR(IF(0=LEN(ReferenceData!$F$6),"",ReferenceData!$F$6),"") -> -29.716 | G6: =IFERROR(IF(0=LEN(ReferenceData!$G$6),"",ReferenceData!$G$6),"") -> 206.965 | H6: =IFERROR(IF(0=LEN(ReferenceData!$H$6),"",ReferenceData!$H$6),"") -> 13.634 | I6: =IFERROR(IF(0=LEN(ReferenceData!$I$6),"",ReferenceData!$I$6),"") -> 75.97 | J6: =IFERROR(IF(0=LEN(ReferenceData!$J$6),"",ReferenceData!$J$6),"") -> 96.792 | K6: =IFERROR(IF(0=LEN(ReferenceData!$K$6),"",ReferenceData!$K$6),"") -> 21.404 | L6: =IFERROR(IF(0=LEN(ReferenceData!$L$6),"",ReferenceData!$L$6),"") -> 56.688 | M6: =IFERROR(IF(0=LEN(ReferenceData!$M$6),"",ReferenceData!$M$6),"") -> 89.189 | N6: =IFERROR(IF(0=LEN(ReferenceData!$N$6),"",ReferenceData!$N$6),"") -> 0.01 | O6: =IFERROR(IF(0=LEN(ReferenceData!$O$6),"",ReferenceData!$O$6),"") -> 20.894 | P6: =IFERROR(IF(0=LEN(ReferenceData!$P$6),"",ReferenceData!$P$6),"") -> 162.858 | Q6: =IFERROR(IF(0=LEN(ReferenceData!$Q$6),"",ReferenceData!$Q$6),"") -> 73.821 | R6: =IFERROR(IF(0=LEN(ReferenceData!$R$6),"",ReferenceData!$R$6),"") -> 116.971 | S6: =IFERROR(IF(0=LEN(ReferenceData!$S$6),"",ReferenceData!$S$6),"") -> 244.937 | T6: =IFERROR(IF(0=LEN(ReferenceData!$T$6),"",ReferenceData!$T$6),"") -> 252.794 | U6: =IFERROR(IF(0=LEN(ReferenceData!$U$6),"",ReferenceData!$U$6),"") -> 1.807 | V6: =IFERROR(IF(0=LEN(ReferenceData!$V$6),"",ReferenceData!$V$6),"") -> -164.611 | W6: =IFERROR(IF(0=LEN(ReferenceData!$W$6),"",ReferenceData!$W$6),"") -> -41.219 | X6: =IFERROR(IF(0=LEN(ReferenceData!$X$6),"",ReferenceData!$X$6),"") -> 78.055 | Y6: =IFERROR(IF(0=LEN(ReferenceData!$Y$6),"",ReferenceData!$Y$6),"") -> 98.975 | Z6: =IFERROR(IF(0=LEN(ReferenceData!$Z$6),"",ReferenceData!$Z$6),"") -> -282.276 | AA6: =IFERROR(IF(0=LEN(ReferenceData!$AA$6),"",ReferenceData!$AA$6),"") -> -39.039 | AB6: =IFERROR(IF(0=LEN(ReferenceData!$AB$6),"",ReferenceData!$AB$6),"") -> 23.455 | AC6: =IFERROR(IF(0=LEN(ReferenceData!$AC$6),"",ReferenceData!$AC$6),"") -> 70.234 | AD6: =IFERROR(IF(0=LEN(ReferenceData!$AD$6),"",ReferenceData!$AD$6),"") -> 83.207 | AE6: =IFERROR(IF(0=LEN(ReferenceData!$AE$6),"",ReferenceData!$AE$6),"") -> 114.925 | AF6: =IFERROR(IF(0=LEN(ReferenceData!$AF$6),"",ReferenceData!$AF$6),"") -> 95.324 | AG6: =IFERROR(IF(0=LEN(ReferenceData!$AG$6),"",ReferenceData!$AG$6),"") -> 98.664 | AH6: =IFERROR(IF(0=LEN(ReferenceData!$AH$6),"",ReferenceData!$AH$6),"") -> -3.402 | AI6: =IFERROR(IF(0=LEN(ReferenceData!$AI$6),"",ReferenceData!$AI$6),"") -> 35.045 | AJ6: =IFERROR(IF(0=LEN(ReferenceData!$AJ$6),"",ReferenceData!$AJ$6),"") -> 43.998 | AK6: =IFERROR(IF(0=LEN(ReferenceData!$AK$6),"",ReferenceData!$AK$6),"") -> 54.859 | AL6: =IFERROR(IF(0=LEN(ReferenceData!$AL$6),"",ReferenceData!$AL$6),"") -> 25.528 | AM6: =IFERROR(IF(0=LEN(ReferenceData!$AM$6),"",ReferenceData!$AM$6),"") -> 6.311 | AN6: =IFERROR(IF(0=LEN(ReferenceData!$AN$6),"",ReferenceData!$AN$6),"") -> 58.147 | AO6: =IFERROR(IF(0=LEN(ReferenceData!$AO$6),"",ReferenceData!$AO$6),"") -> 5.324 | AP6: =IFERROR(IF(0=LEN(ReferenceData!$AP$6),"",ReferenceData!$AP$6),"") -> 30.484 | AQ6: =IFERROR(IF(0=LEN(ReferenceData!$AQ$6),"",ReferenceData!$AQ$6),"") -> 62.318 | AR6: =IFERROR(IF(0=LEN(ReferenceData!$AR$6),"",ReferenceData!$AR$6),"") -> 107.15 | AS6: =IFERROR(IF(0=LEN(ReferenceData!$AS$6),"",ReferenceData!$AS$6),"") -> 126.851 | AT6: =IFERROR(IF(0=LEN(ReferenceData!$AT$6),"",ReferenceData!$AT$6),"") -> 151.248 | AU6: =IFERROR(IF(0=LEN(ReferenceData!$AU$6),"",ReferenceData!$AU$6),"") -> 175.242 | AV6: =IFERROR(IF(0=LEN(ReferenceData!$AV$6),"",ReferenceData!$AV$6),"") -> 85.485 | AW6: =IFERROR(IF(0=LEN(ReferenceData!$AW$6),"",ReferenceData!$AW$6),"") -> 103.934 | AX6: =IFERROR(IF(0=LEN(ReferenceData!$AX$6),"",ReferenceData!$AX$6),"") -> 97.753 | AY6: =IFERROR(IF(0=LEN(ReferenceData!$AY$6),"",ReferenceData!$AY$6),"") -> 51.995 | AZ6: =IFERROR(IF(0=LEN(ReferenceData!$AZ$6),"",ReferenceData!$AZ$6),"") -> 117.343 | BA6: =IFERROR(IF(0=LEN(ReferenceData!$BA$6),"",ReferenceData!$BA$6),"") -> 136.649 | BB6: =IFERROR(IF(0=LEN(ReferenceData!$BB$6),"",ReferenceData!$BB$6),"") -> 82.693 | BC6: =IFERROR(IF(0=LEN(ReferenceData!$BC$6),"",ReferenceData!$BC$6),"") -> 85.223 | BD6: =IFERROR(IF(0=LEN(ReferenceData!$BD$6),"",ReferenceData!$BD$6),"") -> 28.734 | BE6: =IFERROR(IF(0=LEN(ReferenceData!$BE$6),"",ReferenceData!$BE$6),"") -> 84.429 | BF6: =IFERROR(IF(0=LEN(ReferenceData!$BF$6),"",ReferenceData!$BF$6),"") -> 91.406 | BG6: =IFERROR(IF(0=LEN(ReferenceData!$BG$6),"",ReferenceData!$BG$6),"") -> 80.278 | BH6: =IFERROR(IF(0=LEN(ReferenceData!$BH$6),"",ReferenceData!$BH$6),"") -> 103.956 | BI6: =IFERROR(IF(0=LEN(ReferenceData!$BI$6),"",ReferenceData!$BI$6),"") -> -12.033 | BJ6: =IFERROR(IF(0=LEN(ReferenceData!$BJ$6),"",ReferenceData!$BJ$6),"") -> 61.047 | BK6: =IFERROR(IF(0=LEN(ReferenceData!$BK$6),"",ReferenceData!$BK$6),"") -> 32.078 | BL6: =IFERROR(IF(0=LEN(ReferenceData!$BL$6),"",ReferenceData!$BL$6),"") -> 67.301 | BM6: =IFERROR(IF(0=LEN(ReferenceData!$BM$6),"",ReferenceData!$BM$6),"") -> 112.897
A7: =IFERROR(IF(0=LEN(ReferenceData!$A$7),"",ReferenceData!$A$7),"") -> Government: Consumption Expenditure | B7: =IFERROR(IF(0=LEN(ReferenceData!$B$7),"",ReferenceData!$B$7),"") -> GCEXCONE Index | C7: =IFERROR(IF(0=LEN(ReferenceData!$C$7),"",ReferenceData!$C$7),"") -> PR005 | D7: =IFERROR(IF(0=LEN(ReferenceData!$D$7),"",ReferenceData!$D$7),"") -> PX_LAST | E7: =IFERROR(IF(0=LEN(ReferenceData!$E$7),"",ReferenceData!$E$7),"") -> Dynamic | F7: =IFERROR(IF(0=LEN(ReferenceData!$F$7),"",ReferenceData!$F$7),"") -> 4054.615 | G7: =IFERROR(IF(0=LEN(ReferenceData!$G$7),"",ReferenceData!$G$7),"") -> 4030.962 | H7: =IFERROR(IF(0=LEN(ReferenceData!$H$7),"",ReferenceData!$H$7),"") -> 3996.878 | I7: =IFERROR(IF(0=LEN(ReferenceData!$I$7),"",ReferenceData!$I$7),"") -> 3947.656 | J7: =IFERROR(IF(0=LEN(ReferenceData!$J$7),"",ReferenceData!$J$7),"") -> 3882.139 | K7: =IFERROR(IF(0=LEN(ReferenceData!$K$7),"",ReferenceData!$K$7),"") -> 3840.088 | L7: =IFERROR(IF(0=LEN(ReferenceData!$L$7),"",ReferenceData!$L$7),"") -> 3781.725 | M7: =IFERROR(IF(0=LEN(ReferenceData!$M$7),"",ReferenceData!$M$7),"") -> 3758.931 | N7: =IFERROR(IF(0=LEN(ReferenceData!$N$7),"",ReferenceData!$N$7),"") -> 3674.318 | O7: =IFERROR(IF(0=LEN(ReferenceData!$O$7),"",ReferenceData!$O$7),"") -> 3680.844 | P7: =IFERROR(IF(0=LEN(ReferenceData!$P$7),"",ReferenceData!$P$7),"") -> 3641.91 | Q7: =IFERROR(IF(0=LEN(ReferenceData!$Q$7),"",ReferenceData!$Q$7),"") -> 3590.272 | R7: =IFERROR(IF(0=LEN(ReferenceData!$R$7),"",ReferenceData!$R$7),"") -> 3560.032 | S7: =IFERROR(IF(0=LEN(ReferenceData!$S$7),"",ReferenceData!$S$7),"") -> 3473.916 | T7: =IFERROR(IF(0=LEN(ReferenceData!$T$7),"",ReferenceData!$T$7),"") -> 3440.748 | U7: =IFERROR(IF(0=LEN(ReferenceData!$U$7),"",ReferenceData!$U$7),"") -> 3386.91 | V7: =IFERROR(IF(0=LEN(ReferenceData!$V$7),"",ReferenceData!$V$7),"") -> 3348.272 | W7: =IFERROR(IF(0=LEN(ReferenceData!$W$7),"",ReferenceData!$W$7),"") -> 3325.207 | X7: =IFERROR(IF(0=LEN(ReferenceData!$X$7),"",ReferenceData!$X$7),"") -> 3195.54 | Y7: =IFERROR(IF(0=LEN(ReferenceData!$Y$7),"",ReferenceData!$Y$7),"") -> 3182.435 | Z7: =IFERROR(IF(0=LEN(ReferenceData!$Z$7),"",ReferenceData!$Z$7),"") -> 3209.423 | AA7: =IFERROR(IF(0=LEN(ReferenceData!$AA$7),"",ReferenceData!$AA$7),"") -> 3136.014 | AB7: =IFERROR(IF(0=LEN(ReferenceData!$AB$7),"",ReferenceData!$AB$7),"") -> 3080.936 | AC7: =IFERROR(IF(0=LEN(ReferenceData!$AC$7),"",ReferenceData!$AC$7),"") -> 3034.139 | AD7: =IFERROR(IF(0=LEN(ReferenceData!$AD$7),"",ReferenceData!$AD$7),"") -> 2994.223 | AE7: =IFERROR(IF(0=LEN(ReferenceData!$AE$7),"",ReferenceData!$AE$7),"") -> 2938.925 | AF7: =IFERROR(IF(0=LEN(ReferenceData!$AF$7),"",ReferenceData!$AF$7),"") -> 2912.96 | AG7: =IFERROR(IF(0=LEN(ReferenceData!$AG$7),"",ReferenceData!$AG$7),"") -> 2885.521 | AH7: =IFERROR(IF(0=LEN(ReferenceData!$AH$7),"",ReferenceData!$AH$7),"") -> 2839.147 | AI7: =IFERROR(IF(0=LEN(ReferenceData!$AI$7),"",ReferenceData!$AI$7),"") -> 2801.299 | AJ7: =IFERROR(IF(0=LEN(ReferenceData!$AJ$7),"",ReferenceData!$AJ$7),"") -> 2761.375 | AK7: =IFERROR(IF(0=LEN(ReferenceData!$AK$7),"",ReferenceData!$AK$7),"") -> 2715.851 | AL7: =IFERROR(IF(0=LEN(ReferenceData!$AL$7),"",ReferenceData!$AL$7),"") -> 2695.724 | AM7: =IFERROR(IF(0=LEN(ReferenceData!$AM$7),"",ReferenceData!$AM$7),"") -> 2689.905 | AN7: =IFERROR(IF(0=LEN(ReferenceData!$AN$7),"",ReferenceData!$AN$7),"") -> 2680.996 | AO7: =IFERROR(IF(0=LEN(ReferenceData!$AO$7),"",ReferenceData!$AO$7),"") -> 2668.281 | AP7: =IFERROR(IF(0=LEN(ReferenceData!$AP$7),"",ReferenceData!$AP$7),"") -> 2642.923 | AQ7: =IFERROR(IF(0=LEN(ReferenceData!$AQ$7),"",ReferenceData!$AQ$7),"") -> 2621.296 | AR7: =IFERROR(IF(0=LEN(ReferenceData!$AR$7),"",ReferenceData!$AR$7),"") -> 2624.356 | AS7: =IFERROR(IF(0=LEN(ReferenceData!$AS$7),"",ReferenceData!$AS$7),"") -> 2615.896 | AT7: =IFERROR(IF(0=LEN(ReferenceData!$AT$7),"",ReferenceData!$AT$7),"") -> 2601.375 | AU7: =IFERROR(IF(0=LEN(ReferenceData!$AU$7),"",ReferenceData!$AU$7),"") -> 2574.327 | AV7: =IFERROR(IF(0=LEN(ReferenceData!$AV$7),"",ReferenceData!$AV$7),"") -> 2571.889 | AW7: =IFERROR(IF(0=LEN(ReferenceData!$AW$7),"",ReferenceData!$AW$7),"") -> 2581.399 | AX7: =IFERROR(IF(0=LEN(ReferenceData!$AX$7),"",ReferenceData!$AX$7),"") -> 2548.426 | AY7: =IFERROR(IF(0=LEN(ReferenceData!$AY$7),"",ReferenceData!$AY$7),"") -> 2547.392 | AZ7: =IFERROR(IF(0=LEN(ReferenceData!$AZ$7),"",ReferenceData!$AZ$7),"") -> 2536.463 | BA7: =IFERROR(IF(0=LEN(ReferenceData!$BA$7),"",ReferenceData!$BA$7),"") -> 2530.734 | BB7: =IFERROR(IF(0=LEN(ReferenceData!$BB$7),"",ReferenceData!$BB$7),"") -> 2531.613 | BC7: =IFERROR(IF(0=LEN(ReferenceData!$BC$7),"",ReferenceData!$BC$7),"") -> 2524.169 | BD7: =IFERROR(IF(0=LEN(ReferenceData!$BD$7),"",ReferenceData!$BD$7),"") -> 2521.55 | BE7: =IFERROR(IF(0=LEN(ReferenceData!$BE$7),"",ReferenceData!$BE$7),"") -> 2519.684 | BF7: =IFERROR(IF(0=LEN(ReferenceData!$BF$7),"",ReferenceData!$BF$7),"") -> 2503.34 | BG7: =IFERROR(IF(0=LEN(ReferenceData!$BG$7),"",ReferenceData!$BG$7),"") -> 2517.184 | BH7: =IFERROR(IF(0=LEN(ReferenceData!$BH$7),"",ReferenceData!$BH$7),"") -> 2495.035 | BI7: =IFERROR(IF(0=LEN(ReferenceData!$BI$7),"",ReferenceData!$BI$7),"") -> 2501.81 | BJ7: =IFERROR(IF(0=LEN(ReferenceData!$BJ$7),"",ReferenceData!$BJ$7),"") -> 2531.982 | BK7: =IFERROR(IF(0=LEN(ReferenceData!$BK$7),"",ReferenceData!$BK$7),"") -> 2516.417 | BL7: =IFERROR(IF(0=LEN(ReferenceData!$BL$7),"",ReferenceData!$BL$7),"") -> 2516.921 | BM7: =IFERROR(IF(0=LEN(ReferenceData!$BM$7),"",ReferenceData!$BM$7),"") -> 2508.885
A8: =IFERROR(IF(0=LEN(ReferenceData!$A$8),"",ReferenceData!$A$8),"") -> Government: Gross Investment | B8: =IFERROR(IF(0=LEN(ReferenceData!$B$8),"",ReferenceData!$B$8),"") -> GCEXGRSS Index | C8: =IFERROR(IF(0=LEN(ReferenceData!$C$8),"",ReferenceData!$C$8),"") -> PR005 | D8: =IFERROR(IF(0=LEN(ReferenceData!$D$8),"",ReferenceData!$D$8),"") -> PX_LAST | E8: =IFERROR(IF(0=LEN(ReferenceData!$E$8),"",ReferenceData!$E$8),"") -> Dynamic | F8: =IFERROR(IF(0=LEN(ReferenceData!$F$8),"",ReferenceData!$F$8),"") -> 1135.041 | G8: =IFERROR(IF(0=LEN(ReferenceData!$G$8),"",ReferenceData!$G$8),"") -> 1118.93 | H8: =IFERROR(IF(0=LEN(ReferenceData!$H$8),"",ReferenceData!$H$8),"") -> 1102.851 | I8: =IFERROR(IF(0=LEN(ReferenceData!$I$8),"",ReferenceData!$I$8),"") -> 1087.352 | J8: =IFERROR(IF(0=LEN(ReferenceData!$J$8),"",ReferenceData!$J$8),"") -> 1060.902 | K8: =IFERROR(IF(0=LEN(ReferenceData!$K$8),"",ReferenceData!$K$8),"") -> 1040.872 | L8: =IFERROR(IF(0=LEN(ReferenceData!$L$8),"",ReferenceData!$L$8),"") -> 1033.426 | M8: =IFERROR(IF(0=LEN(ReferenceData!$M$8),"",ReferenceData!$M$8),"") -> 997.517 | N8: =IFERROR(IF(0=LEN(ReferenceData!$N$8),"",ReferenceData!$N$8),"") -> 971.587 | O8: =IFERROR(IF(0=LEN(ReferenceData!$O$8),"",ReferenceData!$O$8),"") -> 943.742 | P8: =IFERROR(IF(0=LEN(ReferenceData!$P$8),"",ReferenceData!$P$8),"") -> 922.882 | Q8: =IFERROR(IF(0=LEN(ReferenceData!$Q$8),"",ReferenceData!$Q$8),"") -> 889.778 | R8: =IFERROR(IF(0=LEN(ReferenceData!$R$8),"",ReferenceData!$R$8),"") -> 877.577 | S8: =IFERROR(IF(0=LEN(ReferenceData!$S$8),"",ReferenceData!$S$8),"") -> 858.694 | T8: =IFERROR(IF(0=LEN(ReferenceData!$T$8),"",ReferenceData!$T$8),"") -> 841.57 | U8: =IFERROR(IF(0=LEN(ReferenceData!$U$8),"",ReferenceData!$U$8),"") -> 827.06 | V8: =IFERROR(IF(0=LEN(ReferenceData!$V$8),"",ReferenceData!$V$8),"") -> 821.744 | W8: =IFERROR(IF(0=LEN(ReferenceData!$W$8),"",ReferenceData!$W$8),"") -> 822.419 | X8: =IFERROR(IF(0=LEN(ReferenceData!$X$8),"",ReferenceData!$X$8),"") -> 832.455 | Y8: =IFERROR(IF(0=LEN(ReferenceData!$Y$8),"",ReferenceData!$Y$8),"") -> 819.135 | Z8: =IFERROR(IF(0=LEN(ReferenceData!$Z$8),"",ReferenceData!$Z$8),"") -> 816.551 | AA8: =IFERROR(IF(0=LEN(ReferenceData!$AA$8),"",ReferenceData!$AA$8),"") -> 806.998 | AB8: =IFERROR(IF(0=LEN(ReferenceData!$AB$8),"",ReferenceData!$AB$8),"") -> 784.032 | AC8: =IFERROR(IF(0=LEN(ReferenceData!$AC$8),"",ReferenceData!$AC$8),"") -> 780.698 | AD8: =IFERROR(IF(0=LEN(ReferenceData!$AD$8),"",ReferenceData!$AD$8),"") -> 767.02 | AE8: =IFERROR(IF(0=LEN(ReferenceData!$AE$8),"",ReferenceData!$AE$8),"") -> 764.009 | AF8: =IFERROR(IF(0=LEN(ReferenceData!$AF$8),"",ReferenceData!$AF$8),"") -> 737.888 | AG8: =IFERROR(IF(0=LEN(ReferenceData!$AG$8),"",ReferenceData!$AG$8),"") -> 740.565 | AH8: =IFERROR(IF(0=LEN(ReferenceData!$AH$8),"",ReferenceData!$AH$8),"") -> 731.567 | AI8: =IFERROR(IF(0=LEN(ReferenceData!$AI$8),"",ReferenceData!$AI$8),"") -> 712.577 | AJ8: =IFERROR(IF(0=LEN(ReferenceData!$AJ$8),"",ReferenceData!$AJ$8),"") -> 704.762 | AK8: =IFERROR(IF(0=LEN(ReferenceData!$AK$8),"",ReferenceData!$AK$8),"") -> 683.035 | AL8: =IFERROR(IF(0=LEN(ReferenceData!$AL$8),"",ReferenceData!$AL$8),"") -> 674.72 | AM8: =IFERROR(IF(0=LEN(ReferenceData!$AM$8),"",ReferenceData!$AM$8),"") -> 663.191 | AN8: =IFERROR(IF(0=LEN(ReferenceData!$AN$8),"",ReferenceData!$AN$8),"") -> 656.249 | AO8: =IFERROR(IF(0=LEN(ReferenceData!$AO$8),"",ReferenceData!$AO$8),"") -> 646.89 | AP8: =IFERROR(IF(0=LEN(ReferenceData!$AP$8),"",ReferenceData!$AP$8),"") -> 646.644 | AQ8: =IFERROR(IF(0=LEN(ReferenceData!$AQ$8),"",ReferenceData!$AQ$8),"") -> 648.845 | AR8: =IFERROR(IF(0=LEN(ReferenceData!$AR$8),"",ReferenceData!$AR$8),"") -> 633.787 | AS8: =IFERROR(IF(0=LEN(ReferenceData!$AS$8),"",ReferenceData!$AS$8),"") -> 637.658 | AT8: =IFERROR(IF(0=LEN(ReferenceData!$AT$8),"",ReferenceData!$AT$8),"") -> 632.692 | AU8: =IFERROR(IF(0=LEN(ReferenceData!$AU$8),"",ReferenceData!$AU$8),"") -> 613.588 | AV8: =IFERROR(IF(0=LEN(ReferenceData!$AV$8),"",ReferenceData!$AV$8),"") -> 617.364 | AW8: =IFERROR(IF(0=LEN(ReferenceData!$AW$8),"",ReferenceData!$AW$8),"") -> 610.35 | AX8: =IFERROR(IF(0=LEN(ReferenceData!$AX$8),"",ReferenceData!$AX$8),"") -> 605.94 | AY8: =IFERROR(IF(0=LEN(ReferenceData!$AY$8),"",ReferenceData!$AY$8),"") -> 591.669 | AZ8: =IFERROR(IF(0=LEN(ReferenceData!$AZ$8),"",ReferenceData!$AZ$8),"") -> 604.054 | BA8: =IFERROR(IF(0=LEN(ReferenceData!$BA$8),"",ReferenceData!$BA$8),"") -> 604.458 | BB8: =IFERROR(IF(0=LEN(ReferenceData!$BB$8),"",ReferenceData!$BB$8),"") -> 599.53 | BC8: =IFERROR(IF(0=LEN(ReferenceData!$BC$8),"",ReferenceData!$BC$8),"") -> 599.285 | BD8: =IFERROR(IF(0=LEN(ReferenceData!$BD$8),"",ReferenceData!$BD$8),"") -> 610.758 | BE8: =IFERROR(IF(0=LEN(ReferenceData!$BE$8),"",ReferenceData!$BE$8),"") -> 619.428 | BF8: =IFERROR(IF(0=LEN(ReferenceData!$BF$8),"",ReferenceData!$BF$8),"") -> 627.098 | BG8: =IFERROR(IF(0=LEN(ReferenceData!$BG$8),"",ReferenceData!$BG$8),"") -> 626.841 | BH8: =IFERROR(IF(0=LEN(ReferenceData!$BH$8),"",ReferenceData!$BH$8),"") -> 635.731 | BI8: =IFERROR(IF(0=LEN(ReferenceData!$BI$8),"",ReferenceData!$BI$8),"") -> 635.112 | BJ8: =IFERROR(IF(0=LEN(ReferenceData!$BJ$8),"",ReferenceData!$BJ$8),"") -> 636.279 | BK8: =IFERROR(IF(0=LEN(ReferenceData!$BK$8),"",ReferenceData!$BK$8),"") -> 639.351 | BL8: =IFERROR(IF(0=LEN(ReferenceData!$BL$8),"",ReferenceData!$BL$8),"") -> 647.396 | BM8: =IFERROR(IF(0=LEN(ReferenceData!$BM$8),"",ReferenceData!$BM$8),"") -> 649.416
A9: =IFERROR(IF(0=LEN(ReferenceData!$A$9),"",ReferenceData!$A$9),"") -> Exports | B9: =IFERROR(IF(0=LEN(ReferenceData!$B$9),"",ReferenceData!$B$9),"") -> GDP$EXP Index | C9: =IFERROR(IF(0=LEN(ReferenceData!$C$9),"",ReferenceData!$C$9),"") -> PR005 | D9: =IFERROR(IF(0=LEN(ReferenceData!$D$9),"",ReferenceData!$D$9),"") -> PX_LAST | E9: =IFERROR(IF(0=LEN(ReferenceData!$E$9),"",ReferenceData!$E$9),"") -> Dynamic | F9: =IFERROR(IF(0=LEN(ReferenceData!$F$9),"",ReferenceData!$F$9),"") -> 3241.946 | G9: =IFERROR(IF(0=LEN(ReferenceData!$G$9),"",ReferenceData!$G$9),"") -> 3266.413 | H9: =IFERROR(IF(0=LEN(ReferenceData!$H$9),"",ReferenceData!$H$9),"") -> 3220.929 | I9: =IFERROR(IF(0=LEN(ReferenceData!$I$9),"",ReferenceData!$I$9),"") -> 3220.292 | J9: =IFERROR(IF(0=LEN(ReferenceData!$J$9),"",ReferenceData!$J$9),"") -> 3154.321 | K9: =IFERROR(IF(0=LEN(ReferenceData!$K$9),"",ReferenceData!$K$9),"") -> 3125.421 | L9: =IFERROR(IF(0=LEN(ReferenceData!$L$9),"",ReferenceData!$L$9),"") -> 3091.748 | M9: =IFERROR(IF(0=LEN(ReferenceData!$M$9),"",ReferenceData!$M$9),"") -> 3062.041 | N9: =IFERROR(IF(0=LEN(ReferenceData!$N$9),"",ReferenceData!$N$9),"") -> 2995.524 | O9: =IFERROR(IF(0=LEN(ReferenceData!$O$9),"",ReferenceData!$O$9),"") -> 3060.562 | P9: =IFERROR(IF(0=LEN(ReferenceData!$P$9),"",ReferenceData!$P$9),"") -> 3046.718 | Q9: =IFERROR(IF(0=LEN(ReferenceData!$Q$9),"",ReferenceData!$Q$9),"") -> 3102.55 | R9: =IFERROR(IF(0=LEN(ReferenceData!$R$9),"",ReferenceData!$R$9),"") -> 3071.551 | S9: =IFERROR(IF(0=LEN(ReferenceData!$S$9),"",ReferenceData!$S$9),"") -> 2848.698 | T9: =IFERROR(IF(0=LEN(ReferenceData!$T$9),"",ReferenceData!$T$9),"") -> 2765.36 | U9: =IFERROR(IF(0=LEN(ReferenceData!$U$9),"",ReferenceData!$U$9),"") -> 2570.103 | V9: =IFERROR(IF(0=LEN(ReferenceData!$V$9),"",ReferenceData!$V$9),"") -> 2505.032 | W9: =IFERROR(IF(0=LEN(ReferenceData!$W$9),"",ReferenceData!$W$9),"") -> 2381.224 | X9: =IFERROR(IF(0=LEN(ReferenceData!$X$9),"",ReferenceData!$X$9),"") -> 2268.891 | Y9: =IFERROR(IF(0=LEN(ReferenceData!$Y$9),"",ReferenceData!$Y$9),"") -> 2105.083 | Z9: =IFERROR(IF(0=LEN(ReferenceData!$Z$9),"",ReferenceData!$Z$9),"") -> 1814.401 | AA9: =IFERROR(IF(0=LEN(ReferenceData!$AA$9),"",ReferenceData!$AA$9),"") -> 2416.181 | AB9: =IFERROR(IF(0=LEN(ReferenceData!$AB$9),"",ReferenceData!$AB$9),"") -> 2537.466 | AC9: =IFERROR(IF(0=LEN(ReferenceData!$AC$9),"",ReferenceData!$AC$9),"") -> 2532.405 | AD9: =IFERROR(IF(0=LEN(ReferenceData!$AD$9),"",ReferenceData!$AD$9),"") -> 2547.448 | AE9: =IFERROR(IF(0=LEN(ReferenceData!$AE$9),"",ReferenceData!$AE$9),"") -> 2540.244 | AF9: =IFERROR(IF(0=LEN(ReferenceData!$AF$9),"",ReferenceData!$AF$9),"") -> 2537.415 | AG9: =IFERROR(IF(0=LEN(ReferenceData!$AG$9),"",ReferenceData!$AG$9),"") -> 2535.501 | AH9: =IFERROR(IF(0=LEN(ReferenceData!$AH$9),"",ReferenceData!$AH$9),"") -> 2562.172 | AI9: =IFERROR(IF(0=LEN(ReferenceData!$AI$9),"",ReferenceData!$AI$9),"") -> 2517.268 | AJ9: =IFERROR(IF(0=LEN(ReferenceData!$AJ$9),"",ReferenceData!$AJ$9),"") -> 2479.107 | AK9: =IFERROR(IF(0=LEN(ReferenceData!$AK$9),"",ReferenceData!$AK$9),"") -> 2384.524 | AL9: =IFERROR(IF(0=LEN(ReferenceData!$AL$9),"",ReferenceData!$AL$9),"") -> 2349.681 | AM9: =IFERROR(IF(0=LEN(ReferenceData!$AM$9),"",ReferenceData!$AM$9),"") -> 2339.728 | AN9: =IFERROR(IF(0=LEN(ReferenceData!$AN$9),"",ReferenceData!$AN$9),"") -> 2268.339 | AO9: =IFERROR(IF(0=LEN(ReferenceData!$AO$9),"",ReferenceData!$AO$9),"") -> 2270 | AP9: =IFERROR(IF(0=LEN(ReferenceData!$AP$9),"",ReferenceData!$AP$9),"") -> 2221.936 | AQ9: =IFERROR(IF(0=LEN(ReferenceData!$AQ$9),"",ReferenceData!$AQ$9),"") -> 2181.957 | AR9: =IFERROR(IF(0=LEN(ReferenceData!$AR$9),"",ReferenceData!$AR$9),"") -> 2222.279 | AS9: =IFERROR(IF(0=LEN(ReferenceData!$AS$9),"",ReferenceData!$AS$9),"") -> 2260.724 | AT9: =IFERROR(IF(0=LEN(ReferenceData!$AT$9),"",ReferenceData!$AT$9),"") -> 2300.441 | AU9: =IFERROR(IF(0=LEN(ReferenceData!$AU$9),"",ReferenceData!$AU$9),"") -> 2299.045 | AV9: =IFERROR(IF(0=LEN(ReferenceData!$AV$9),"",ReferenceData!$AV$9),"") -> 2376.218 | AW9: =IFERROR(IF(0=LEN(ReferenceData!$AW$9),"",ReferenceData!$AW$9),"") -> 2399.191 | AX9: =IFERROR(IF(0=LEN(ReferenceData!$AX$9),"",ReferenceData!$AX$9),"") -> 2395.168 | AY9: =IFERROR(IF(0=LEN(ReferenceData!$AY$9),"",ReferenceData!$AY$9),"") -> 2343.602 | AZ9: =IFERROR(IF(0=LEN(ReferenceData!$AZ$9),"",ReferenceData!$AZ$9),"") -> 2349.24 | BA9: =IFERROR(IF(0=LEN(ReferenceData!$BA$9),"",ReferenceData!$BA$9),"") -> 2285.116 | BB9: =IFERROR(IF(0=LEN(ReferenceData!$BB$9),"",ReferenceData!$BB$9),"") -> 2261.403 | BC9: =IFERROR(IF(0=LEN(ReferenceData!$BC$9),"",ReferenceData!$BC$9),"") -> 2255.929 | BD9: =IFERROR(IF(0=LEN(ReferenceData!$BD$9),"",ReferenceData!$BD$9),"") -> 2237.498 | BE9: =IFERROR(IF(0=LEN(ReferenceData!$BE$9),"",ReferenceData!$BE$9),"") -> 2227.734 | BF9: =IFERROR(IF(0=LEN(ReferenceData!$BF$9),"",ReferenceData!$BF$9),"") -> 2215.586 | BG9: =IFERROR(IF(0=LEN(ReferenceData!$BG$9),"",ReferenceData!$BG$9),"") -> 2189.981 | BH9: =IFERROR(IF(0=LEN(ReferenceData!$BH$9),"",ReferenceData!$BH$9),"") -> 2150.123 | BI9: =IFERROR(IF(0=LEN(ReferenceData!$BI$9),"",ReferenceData!$BI$9),"") -> 2156.793 | BJ9: =IFERROR(IF(0=LEN(ReferenceData!$BJ$9),"",ReferenceData!$BJ$9),"") -> 2116.132 | BK9: =IFERROR(IF(0=LEN(ReferenceData!$BK$9),"",ReferenceData!$BK$9),"") -> 2040.407 | BL9: =IFERROR(IF(0=LEN(ReferenceData!$BL$9),"",ReferenceData!$BL$9),"") -> 1972.116 | BM9: =IFERROR(IF(0=LEN(ReferenceData!$BM$9),"",ReferenceData!$BM$9),"") -> 1877.253
A10: =IFERROR(IF(0=LEN(ReferenceData!$A$10),"",ReferenceData!$A$10),"") -> Imports | B10: =IFERROR(IF(0=LEN(ReferenceData!$B$10),"",ReferenceData!$B$10),"") -> GDP$IMP Index | C10: =IFERROR(IF(0=LEN(ReferenceData!$C$10),"",ReferenceData!$C$10),"") -> PR005 | D10: =IFERROR(IF(0=LEN(ReferenceData!$D$10),"",ReferenceData!$D$10),"") -> PX_LAST | E10: =IFERROR(IF(0=LEN(ReferenceData!$E$10),"",ReferenceData!$E$10),"") -> Dynamic | F10: =IFERROR(IF(0=LEN(ReferenceData!$F$10),"",ReferenceData!$F$10),"") -> 4114.33 | G10: =IFERROR(IF(0=LEN(ReferenceData!$G$10),"",ReferenceData!$G$10),"") -> 4511.554 | H10: =IFERROR(IF(0=LEN(ReferenceData!$H$10),"",ReferenceData!$H$10),"") -> 4141.013 | I10: =IFERROR(IF(0=LEN(ReferenceData!$I$10),"",ReferenceData!$I$10),"") -> 4163.975 | J10: =IFERROR(IF(0=LEN(ReferenceData!$J$10),"",ReferenceData!$J$10),"") -> 4061.192 | K10: =IFERROR(IF(0=LEN(ReferenceData!$K$10),"",ReferenceData!$K$10),"") -> 3966.989 | L10: =IFERROR(IF(0=LEN(ReferenceData!$L$10),"",ReferenceData!$L$10),"") -> 3882.899 | M10: =IFERROR(IF(0=LEN(ReferenceData!$M$10),"",ReferenceData!$M$10),"") -> 3843.132 | N10: =IFERROR(IF(0=LEN(ReferenceData!$N$10),"",ReferenceData!$N$10),"") -> 3799.003 | O10: =IFERROR(IF(0=LEN(ReferenceData!$O$10),"",ReferenceData!$O$10),"") -> 3874.21 | P10: =IFERROR(IF(0=LEN(ReferenceData!$P$10),"",ReferenceData!$P$10),"") -> 3897.402 | Q10: =IFERROR(IF(0=LEN(ReferenceData!$Q$10),"",ReferenceData!$Q$10),"") -> 3988.447 | R10: =IFERROR(IF(0=LEN(ReferenceData!$R$10),"",ReferenceData!$R$10),"") -> 4093.663 | S10: =IFERROR(IF(0=LEN(ReferenceData!$S$10),"",ReferenceData!$S$10),"") -> 3925.742 | T10: =IFERROR(IF(0=LEN(ReferenceData!$T$10),"",ReferenceData!$T$10),"") -> 3685.956 | U10: =IFERROR(IF(0=LEN(ReferenceData!$U$10),"",ReferenceData!$U$10),"") -> 3458.783 | V10: =IFERROR(IF(0=LEN(ReferenceData!$V$10),"",ReferenceData!$V$10),"") -> 3340.114 | W10: =IFERROR(IF(0=LEN(ReferenceData!$W$10),"",ReferenceData!$W$10),"") -> 3176.982 | X10: =IFERROR(IF(0=LEN(ReferenceData!$X$10),"",ReferenceData!$X$10),"") -> 3027.199 | Y10: =IFERROR(IF(0=LEN(ReferenceData!$Y$10),"",ReferenceData!$Y$10),"") -> 2801.482 | Z10: =IFERROR(IF(0=LEN(ReferenceData!$Z$10),"",ReferenceData!$Z$10),"") -> 2350.926 | AA10: =IFERROR(IF(0=LEN(ReferenceData!$AA$10),"",ReferenceData!$AA$10),"") -> 2929.759 | AB10: =IFERROR(IF(0=LEN(ReferenceData!$AB$10),"",ReferenceData!$AB$10),"") -> 3050.824 | AC10: =IFERROR(IF(0=LEN(ReferenceData!$AC$10),"",ReferenceData!$AC$10),"") -> 3117.952 | AD10: =IFERROR(IF(0=LEN(ReferenceData!$AD$10),"",ReferenceData!$AD$10),"") -> 3165.41 | AE10: =IFERROR(IF(0=LEN(ReferenceData!$AE$10),"",ReferenceData!$AE$10),"") -> 3132.539 | AF10: =IFERROR(IF(0=LEN(ReferenceData!$AF$10),"",ReferenceData!$AF$10),"") -> 3171.622 | AG10: =IFERROR(IF(0=LEN(ReferenceData!$AG$10),"",ReferenceData!$AG$10),"") -> 3153.747 | AH10: =IFERROR(IF(0=LEN(ReferenceData!$AH$10),"",ReferenceData!$AH$10),"") -> 3105.995 | AI10: =IFERROR(IF(0=LEN(ReferenceData!$AI$10),"",ReferenceData!$AI$10),"") -> 3093.299 | AJ10: =IFERROR(IF(0=LEN(ReferenceData!$AJ$10),"",ReferenceData!$AJ$10),"") -> 3034.004 | AK10: =IFERROR(IF(0=LEN(ReferenceData!$AK$10),"",ReferenceData!$AK$10),"") -> 2916.022 | AL10: =IFERROR(IF(0=LEN(ReferenceData!$AL$10),"",ReferenceData!$AL$10),"") -> 2903.18 | AM10: =IFERROR(IF(0=LEN(ReferenceData!$AM$10),"",ReferenceData!$AM$10),"") -> 2873.148 | AN10: =IFERROR(IF(0=LEN(ReferenceData!$AN$10),"",ReferenceData!$AN$10),"") -> 2799.145 | AO10: =IFERROR(IF(0=LEN(ReferenceData!$AO$10),"",ReferenceData!$AO$10),"") -> 2751.229 | AP10: =IFERROR(IF(0=LEN(ReferenceData!$AP$10),"",ReferenceData!$AP$10),"") -> 2711.306 | AQ10: =IFERROR(IF(0=LEN(ReferenceData!$AQ$10),"",ReferenceData!$AQ$10),"") -> 2693.639 | AR10: =IFERROR(IF(0=LEN(ReferenceData!$AR$10),"",ReferenceData!$AR$10),"") -> 2745.517 | AS10: =IFERROR(IF(0=LEN(ReferenceData!$AS$10),"",ReferenceData!$AS$10),"") -> 2798.806 | AT10: =IFERROR(IF(0=LEN(ReferenceData!$AT$10),"",ReferenceData!$AT$10),"") -> 2809.968 | AU10: =IFERROR(IF(0=LEN(ReferenceData!$AU$10),"",ReferenceData!$AU$10),"") -> 2825.476 | AV10: =IFERROR(IF(0=LEN(ReferenceData!$AV$10),"",ReferenceData!$AV$10),"") -> 2906.969 | AW10: =IFERROR(IF(0=LEN(ReferenceData!$AW$10),"",ReferenceData!$AW$10),"") -> 2888.549 | AX10: =IFERROR(IF(0=LEN(ReferenceData!$AX$10),"",ReferenceData!$AX$10),"") -> 2900.572 | AY10: =IFERROR(IF(0=LEN(ReferenceData!$AY$10),"",ReferenceData!$AY$10),"") -> 2853.69 | AZ10: =IFERROR(IF(0=LEN(ReferenceData!$AZ$10),"",ReferenceData!$AZ$10),"") -> 2783.259 | BA10: =IFERROR(IF(0=LEN(ReferenceData!$BA$10),"",ReferenceData!$BA$10),"") -> 2767.183 | BB10: =IFERROR(IF(0=LEN(ReferenceData!$BB$10),"",ReferenceData!$BB$10),"") -> 2759.783 | BC10: =IFERROR(IF(0=LEN(ReferenceData!$BC$10),"",ReferenceData!$BC$10),"") -> 2755.277 | BD10: =IFERROR(IF(0=LEN(ReferenceData!$BD$10),"",ReferenceData!$BD$10),"") -> 2753.373 | BE10: =IFERROR(IF(0=LEN(ReferenceData!$BE$10),"",ReferenceData!$BE$10),"") -> 2750.817 | BF10: =IFERROR(IF(0=LEN(ReferenceData!$BF$10),"",ReferenceData!$BF$10),"") -> 2780.827 | BG10: =IFERROR(IF(0=LEN(ReferenceData!$BG$10),"",ReferenceData!$BG$10),"") -> 2792.253 | BH10: =IFERROR(IF(0=LEN(ReferenceData!$BH$10),"",ReferenceData!$BH$10),"") -> 2751.911 | BI10: =IFERROR(IF(0=LEN(ReferenceData!$BI$10),"",ReferenceData!$BI$10),"") -> 2723.903 | BJ10: =IFERROR(IF(0=LEN(ReferenceData!$BJ$10),"",ReferenceData!$BJ$10),"") -> 2697.224 | BK10: =IFERROR(IF(0=LEN(ReferenceData!$BK$10),"",ReferenceData!$BK$10),"") -> 2608.884 | BL10: =IFERROR(IF(0=LEN(ReferenceData!$BL$10),"",ReferenceData!$BL$10),"") -> 2495.702 | BM10: =IFERROR(IF(0=LEN(ReferenceData!$BM$10),"",ReferenceData!$BM$10),"") -> 2431.195
A11: =IFERROR(IF(0=LEN(ReferenceData!$A$11),"",ReferenceData!$A$11),"") -> Western Europe (Bil.) - Euro Area (EUR) | B11: =IFERROR(IF(0=LEN(ReferenceData!$B$11),"",ReferenceData!$B$11),"") -> EUGDEMU Index | C11: =IFERROR(IF(0=LEN(ReferenceData!$C$11),"",ReferenceData!$C$11),"") | D11: =IFERROR(IF(0=LEN(ReferenceData!$D$11),"",ReferenceData!$D$11),"") | E11: =IFERROR(IF(0=LEN(ReferenceData!$E$11),"",ReferenceData!$E$11),"") -> Expression | F11: =IFERROR(IF(0=LEN(ReferenceData!$F$11),"",ReferenceData!$F$11),"") | G11: =IFERROR(IF(0=LEN(ReferenceData!$G$11),"",ReferenceData!$G$11),"") -> 3885.9885 | H11: =IFERROR(IF(0=LEN(ReferenceData!$H$11),"",ReferenceData!$H$11),"") -> 3852.702 | I11: =IFERROR(IF(0=LEN(ReferenceData!$I$11),"",ReferenceData!$I$11),"") -> 3807.5193 | J11: =IFERROR(IF(0=LEN(ReferenceData!$J$11),"",ReferenceData!$J$11),"") -> 3772.4073 | K11: =IFERROR(IF(0=LEN(ReferenceData!$K$11),"",ReferenceData!$K$11),"") -> 3743.2065 | L11: =IFERROR(IF(0=LEN(ReferenceData!$L$11),"",ReferenceData!$L$11),"") -> 3708.097 | M11: =IFERROR(IF(0=LEN(ReferenceData!$M$11),"",ReferenceData!$M$11),"") -> 3667.9545 | N11: =IFERROR(IF(0=LEN(ReferenceData!$N$11),"",ReferenceData!$N$11),"") -> 3640.3645 | O11: =IFERROR(IF(0=LEN(ReferenceData!$O$11),"",ReferenceData!$O$11),"") -> 3592.8278 | P11: =IFERROR(IF(0=LEN(ReferenceData!$P$11),"",ReferenceData!$P$11),"") -> 3527.2652 | Q11: =IFERROR(IF(0=LEN(ReferenceData!$Q$11),"",ReferenceData!$Q$11),"") -> 3460.664 | R11: =IFERROR(IF(0=LEN(ReferenceData!$R$11),"",ReferenceData!$R$11),"") -> 3399.6503 | S11: =IFERROR(IF(0=LEN(ReferenceData!$S$11),"",ReferenceData!$S$11),"") -> 3326.8777 | T11: =IFERROR(IF(0=LEN(ReferenceData!$T$11),"",ReferenceData!$T$11),"") -> 3263.3072 | U11: =IFERROR(IF(0=LEN(ReferenceData!$U$11),"",ReferenceData!$U$11),"") -> 3199.6137 | V11: =IFERROR(IF(0=LEN(ReferenceData!$V$11),"",ReferenceData!$V$11),"") -> 3105.8169 | W11: =IFERROR(IF(0=LEN(ReferenceData!$W$11),"",ReferenceData!$W$11),"") -> 3028.6187 | X11: =IFERROR(IF(0=LEN(ReferenceData!$X$11),"",ReferenceData!$X$11),"") -> 2992.5549 | Y11: =IFERROR(IF(0=LEN(ReferenceData!$Y$11),"",ReferenceData!$Y$11),"") -> 2958.6418 | Z11: =IFERROR(IF(0=LEN(ReferenceData!$Z$11),"",ReferenceData!$Z$11),"") -> 2678.0275 | AA11: =IFERROR(IF(0=LEN(ReferenceData!$AA$11),"",ReferenceData!$AA$11),"") -> 2976.8248 | AB11: =IFERROR(IF(0=LEN(ReferenceData!$AB$11),"",ReferenceData!$AB$11),"") -> 3065.2432 | AC11: =IFERROR(IF(0=LEN(ReferenceData!$AC$11),"",ReferenceData!$AC$11),"") -> 3048.1265 | AD11: =IFERROR(IF(0=LEN(ReferenceData!$AD$11),"",ReferenceData!$AD$11),"") -> 3027.6762 | AE11: =IFERROR(IF(0=LEN(ReferenceData!$AE$11),"",ReferenceData!$AE$11),"") -> 3006.5916 | AF11: =IFERROR(IF(0=LEN(ReferenceData!$AF$11),"",ReferenceData!$AF$11),"") -> 2975.5678 | AG11: =IFERROR(IF(0=LEN(ReferenceData!$AG$11),"",ReferenceData!$AG$11),"") -> 2943.8759 | AH11: =IFERROR(IF(0=LEN(ReferenceData!$AH$11),"",ReferenceData!$AH$11),"") -> 2926.8874 | AI11: =IFERROR(IF(0=LEN(ReferenceData!$AI$11),"",ReferenceData!$AI$11),"") -> 2904.8177 | AJ11: =IFERROR(IF(0=LEN(ReferenceData!$AJ$11),"",ReferenceData!$AJ$11),"") -> 2889.9533 | AK11: =IFERROR(IF(0=LEN(ReferenceData!$AK$11),"",ReferenceData!$AK$11),"") -> 2856.9899 | AL11: =IFERROR(IF(0=LEN(ReferenceData!$AL$11),"",ReferenceData!$AL$11),"") -> 2830.3412 | AM11: =IFERROR(IF(0=LEN(ReferenceData!$AM$11),"",ReferenceData!$AM$11),"") -> 2798.8087 | AN11: =IFERROR(IF(0=LEN(ReferenceData!$AN$11),"",ReferenceData!$AN$11),"") -> 2766.2286 | AO11: =IFERROR(IF(0=LEN(ReferenceData!$AO$11),"",ReferenceData!$AO$11),"") -> 2743.7322 | AP11: =IFERROR(IF(0=LEN(ReferenceData!$AP$11),"",ReferenceData!$AP$11),"") -> 2723.8741 | AQ11: =IFERROR(IF(0=LEN(ReferenceData!$AQ$11),"",ReferenceData!$AQ$11),"") -> 2713.3994 | AR11: =IFERROR(IF(0=LEN(ReferenceData!$AR$11),"",ReferenceData!$AR$11),"") -> 2693.0786 | AS11: =IFERROR(IF(0=LEN(ReferenceData!$AS$11),"",ReferenceData!$AS$11),"") -> 2676.4627 | AT11: =IFERROR(IF(0=LEN(ReferenceData!$AT$11),"",ReferenceData!$AT$11),"") -> 2656.2975 | AU11: =IFERROR(IF(0=LEN(ReferenceData!$AU$11),"",ReferenceData!$AU$11),"") -> 2633.1903 | AV11: =IFERROR(IF(0=LEN(ReferenceData!$AV$11),"",ReferenceData!$AV$11),"") -> 2601.3535 | AW11: =IFERROR(IF(0=LEN(ReferenceData!$AW$11),"",ReferenceData!$AW$11),"") -> 2583.9663 | AX11: =IFERROR(IF(0=LEN(ReferenceData!$AX$11),"",ReferenceData!$AX$11),"") -> 2567.4388 | AY11: =IFERROR(IF(0=LEN(ReferenceData!$AY$11),"",ReferenceData!$AY$11),"") -> 2555.6487 | AZ11: =IFERROR(IF(0=LEN(ReferenceData!$AZ$11),"",ReferenceData!$AZ$11),"") -> 2532.5553 | BA11: =IFERROR(IF(0=LEN(ReferenceData!$BA$11),"",ReferenceData!$BA$11),"") -> 2525.3384 | BB11: =IFERROR(IF(0=LEN(ReferenceData!$BB$11),"",ReferenceData!$BB$11),"") -> 2514.883 | BC11: =IFERROR(IF(0=LEN(ReferenceData!$BC$11),"",ReferenceData!$BC$11),"") -> 2492.6291 | BD11: =IFERROR(IF(0=LEN(ReferenceData!$BD$11),"",ReferenceData!$BD$11),"") -> 2486.918 | BE11: =IFERROR(IF(0=LEN(ReferenceData!$BE$11),"",ReferenceData!$BE$11),"") -> 2492.9426 | BF11: =IFERROR(IF(0=LEN(ReferenceData!$BF$11),"",ReferenceData!$BF$11),"") -> 2485.9026 | BG11: =IFERROR(IF(0=LEN(ReferenceData!$BG$11),"",ReferenceData!$BG$11),"") -> 2487.869 | BH11: =IFERROR(IF(0=LEN(ReferenceData!$BH$11),"",ReferenceData!$BH$11),"") -> 2484.4287 | BI11: =IFERROR(IF(0=LEN(ReferenceData!$BI$11),"",ReferenceData!$BI$11),"") -> 2485.1313 | BJ11: =IFERROR(IF(0=LEN(ReferenceData!$BJ$11),"",ReferenceData!$BJ$11),"") -> 2476.8837 | BK11: =IFERROR(IF(0=LEN(ReferenceData!$BK$11),"",ReferenceData!$BK$11),"") -> 2472.0133 | BL11: =IFERROR(IF(0=LEN(ReferenceData!$BL$11),"",ReferenceData!$BL$11),"") -> 2439.4036 | BM11: =IFERROR(IF(0=LEN(ReferenceData!$BM$11),"",ReferenceData!$BM$11),"") -> 2420.9213
A12: =IFERROR(IF(0=LEN(ReferenceData!$A$12),"",ReferenceData!$A$12),"") -> Final Consumption Expenditure | B12: =IFERROR(IF(0=LEN(ReferenceData!$B$12),"",ReferenceData!$B$12),"") -> ENFCEAS Index | C12: =IFERROR(IF(0=LEN(ReferenceData!$C$12),"",ReferenceData!$C$12),"") | D12: =IFERROR(IF(0=LEN(ReferenceData!$D$12),"",ReferenceData!$D$12),"") | E12: =IFERROR(IF(0=LEN(ReferenceData!$E$12),"",ReferenceData!$E$12),"") -> Expression | F12: =IFERROR(IF(0=LEN(ReferenceData!$F$12),"",ReferenceData!$F$12),"") | G12: =IFERROR(IF(0=LEN(ReferenceData!$G$12),"",ReferenceData!$G$12),"") -> 2888.1282 | H12: =IFERROR(IF(0=LEN(ReferenceData!$H$12),"",ReferenceData!$H$12),"") -> 2858.7927 | I12: =IFERROR(IF(0=LEN(ReferenceData!$I$12),"",ReferenceData!$I$12),"") -> 2834.7721 | J12: =IFERROR(IF(0=LEN(ReferenceData!$J$12),"",ReferenceData!$J$12),"") -> 2805.52 | K12: =IFERROR(IF(0=LEN(ReferenceData!$K$12),"",ReferenceData!$K$12),"") -> 2780.9173 | L12: =IFERROR(IF(0=LEN(ReferenceData!$L$12),"",ReferenceData!$L$12),"") -> 2752.5781 | M12: =IFERROR(IF(0=LEN(ReferenceData!$M$12),"",ReferenceData!$M$12),"") -> 2723.3114 | N12: =IFERROR(IF(0=LEN(ReferenceData!$N$12),"",ReferenceData!$N$12),"") -> 2693.8129 | O12: =IFERROR(IF(0=LEN(ReferenceData!$O$12),"",ReferenceData!$O$12),"") -> 2657.7057 | P12: =IFERROR(IF(0=LEN(ReferenceData!$P$12),"",ReferenceData!$P$12),"") -> 2620.6016 | Q12: =IFERROR(IF(0=LEN(ReferenceData!$Q$12),"",ReferenceData!$Q$12),"") -> 2576.7203 | R12: =IFERROR(IF(0=LEN(ReferenceData!$R$12),"",ReferenceData!$R$12),"") -> 2517.643 | S12: =IFERROR(IF(0=LEN(ReferenceData!$S$12),"",ReferenceData!$S$12),"") -> 2458.7145 | T12: =IFERROR(IF(0=LEN(ReferenceData!$T$12),"",ReferenceData!$T$12),"") -> 2401.025 | U12: =IFERROR(IF(0=LEN(ReferenceData!$U$12),"",ReferenceData!$U$12),"") -> 2360.2405 | V12: =IFERROR(IF(0=LEN(ReferenceData!$V$12),"",ReferenceData!$V$12),"") -> 2277.7042 | W12: =IFERROR(IF(0=LEN(ReferenceData!$W$12),"",ReferenceData!$W$12),"") -> 2196.5321 | X12: =IFERROR(IF(0=LEN(ReferenceData!$X$12),"",ReferenceData!$X$12),"") -> 2192.7202 | Y12: =IFERROR(IF(0=LEN(ReferenceData!$Y$12),"",ReferenceData!$Y$12),"") -> 2221.9214 | Z12: =IFERROR(IF(0=LEN(ReferenceData!$Z$12),"",ReferenceData!$Z$12),"") -> 2019.9591 | AA12: =IFERROR(IF(0=LEN(ReferenceData!$AA$12),"",ReferenceData!$AA$12),"") -> 2204.7461 | AB12: =IFERROR(IF(0=LEN(ReferenceData!$AB$12),"",ReferenceData!$AB$12),"") -> 2273.1355 | AC12: =IFERROR(IF(0=LEN(ReferenceData!$AC$12),"",ReferenceData!$AC$12),"") -> 2262.406 | AD12: =IFERROR(IF(0=LEN(ReferenceData!$AD$12),"",ReferenceData!$AD$12),"") -> 2243.8448 | AE12: =IFERROR(IF(0=LEN(ReferenceData!$AE$12),"",ReferenceData!$AE$12),"") -> 2223.8868 | AF12: =IFERROR(IF(0=LEN(ReferenceData!$AF$12),"",ReferenceData!$AF$12),"") -> 2211.9023 | AG12: =IFERROR(IF(0=LEN(ReferenceData!$AG$12),"",ReferenceData!$AG$12),"") -> 2192.1088 | AH12: =IFERROR(IF(0=LEN(ReferenceData!$AH$12),"",ReferenceData!$AH$12),"") -> 2179.0635 | AI12: =IFERROR(IF(0=LEN(ReferenceData!$AI$12),"",ReferenceData!$AI$12),"") -> 2162.9735 | AJ12: =IFERROR(IF(0=LEN(ReferenceData!$AJ$12),"",ReferenceData!$AJ$12),"") -> 2146.671 | AK12: =IFERROR(IF(0=LEN(ReferenceData!$AK$12),"",ReferenceData!$AK$12),"") -> 2127.6025 | AL12: =IFERROR(IF(0=LEN(ReferenceData!$AL$12),"",ReferenceData!$AL$12),"") -> 2115.5038 | AM12: =IFERROR(IF(0=LEN(ReferenceData!$AM$12),"",ReferenceData!$AM$12),"") -> 2097.6108 | AN12: =IFERROR(IF(0=LEN(ReferenceData!$AN$12),"",ReferenceData!$AN$12),"") -> 2079.8827 | AO12: =IFERROR(IF(0=LEN(ReferenceData!$AO$12),"",ReferenceData!$AO$12),"") -> 2060.1064 | AP12: =IFERROR(IF(0=LEN(ReferenceData!$AP$12),"",ReferenceData!$AP$12),"") -> 2046.0933 | AQ12: =IFERROR(IF(0=LEN(ReferenceData!$AQ$12),"",ReferenceData!$AQ$12),"") -> 2035.5053 | AR12: =IFERROR(IF(0=LEN(ReferenceData!$AR$12),"",ReferenceData!$AR$12),"") -> 2024.6596 | AS12: =IFERROR(IF(0=LEN(ReferenceData!$AS$12),"",ReferenceData!$AS$12),"") -> 2014.993 | AT12: =IFERROR(IF(0=LEN(ReferenceData!$AT$12),"",ReferenceData!$AT$12),"") -> 2006.2547 | AU12: =IFERROR(IF(0=LEN(ReferenceData!$AU$12),"",ReferenceData!$AU$12),"") -> 1986.5366 | AV12: =IFERROR(IF(0=LEN(ReferenceData!$AV$12),"",ReferenceData!$AV$12),"") -> 1981.4085 | AW12: =IFERROR(IF(0=LEN(ReferenceData!$AW$12),"",ReferenceData!$AW$12),"") -> 1969.5667 | AX12: =IFERROR(IF(0=LEN(ReferenceData!$AX$12),"",ReferenceData!$AX$12),"") -> 1959.3503 | AY12: =IFERROR(IF(0=LEN(ReferenceData!$AY$12),"",ReferenceData!$AY$12),"") -> 1952.1088 | AZ12: =IFERROR(IF(0=LEN(ReferenceData!$AZ$12),"",ReferenceData!$AZ$12),"") -> 1946.3309 | BA12: =IFERROR(IF(0=LEN(ReferenceData!$BA$12),"",ReferenceData!$BA$12),"") -> 1941.221 | BB12: =IFERROR(IF(0=LEN(ReferenceData!$BB$12),"",ReferenceData!$BB$12),"") -> 1931.8702 | BC12: =IFERROR(IF(0=LEN(ReferenceData!$BC$12),"",ReferenceData!$BC$12),"") -> 1924.6826 | BD12: =IFERROR(IF(0=LEN(ReferenceData!$BD$12),"",ReferenceData!$BD$12),"") -> 1920.0997 | BE12: =IFERROR(IF(0=LEN(ReferenceData!$BE$12),"",ReferenceData!$BE$12),"") -> 1922.1627 | BF12: =IFERROR(IF(0=LEN(ReferenceData!$BF$12),"",ReferenceData!$BF$12),"") -> 1919.8425 | BG12: =IFERROR(IF(0=LEN(ReferenceData!$BG$12),"",ReferenceData!$BG$12),"") -> 1921.5766 | BH12: =IFERROR(IF(0=LEN(ReferenceData!$BH$12),"",ReferenceData!$BH$12),"") -> 1915.3692 | BI12: =IFERROR(IF(0=LEN(ReferenceData!$BI$12),"",ReferenceData!$BI$12),"") -> 1911.7589 | BJ12: =IFERROR(IF(0=LEN(ReferenceData!$BJ$12),"",ReferenceData!$BJ$12),"") -> 1907.5539 | BK12: =IFERROR(IF(0=LEN(ReferenceData!$BK$12),"",ReferenceData!$BK$12),"") -> 1899.2257 | BL12: =IFERROR(IF(0=LEN(ReferenceData!$BL$12),"",ReferenceData!$BL$12),"") -> 1889.6495 | BM12: =IFERROR(IF(0=LEN(ReferenceData!$BM$12),"",ReferenceData!$BM$12),"") -> 1876.8776
A13: =IFERROR(IF(0=LEN(ReferenceData!$A$13),"",ReferenceData!$A$13),"") -> Gross Fixed Capital Formation | B13: =IFERROR(IF(0=LEN(ReferenceData!$B$13),"",ReferenceData!$B$13),"") -> ENCPEAS Index | C13: =IFERROR(IF(0=LEN(ReferenceData!$C$13),"",ReferenceData!$C$13),"") | D13: =IFERROR(IF(0=LEN(ReferenceData!$D$13),"",ReferenceData!$D$13),"") | E13: =IFERROR(IF(0=LEN(ReferenceData!$E$13),"",ReferenceData!$E$13),"") -> Expression | F13: =IFERROR(IF(0=LEN(ReferenceData!$F$13),"",ReferenceData!$F$13),"") | G13: =IFERROR(IF(0=LEN(ReferenceData!$G$13),"",ReferenceData!$G$13),"") -> 836.3054 | H13: =IFERROR(IF(0=LEN(ReferenceData!$H$13),"",ReferenceData!$H$13),"") -> 828.5335 | I13: =IFERROR(IF(0=LEN(ReferenceData!$I$13),"",ReferenceData!$I$13),"") -> 813.3532 | J13: =IFERROR(IF(0=LEN(ReferenceData!$J$13),"",ReferenceData!$J$13),"") -> 780.6301 | K13: =IFERROR(IF(0=LEN(ReferenceData!$K$13),"",ReferenceData!$K$13),"") -> 789.9666 | L13: =IFERROR(IF(0=LEN(ReferenceData!$L$13),"",ReferenceData!$L$13),"") -> 815.9231 | M13: =IFERROR(IF(0=LEN(ReferenceData!$M$13),"",ReferenceData!$M$13),"") -> 806.4788 | N13: =IFERROR(IF(0=LEN(ReferenceData!$N$13),"",ReferenceData!$N$13),"") -> 817.1378 | O13: =IFERROR(IF(0=LEN(ReferenceData!$O$13),"",ReferenceData!$O$13),"") -> 820.8645 | P13: =IFERROR(IF(0=LEN(ReferenceData!$P$13),"",ReferenceData!$P$13),"") -> 819.1068 | Q13: =IFERROR(IF(0=LEN(ReferenceData!$Q$13),"",ReferenceData!$Q$13),"") -> 843.8806 | R13: =IFERROR(IF(0=LEN(ReferenceData!$R$13),"",ReferenceData!$R$13),"") -> 819.9767 | S13: =IFERROR(IF(0=LEN(ReferenceData!$S$13),"",ReferenceData!$S$13),"") -> 781.4184 | T13: =IFERROR(IF(0=LEN(ReferenceData!$T$13),"",ReferenceData!$T$13),"") -> 771.3735 | U13: =IFERROR(IF(0=LEN(ReferenceData!$U$13),"",ReferenceData!$U$13),"") -> 706.9498 | V13: =IFERROR(IF(0=LEN(ReferenceData!$V$13),"",ReferenceData!$V$13),"") -> 692.5553 | W13: =IFERROR(IF(0=LEN(ReferenceData!$W$13),"",ReferenceData!$W$13),"") -> 686.5293 | X13: =IFERROR(IF(0=LEN(ReferenceData!$X$13),"",ReferenceData!$X$13),"") -> 666.0808 | Y13: =IFERROR(IF(0=LEN(ReferenceData!$Y$13),"",ReferenceData!$Y$13),"") -> 608.8569 | Z13: =IFERROR(IF(0=LEN(ReferenceData!$Z$13),"",ReferenceData!$Z$13),"") -> 570.3004 | AA13: =IFERROR(IF(0=LEN(ReferenceData!$AA$13),"",ReferenceData!$AA$13),"") -> 705.3384 | AB13: =IFERROR(IF(0=LEN(ReferenceData!$AB$13),"",ReferenceData!$AB$13),"") -> 720.6733 | AC13: =IFERROR(IF(0=LEN(ReferenceData!$AC$13),"",ReferenceData!$AC$13),"") -> 653.7738 | AD13: =IFERROR(IF(0=LEN(ReferenceData!$AD$13),"",ReferenceData!$AD$13),"") -> 693.2723 | AE13: =IFERROR(IF(0=LEN(ReferenceData!$AE$13),"",ReferenceData!$AE$13),"") -> 650.2235 | AF13: =IFERROR(IF(0=LEN(ReferenceData!$AF$13),"",ReferenceData!$AF$13),"") -> 667.7749 | AG13: =IFERROR(IF(0=LEN(ReferenceData!$AG$13),"",ReferenceData!$AG$13),"") -> 635.6678 | AH13: =IFERROR(IF(0=LEN(ReferenceData!$AH$13),"",ReferenceData!$AH$13),"") -> 621.3755 | AI13: =IFERROR(IF(0=LEN(ReferenceData!$AI$13),"",ReferenceData!$AI$13),"") -> 609.0586 | AJ13: =IFERROR(IF(0=LEN(ReferenceData!$AJ$13),"",ReferenceData!$AJ$13),"") -> 603.208 | AK13: =IFERROR(IF(0=LEN(ReferenceData!$AK$13),"",ReferenceData!$AK$13),"") -> 591.2324 | AL13: =IFERROR(IF(0=LEN(ReferenceData!$AL$13),"",ReferenceData!$AL$13),"") -> 618.6726 | AM13: =IFERROR(IF(0=LEN(ReferenceData!$AM$13),"",ReferenceData!$AM$13),"") -> 572.9821 | AN13: =IFERROR(IF(0=LEN(ReferenceData!$AN$13),"",ReferenceData!$AN$13),"") -> 576.5579 | AO13: =IFERROR(IF(0=LEN(ReferenceData!$AO$13),"",ReferenceData!$AO$13),"") -> 559.4096 | AP13: =IFERROR(IF(0=LEN(ReferenceData!$AP$13),"",ReferenceData!$AP$13),"") -> 550.2859 | AQ13: =IFERROR(IF(0=LEN(ReferenceData!$AQ$13),"",ReferenceData!$AQ$13),"") -> 551.2994 | AR13: =IFERROR(IF(0=LEN(ReferenceData!$AR$13),"",ReferenceData!$AR$13),"") -> 549.6557 | AS13: =IFERROR(IF(0=LEN(ReferenceData!$AS$13),"",ReferenceData!$AS$13),"") -> 532.2464 | AT13: =IFERROR(IF(0=LEN(ReferenceData!$AT$13),"",ReferenceData!$AT$13),"") -> 550.1947 | AU13: =IFERROR(IF(0=LEN(ReferenceData!$AU$13),"",ReferenceData!$AU$13),"") -> 514.6238 | AV13: =IFERROR(IF(0=LEN(ReferenceData!$AV$13),"",ReferenceData!$AV$13),"") -> 508.7399 | AW13: =IFERROR(IF(0=LEN(ReferenceData!$AW$13),"",ReferenceData!$AW$13),"") -> 514.2515 | AX13: =IFERROR(IF(0=LEN(ReferenceData!$AX$13),"",ReferenceData!$AX$13),"") -> 511.056 | AY13: =IFERROR(IF(0=LEN(ReferenceData!$AY$13),"",ReferenceData!$AY$13),"") -> 509.1821 | AZ13: =IFERROR(IF(0=LEN(ReferenceData!$AZ$13),"",ReferenceData!$AZ$13),"") -> 496.0573 | BA13: =IFERROR(IF(0=LEN(ReferenceData!$BA$13),"",ReferenceData!$BA$13),"") -> 496.2414 | BB13: =IFERROR(IF(0=LEN(ReferenceData!$BB$13),"",ReferenceData!$BB$13),"") -> 489.269 | BC13: =IFERROR(IF(0=LEN(ReferenceData!$BC$13),"",ReferenceData!$BC$13),"") -> 478.2403 | BD13: =IFERROR(IF(0=LEN(ReferenceData!$BD$13),"",ReferenceData!$BD$13),"") -> 481.7896 | BE13: =IFERROR(IF(0=LEN(ReferenceData!$BE$13),"",ReferenceData!$BE$13),"") -> 488.335 | BF13: =IFERROR(IF(0=LEN(ReferenceData!$BF$13),"",ReferenceData!$BF$13),"") -> 497.2463 | BG13: =IFERROR(IF(0=LEN(ReferenceData!$BG$13),"",ReferenceData!$BG$13),"") -> 506.0857 | BH13: =IFERROR(IF(0=LEN(ReferenceData!$BH$13),"",ReferenceData!$BH$13),"") -> 516.2885 | BI13: =IFERROR(IF(0=LEN(ReferenceData!$BI$13),"",ReferenceData!$BI$13),"") -> 528.4429 | BJ13: =IFERROR(IF(0=LEN(ReferenceData!$BJ$13),"",ReferenceData!$BJ$13),"") -> 531.3475 | BK13: =IFERROR(IF(0=LEN(ReferenceData!$BK$13),"",ReferenceData!$BK$13),"") -> 539.9913 | BL13: =IFERROR(IF(0=LEN(ReferenceData!$BL$13),"",ReferenceData!$BL$13),"") -> 511.1024 | BM13: =IFERROR(IF(0=LEN(ReferenceData!$BM$13),"",ReferenceData!$BM$13),"") -> 503.6381
A14: =IFERROR(IF(0=LEN(ReferenceData!$A$14),"",ReferenceData!$A$14),"") -> Exports | B14: =IFERROR(IF(0=LEN(ReferenceData!$B$14),"",ReferenceData!$B$14),"") -> ECEXEMU Index | C14: =IFERROR(IF(0=LEN(ReferenceData!$C$14),"",ReferenceData!$C$14),"") | D14: =IFERROR(IF(0=LEN(ReferenceData!$D$14),"",ReferenceData!$D$14),"") | E14: =IFERROR(IF(0=LEN(ReferenceData!$E$14),"",ReferenceData!$E$14),"") -> Expression | F14: =IFERROR(IF(0=LEN(ReferenceData!$F$14),"",ReferenceData!$F$14),"") | G14: =IFERROR(IF(0=LEN(ReferenceData!$G$14),"",ReferenceData!$G$14),"") -> 1932.9015 | H14: =IFERROR(IF(0=LEN(ReferenceData!$H$14),"",ReferenceData!$H$14),"") -> 1890.9865 | I14: =IFERROR(IF(0=LEN(ReferenceData!$I$14),"",ReferenceData!$I$14),"") -> 1878.8099 | J14: =IFERROR(IF(0=LEN(ReferenceData!$J$14),"",ReferenceData!$J$14),"") -> 1901.4877 | K14: =IFERROR(IF(0=LEN(ReferenceData!$K$14),"",ReferenceData!$K$14),"") -> 1847.1993 | L14: =IFERROR(IF(0=LEN(ReferenceData!$L$14),"",ReferenceData!$L$14),"") -> 1841.0906 | M14: =IFERROR(IF(0=LEN(ReferenceData!$M$14),"",ReferenceData!$M$14),"") -> 1827.2147 | N14: =IFERROR(IF(0=LEN(ReferenceData!$N$14),"",ReferenceData!$N$14),"") -> 1849.8464 | O14: =IFERROR(IF(0=LEN(ReferenceData!$O$14),"",ReferenceData!$O$14),"") -> 1875.1133 | P14: =IFERROR(IF(0=LEN(ReferenceData!$P$14),"",ReferenceData!$P$14),"") -> 1918.1723 | Q14: =IFERROR(IF(0=LEN(ReferenceData!$Q$14),"",ReferenceData!$Q$14),"") -> 1912.4868 | R14: =IFERROR(IF(0=LEN(ReferenceData!$R$14),"",ReferenceData!$R$14),"") -> 1843.904 | S14: =IFERROR(IF(0=LEN(ReferenceData!$S$14),"",ReferenceData!$S$14),"") -> 1738.048 | T14: =IFERROR(IF(0=LEN(ReferenceData!$T$14),"",ReferenceData!$T$14),"") -> 1653.802 | U14: =IFERROR(IF(0=LEN(ReferenceData!$U$14),"",ReferenceData!$U$14),"") -> 1552.5554 | V14: =IFERROR(IF(0=LEN(ReferenceData!$V$14),"",ReferenceData!$V$14),"") -> 1482.0319 | W14: =IFERROR(IF(0=LEN(ReferenceData!$W$14),"",ReferenceData!$W$14),"") -> 1423.5915 | X14: =IFERROR(IF(0=LEN(ReferenceData!$X$14),"",ReferenceData!$X$14),"") -> 1376.188 | Y14: =IFERROR(IF(0=LEN(ReferenceData!$Y$14),"",ReferenceData!$Y$14),"") -> 1293.2405 | Z14: =IFERROR(IF(0=LEN(ReferenceData!$Z$14),"",ReferenceData!$Z$14),"") -> 1113.1756 | AA14: =IFERROR(IF(0=LEN(ReferenceData!$AA$14),"",ReferenceData!$AA$14),"") -> 1398.3768 | AB14: =IFERROR(IF(0=LEN(ReferenceData!$AB$14),"",ReferenceData!$AB$14),"") -> 1448.7375 | AC14: =IFERROR(IF(0=LEN(ReferenceData!$AC$14),"",ReferenceData!$AC$14),"") -> 1442.9878 | AD14: =IFERROR(IF(0=LEN(ReferenceData!$AD$14),"",ReferenceData!$AD$14),"") -> 1438.9038 | AE14: =IFERROR(IF(0=LEN(ReferenceData!$AE$14),"",ReferenceData!$AE$14),"") -> 1434.1172 | AF14: =IFERROR(IF(0=LEN(ReferenceData!$AF$14),"",ReferenceData!$AF$14),"") -> 1407.4938 | AG14: =IFERROR(IF(0=LEN(ReferenceData!$AG$14),"",ReferenceData!$AG$14),"") -> 1397.1321 | AH14: =IFERROR(IF(0=LEN(ReferenceData!$AH$14),"",ReferenceData!$AH$14),"") -> 1377.5984 | AI14: =IFERROR(IF(0=LEN(ReferenceData!$AI$14),"",ReferenceData!$AI$14),"") -> 1359.6916 | AJ14: =IFERROR(IF(0=LEN(ReferenceData!$AJ$14),"",ReferenceData!$AJ$14),"") -> 1354.1108 | AK14: =IFERROR(IF(0=LEN(ReferenceData!$AK$14),"",ReferenceData!$AK$14),"") -> 1319.7198 | AL14: =IFERROR(IF(0=LEN(ReferenceData!$AL$14),"",ReferenceData!$AL$14),"") -> 1309.0547 | AM14: =IFERROR(IF(0=LEN(ReferenceData!$AM$14),"",ReferenceData!$AM$14),"") -> 1292.6376 | AN14: =IFERROR(IF(0=LEN(ReferenceData!$AN$14),"",ReferenceData!$AN$14),"") -> 1248.5772 | AO14: =IFERROR(IF(0=LEN(ReferenceData!$AO$14),"",ReferenceData!$AO$14),"") -> 1228.7262 | AP14: =IFERROR(IF(0=LEN(ReferenceData!$AP$14),"",ReferenceData!$AP$14),"") -> 1210.7564 | AQ14: =IFERROR(IF(0=LEN(ReferenceData!$AQ$14),"",ReferenceData!$AQ$14),"") -> 1200.0133 | AR14: =IFERROR(IF(0=LEN(ReferenceData!$AR$14),"",ReferenceData!$AR$14),"") -> 1207.8134 | AS14: =IFERROR(IF(0=LEN(ReferenceData!$AS$14),"",ReferenceData!$AS$14),"") -> 1205.2655 | AT14: =IFERROR(IF(0=LEN(ReferenceData!$AT$14),"",ReferenceData!$AT$14),"") -> 1207.3925 | AU14: =IFERROR(IF(0=LEN(ReferenceData!$AU$14),"",ReferenceData!$AU$14),"") -> 1186.8432 | AV14: =IFERROR(IF(0=LEN(ReferenceData!$AV$14),"",ReferenceData!$AV$14),"") -> 1147.2353 | AW14: =IFERROR(IF(0=LEN(ReferenceData!$AW$14),"",ReferenceData!$AW$14),"") -> 1134.5811 | AX14: =IFERROR(IF(0=LEN(ReferenceData!$AX$14),"",ReferenceData!$AX$14),"") -> 1114.4957 | AY14: =IFERROR(IF(0=LEN(ReferenceData!$AY$14),"",ReferenceData!$AY$14),"") -> 1103.4947 | AZ14: =IFERROR(IF(0=LEN(ReferenceData!$AZ$14),"",ReferenceData!$AZ$14),"") -> 1096.8971 | BA14: =IFERROR(IF(0=LEN(ReferenceData!$BA$14),"",ReferenceData!$BA$14),"") -> 1088.3495 | BB14: =IFERROR(IF(0=LEN(ReferenceData!$BB$14),"",ReferenceData!$BB$14),"") -> 1080.8443 | BC14: =IFERROR(IF(0=LEN(ReferenceData!$BC$14),"",ReferenceData!$BC$14),"") -> 1074.4504 | BD14: =IFERROR(IF(0=LEN(ReferenceData!$BD$14),"",ReferenceData!$BD$14),"") -> 1071.9658 | BE14: =IFERROR(IF(0=LEN(ReferenceData!$BE$14),"",ReferenceData!$BE$14),"") -> 1076.9055 | BF14: =IFERROR(IF(0=LEN(ReferenceData!$BF$14),"",ReferenceData!$BF$14),"") -> 1060.6022 | BG14: =IFERROR(IF(0=LEN(ReferenceData!$BG$14),"",ReferenceData!$BG$14),"") -> 1051.9603 | BH14: =IFERROR(IF(0=LEN(ReferenceData!$BH$14),"",ReferenceData!$BH$14),"") -> 1029.571 | BI14: =IFERROR(IF(0=LEN(ReferenceData!$BI$14),"",ReferenceData!$BI$14),"") -> 1028.4407 | BJ14: =IFERROR(IF(0=LEN(ReferenceData!$BJ$14),"",ReferenceData!$BJ$14),"") -> 1017.8868 | BK14: =IFERROR(IF(0=LEN(ReferenceData!$BK$14),"",ReferenceData!$BK$14),"") -> 1004.5667 | BL14: =IFERROR(IF(0=LEN(ReferenceData!$BL$14),"",ReferenceData!$BL$14),"") -> 967.5614 | BM14: =IFERROR(IF(0=LEN(ReferenceData!$BM$14),"",ReferenceData!$BM$14),"") -> 943.6423
A15: =IFERROR(IF(0=LEN(ReferenceData!$A$15),"",ReferenceData!$A$15),"") -> Imports | B15: =IFERROR(IF(0=LEN(ReferenceData!$B$15),"",ReferenceData!$B$15),"") -> ECIMEMU Index | C15: =IFERROR(IF(0=LEN(ReferenceData!$C$15),"",ReferenceData!$C$15),"") | D15: =IFERROR(IF(0=LEN(ReferenceData!$D$15),"",ReferenceData!$D$15),"") | E15: =IFERROR(IF(0=LEN(ReferenceData!$E$15),"",ReferenceData!$E$15),"") -> Expression | F15: =IFERROR(IF(0=LEN(ReferenceData!$F$15),"",ReferenceData!$F$15),"") | G15: =IFERROR(IF(0=LEN(ReferenceData!$G$15),"",ReferenceData!$G$15),"") -> 1771.3466 | H15: =IFERROR(IF(0=LEN(ReferenceData!$H$15),"",ReferenceData!$H$15),"") -> 1725.6107 | I15: =IFERROR(IF(0=LEN(ReferenceData!$I$15),"",ReferenceData!$I$15),"") -> 1719.4159 | J15: =IFERROR(IF(0=LEN(ReferenceData!$J$15),"",ReferenceData!$J$15),"") -> 1715.2305 | K15: =IFERROR(IF(0=LEN(ReferenceData!$K$15),"",ReferenceData!$K$15),"") -> 1674.8768 | L15: =IFERROR(IF(0=LEN(ReferenceData!$L$15),"",ReferenceData!$L$15),"") -> 1701.4948 | M15: =IFERROR(IF(0=LEN(ReferenceData!$M$15),"",ReferenceData!$M$15),"") -> 1689.0504 | N15: =IFERROR(IF(0=LEN(ReferenceData!$N$15),"",ReferenceData!$N$15),"") -> 1720.4325 | O15: =IFERROR(IF(0=LEN(ReferenceData!$O$15),"",ReferenceData!$O$15),"") -> 1760.8557 | P15: =IFERROR(IF(0=LEN(ReferenceData!$P$15),"",ReferenceData!$P$15),"") -> 1830.6155 | Q15: =IFERROR(IF(0=LEN(ReferenceData!$Q$15),"",ReferenceData!$Q$15),"") -> 1872.4235 | R15: =IFERROR(IF(0=LEN(ReferenceData!$R$15),"",ReferenceData!$R$15),"") -> 1781.8735 | S15: =IFERROR(IF(0=LEN(ReferenceData!$S$15),"",ReferenceData!$S$15),"") -> 1651.3032 | T15: =IFERROR(IF(0=LEN(ReferenceData!$T$15),"",ReferenceData!$T$15),"") -> 1562.8933 | U15: =IFERROR(IF(0=LEN(ReferenceData!$U$15),"",ReferenceData!$U$15),"") -> 1420.1319 | V15: =IFERROR(IF(0=LEN(ReferenceData!$V$15),"",ReferenceData!$V$15),"") -> 1346.4746 | W15: =IFERROR(IF(0=LEN(ReferenceData!$W$15),"",ReferenceData!$W$15),"") -> 1278.0341 | X15: =IFERROR(IF(0=LEN(ReferenceData!$X$15),"",ReferenceData!$X$15),"") -> 1242.434 | Y15: =IFERROR(IF(0=LEN(ReferenceData!$Y$15),"",ReferenceData!$Y$15),"") -> 1165.377 | Z15: =IFERROR(IF(0=LEN(ReferenceData!$Z$15),"",ReferenceData!$Z$15),"") -> 1025.4076 | AA15: =IFERROR(IF(0=LEN(ReferenceData!$AA$15),"",ReferenceData!$AA$15),"") -> 1331.6365 | AB15: =IFERROR(IF(0=LEN(ReferenceData!$AB$15),"",ReferenceData!$AB$15),"") -> 1377.3031 | AC15: =IFERROR(IF(0=LEN(ReferenceData!$AC$15),"",ReferenceData!$AC$15),"") -> 1311.0411 | AD15: =IFERROR(IF(0=LEN(ReferenceData!$AD$15),"",ReferenceData!$AD$15),"") -> 1348.3447 | AE15: =IFERROR(IF(0=LEN(ReferenceData!$AE$15),"",ReferenceData!$AE$15),"") -> 1301.6359 | AF15: =IFERROR(IF(0=LEN(ReferenceData!$AF$15),"",ReferenceData!$AF$15),"") -> 1311.6032 | AG15: =IFERROR(IF(0=LEN(ReferenceData!$AG$15),"",ReferenceData!$AG$15),"") -> 1281.0327 | AH15: =IFERROR(IF(0=LEN(ReferenceData!$AH$15),"",ReferenceData!$AH$15),"") -> 1251.15 | AI15: =IFERROR(IF(0=LEN(ReferenceData!$AI$15),"",ReferenceData!$AI$15),"") -> 1226.906 | AJ15: =IFERROR(IF(0=LEN(ReferenceData!$AJ$15),"",ReferenceData!$AJ$15),"") -> 1214.0365 | AK15: =IFERROR(IF(0=LEN(ReferenceData!$AK$15),"",ReferenceData!$AK$15),"") -> 1181.5648 | AL15: =IFERROR(IF(0=LEN(ReferenceData!$AL$15),"",ReferenceData!$AL$15),"") -> 1212.8899 | AM15: =IFERROR(IF(0=LEN(ReferenceData!$AM$15),"",ReferenceData!$AM$15),"") -> 1164.4217 | AN15: =IFERROR(IF(0=LEN(ReferenceData!$AN$15),"",ReferenceData!$AN$15),"") -> 1138.7891 | AO15: =IFERROR(IF(0=LEN(ReferenceData!$AO$15),"",ReferenceData!$AO$15),"") -> 1104.5099 | AP15: =IFERROR(IF(0=LEN(ReferenceData!$AP$15),"",ReferenceData!$AP$15),"") -> 1083.2615 | AQ15: =IFERROR(IF(0=LEN(ReferenceData!$AQ$15),"",ReferenceData!$AQ$15),"") -> 1073.4185 | AR15: =IFERROR(IF(0=LEN(ReferenceData!$AR$15),"",ReferenceData!$AR$15),"") -> 1089.0501 | AS15: =IFERROR(IF(0=LEN(ReferenceData!$AS$15),"",ReferenceData!$AS$15),"") -> 1076.0422 | AT15: =IFERROR(IF(0=LEN(ReferenceData!$AT$15),"",ReferenceData!$AT$15),"") -> 1107.5444 | AU15: =IFERROR(IF(0=LEN(ReferenceData!$AU$15),"",ReferenceData!$AU$15),"") -> 1054.8133 | AV15: =IFERROR(IF(0=LEN(ReferenceData!$AV$15),"",ReferenceData!$AV$15),"") -> 1036.0302 | AW15: =IFERROR(IF(0=LEN(ReferenceData!$AW$15),"",ReferenceData!$AW$15),"") -> 1034.433 | AX15: =IFERROR(IF(0=LEN(ReferenceData!$AX$15),"",ReferenceData!$AX$15),"") -> 1017.4632 | AY15: =IFERROR(IF(0=LEN(ReferenceData!$AY$15),"",ReferenceData!$AY$15),"") -> 1009.1368 | AZ15: =IFERROR(IF(0=LEN(ReferenceData!$AZ$15),"",ReferenceData!$AZ$15),"") -> 1006.7301 | BA15: =IFERROR(IF(0=LEN(ReferenceData!$BA$15),"",ReferenceData!$BA$15),"") -> 1000.4735 | BB15: =IFERROR(IF(0=LEN(ReferenceData!$BB$15),"",ReferenceData!$BB$15),"") -> 987.1005 | BC15: =IFERROR(IF(0=LEN(ReferenceData!$BC$15),"",ReferenceData!$BC$15),"") -> 984.7443 | BD15: =IFERROR(IF(0=LEN(ReferenceData!$BD$15),"",ReferenceData!$BD$15),"") -> 986.9371 | BE15: =IFERROR(IF(0=LEN(ReferenceData!$BE$15),"",ReferenceData!$BE$15),"") -> 994.4606 | BF15: =IFERROR(IF(0=LEN(ReferenceData!$BF$15),"",ReferenceData!$BF$15),"") -> 991.7884 | BG15: =IFERROR(IF(0=LEN(ReferenceData!$BG$15),"",ReferenceData!$BG$15),"") -> 991.7536 | BH15: =IFERROR(IF(0=LEN(ReferenceData!$BH$15),"",ReferenceData!$BH$15),"") -> 976.8001 | BI15: =IFERROR(IF(0=LEN(ReferenceData!$BI$15),"",ReferenceData!$BI$15),"") -> 983.5111 | BJ15: =IFERROR(IF(0=LEN(ReferenceData!$BJ$15),"",ReferenceData!$BJ$15),"") -> 979.9045 | BK15: =IFERROR(IF(0=LEN(ReferenceData!$BK$15),"",ReferenceData!$BK$15),"") -> 971.7704 | BL15: =IFERROR(IF(0=LEN(ReferenceData!$BL$15),"",ReferenceData!$BL$15),"") -> 928.9097 | BM15: =IFERROR(IF(0=LEN(ReferenceData!$BM$15),"",ReferenceData!$BM$15),"") -> 903.2366

Sheet ReferenceData
A2: ="Description" -> Description | B2: ="Ticker" -> Ticker | C2: ="Field ID" -> Field ID | D2: ="Field Mnemonic" -> Field Mnemonic | E2: ="Data State" -> Data State | F2: =ReferenceData!$C$65 -> 2025 Q2 | G2: =ReferenceData!$D$65 -> 2025 Q1 | H2: =ReferenceData!$E$65 -> 2024 Q4 | I2: =ReferenceData!$F$65 -> 2024 Q3 | J2: =ReferenceData!$G$65 -> 2024 Q2 | K2: =ReferenceData!$H$65 -> 2024 Q1 | L2: =ReferenceData!$I$65 -> 2023 Q4 | M2: =ReferenceData!$J$65 -> 2023 Q3 | N2: =ReferenceData!$K$65 -> 2023 Q2 | O2: =ReferenceData!$L$65 -> 2023 Q1 | P2: =ReferenceData!$M$65 -> 2022 Q4 | Q2: =ReferenceData!$N$65 -> 2022 Q3 | R2: =ReferenceData!$O$65 -> 2022 Q2 | S2: =ReferenceData!$P$65 -> 2022 Q1 | T2: =ReferenceData!$Q$65 -> 2021 Q4 | U2: =ReferenceData!$R$65 -> 2021 Q3 | V2: =ReferenceData!$S$65 -> 2021 Q2 | W2: =ReferenceData!$T$65 -> 2021 Q1 | X2: =ReferenceData!$U$65 -> 2020 Q4 | Y2: =ReferenceData!$V$65 -> 2020 Q3 | Z2: =ReferenceData!$W$65 -> 2020 Q2 | AA2: =ReferenceData!$X$65 -> 2020 Q1 | AB2: =ReferenceData!$Y$65 -> 2019 Q4 | AC2: =ReferenceData!$Z$65 -> 2019 Q3 | AD2: =ReferenceData!$AA$65 -> 2019 Q2 | AE2: =ReferenceData!$AB$65 -> 2019 Q1 | AF2: =ReferenceData!$AC$65 -> 2018 Q4 | AG2: =ReferenceData!$AD$65 -> 2018 Q3 | AH2: =ReferenceData!$AE$65 -> 2018 Q2 | AI2: =ReferenceData!$AF$65 -> 2018 Q1 | AJ2: =ReferenceData!$AG$65 -> 2017 Q4 | AK2: =ReferenceData!$AH$65 -> 2017 Q3 | AL2: =ReferenceData!$AI$65 -> 2017 Q2 | AM2: =ReferenceData!$AJ$65 -> 2017 Q1 | AN2: =ReferenceData!$AK$65 -> 2016 Q4 | AO2: =ReferenceData!$AL$65 -> 2016 Q3 | AP2: =ReferenceData!$AM$65 -> 2016 Q2 | AQ2: =ReferenceData!$AN$65 -> 2016 Q1 | AR2: =ReferenceData!$AO$65 -> 2015 Q4 | AS2: =ReferenceData!$AP$65 -> 2015 Q3 | AT2: =ReferenceData!$AQ$65 -> 2015 Q2 | AU2: =ReferenceData!$AR$65 -> 2015 Q1 | AV2: =ReferenceData!$AS$65 -> 2014 Q4 | AW2: =ReferenceData!$AT$65 -> 2014 Q3 | AX2: =ReferenceData!$AU$65 -> 2014 Q2 | AY2: =ReferenceData!$AV$65 -> 2014 Q1 | AZ2: =ReferenceData!$AW$65 -> 2013 Q4 | BA2: =ReferenceData!$AX$65 -> 2013 Q3 | BB2: =ReferenceData!$AY$65 -> 2013 Q2 | BC2: =ReferenceData!$AZ$65 -> 2013 Q1 | BD2: =ReferenceData!$BA$65 -> 2012 Q4 | BE2: =ReferenceData!$BB$65 -> 2012 Q3 | BF2: =ReferenceData!$BC$65 -> 2012 Q2 | BG2: =ReferenceData!$BD$65 -> 2012 Q1 | BH2: =ReferenceData!$BE$65 -> 2011 Q4 | BI2: =ReferenceData!$BF$65 -> 2011 Q3 | BJ2: =ReferenceData!$BG$65 -> 2011 Q2 | BK2: =ReferenceData!$BH$65 -> 2011 Q1 | BL2: =ReferenceData!$BI$65 -> 2010 Q4 | BM2: =ReferenceData!$BJ$65 -> 2010 Q3 | BN2: =$C$65 -> 2025 Q2 | BO2: =$D$65 -> 2025 Q1 | BP2: =$E$65 -> 2024 Q4 | BQ2: =$F$65 -> 2024 Q3 | BR2: =$G$65 -> 2024 Q2 | BS2: =$H$65 -> 2024 Q1 | BT2: =$I$65 -> 2023 Q4 | BU2: =$J$65 -> 2023 Q3 | BV2: =$K$65 -> 2023 Q2 | BW2: =$L$65 -> 2023 Q1 | BX2: =$M$65 -> 2022 Q4 | BY2: =$N$65 -> 2022 Q3 | BZ2: =$O$65 -> 2022 Q2 | CA2: =$P$65 -> 2022 Q1 | CB2: =$Q$65 -> 2021 Q4 | CC2: =$R$65 -> 2021 Q3 | CD2: =$S$65 -> 2021 Q2 | CE2: =$T$65 -> 2021 Q1 | CF2: =$U$65 -> 2020 Q4 | CG2: =$V$65 -> 2020 Q3 | CH2: =$W$65 -> 2020 Q2 | CI2: =$X$65 -> 2020 Q1 | CJ2: =$Y$65 -> 2019 Q4 | CK2: =$Z$65 -> 2019 Q3 | CL2: =$AA$65 -> 2019 Q2 | CM2: =$AB$65 -> 2019 Q1 | CN2: =$AC$65 -> 2018 Q4 | CO2: =$AD$65 -> 2018 Q3 | CP2: =$AE$65 -> 2018 Q2 | CQ2: =$AF$65 -> 2018 Q1 | CR2: =$AG$65 -> 2017 Q4 | CS2: =$AH$65 -> 2017 Q3 | CT2: =$AI$65 -> 2017 Q2 | CU2: =$AJ$65 -> 2017 Q1 | CV2: =$AK$65 -> 2016 Q4 | CW2: =$AL$65 -> 2016 Q3 | CX2: =$AM$65 -> 2016 Q2 | CY2: =$AN$65 -> 2016 Q1 | CZ2: =$AO$65 -> 2015 Q4 | DA2: =$AP$65 -> 2015 Q3 | DB2: =$AQ$65 -> 2015 Q2 | DC2: =$AR$65 -> 2015 Q1 | DD2: =$AS$65 -> 2014 Q4 | DE2: =$AT$65 -> 2014 Q3 | DF2: =$AU$65 -> 2014 Q2 | DG2: =$AV$65 -> 2014 Q1 | DH2: =$AW$65 -> 2013 Q4 | DI2: =$AX$65 -> 2013 Q3 | DJ2: =$AY$65 -> 2013 Q2 | DK2: =$AZ$65 -> 2013 Q1 | DL2: =$BA$65 -> 2012 Q4 | DM2: =$BB$65 -> 2012 Q3 | DN2: =$BC$65 -> 2012 Q2 | DO2: =$BD$65 -> 2012 Q1 | DP2: =$BE$65 -> 2011 Q4 | DQ2: =$BF$65 -> 2011 Q3 | DR2: =$BG$65 -> 2011 Q2 | DS2: =$BH$65 -> 2011 Q1 | DT2: =$BI$65 -> 2010 Q4 | DU2: =$BJ$65 -> 2010 Q3
A3: ="North America (Bil.) - US (USD)" -> North America (Bil.) - US (USD) | B3: ="GDP CUR$ Index" -> GDP CUR$ Index | C3: ="PR005" -> PR005 | D3: ="PX_LAST" -> PX_LAST | E3: ="Dynamic" -> Dynamic | F3: =IF(AND(ISNUMBER($F$38),$B$31=1),$F$38,HLOOKUP(INDIRECT(ADDRESS(2,COLUMN())),OFFSET($BN$2,0,0,ROW()-1,60),ROW()-1,FALSE)) -> 30331.117 | G3: =IF(AND(ISNUMBER($G$38),$B$31=1),$G$38,HLOOKUP(INDIRECT(ADDRESS(2,COLUMN())),OFFSET($BN$2,0,0,ROW()-1,60),ROW()-1,FALSE)) -> 29962.047 | H3: =IF(AND(ISNUMBER($H$38),$B$31=1),$H$38,HLOOKUP(INDIRECT(ADDRESS(2,COLUMN())),OFFSET($BN$2,0,0,ROW()-1,60),ROW()-1,FALSE)) -> 29723.864 | I3: =IF(AND(ISNUMBER($I$38),$B$31=1),$I$38,HLOOKUP(INDIRECT(ADDRESS(2,COLUMN())),OFFSET($BN$2,0,0,ROW()-1,60),ROW()-1,FALSE)) -> 29374.914 | J3: =IF(AND(ISNUMBER($J$38),$B$31=1),$J$38,HLOOKUP(INDIRECT(ADDRESS(2,COLUMN())),OFFSET($BN$2,0,0,ROW()-1,60),ROW()-1,FALSE)) -> 29016.714 | K3: =IF(AND(ISNUMBER($K$38),$B$31=1),$K$38,HLOOKUP(INDIRECT(ADDRESS(2,COLUMN())),OFFSET($BN$2,0,0,ROW()-1,60),ROW()-1,FALSE)) -> 28624.069 | L3: =IF(AND(ISNUMBER($L$38),$B$31=1),$L$38,HLOOKUP(INDIRECT(ADDRESS(2,COLUMN())),OFFSET($BN$2,0,0,ROW()-1,60),ROW()-1,FALSE)) -> 28296.967 | M3: =IF(AND(ISNUMBER($M$38),$B$31=1),$M$38,HLOOKUP(INDIRECT(ADDRESS(2,COLUMN())),OFFSET($BN$2,0,0,ROW()-1,60),ROW()-1,FALSE)) -> 27967.697 | N3: =IF(AND(ISNUMBER($N$38),$B$31=1),$N$38,HLOOKUP(INDIRECT(ADDRESS(2,COLUMN())),OFFSET($BN$2,0,0,ROW()-1,60),ROW()-1,FALSE)) -> 27453.815 | O3: =IF(AND(ISNUMBER($O$38),$B$31=1),$O$38,HLOOKUP(INDIRECT(ADDRESS(2,COLUMN())),OFFSET($BN$2,0,0,ROW()-1,60),ROW()-1,FALSE)) -> 27164.359 | P3: =IF(AND(ISNUMBER($P$38),$B$31=1),$P$38,HLOOKUP(INDIRECT(ADDRESS(2,COLUMN())),OFFSET($BN$2,0,0,ROW()-1,60),ROW()-1,FALSE)) -> 26734.277 | Q3: =IF(AND(ISNUMBER($Q$38),$B$31=1),$Q$38,HLOOKUP(INDIRECT(ADDRESS(2,COLUMN())),OFFSET($BN$2,0,0,ROW()-1,60),ROW()-1,FALSE)) -> 26272.011 | R3: =IF(AND(ISNUMBER($R$38),$B$31=1),$R$38,HLOOKUP(INDIRECT(ADDRESS(2,COLUMN())),OFFSET($BN$2,0,0,ROW()-1,60),ROW()-1,FALSE)) -> 25805.791 | S3: =IF(AND(ISNUMBER($S$38),$B$31=1),$S$38,HLOOKUP(INDIRECT(ADDRESS(2,COLUMN())),OFFSET($BN$2,0,0,ROW()-1,60),ROW()-1,FALSE)) -> 25215.491 | T3: =IF(AND(ISNUMBER($T$38),$B$31=1),$T$38,HLOOKUP(INDIRECT(ADDRESS(2,COLUMN())),OFFSET($BN$2,0,0,ROW()-1,60),ROW()-1,FALSE)) -> 24777.038 | U3: =IF(AND(ISNUMBER($U$38),$B$31=1),$U$38,HLOOKUP(INDIRECT(ADDRESS(2,COLUMN())),OFFSET($BN$2,0,0,ROW()-1,60),ROW()-1,FALSE)) -> 23921.991 | V3: =IF(AND(ISNUMBER($V$38),$B$31=1),$V$38,HLOOKUP(INDIRECT(ADDRESS(2,COLUMN())),OFFSET($BN$2,0,0,ROW()-1,60),ROW()-1,FALSE)) -> 23368.861 | W3: =IF(AND(ISNUMBER($W$38),$B$31=1),$W$38,HLOOKUP(INDIRECT(ADDRESS(2,COLUMN())),OFFSET($BN$2,0,0,ROW()-1,60),ROW()-1,FALSE)) -> 22656.793 | X3: =IF(AND(ISNUMBER($X$38),$B$31=1),$X$38,HLOOKUP(INDIRECT(ADDRESS(2,COLUMN())),OFFSET($BN$2,0,0,ROW()-1,60),ROW()-1,FALSE)) -> 22068.767 | Y3: =IF(AND(ISNUMBER($Y$38),$B$31=1),$Y$38,HLOOKUP(INDIRECT(ADDRESS(2,COLUMN())),OFFSET($BN$2,0,0,ROW()-1,60),ROW()-1,FALSE)) -> 21684.551 | Z3: =IF(AND(ISNUMBER($Z$38),$B$31=1),$Z$38,HLOOKUP(INDIRECT(ADDRESS(2,COLUMN())),OFFSET($BN$2,0,0,ROW()-1,60),ROW()-1,FALSE)) -> 19935.444 | AA3: =IF(AND(ISNUMBER($AA$38),$B$31=1),$AA$38,HLOOKUP(INDIRECT(ADDRESS(2,COLUMN())),OFFSET($BN$2,0,0,ROW()-1,60),ROW()-1,FALSE)) -> 21727.657 | AB3: =IF(AND(ISNUMBER($AB$38),$B$31=1),$AB$38,HLOOKUP(INDIRECT(ADDRESS(2,COLUMN())),OFFSET($BN$2,0,0,ROW()-1,60),ROW()-1,FALSE)) -> 21933.217 | AC3: =IF(AND(ISNUMBER($AC$38),$B$31=1),$AC$38,HLOOKUP(INDIRECT(ADDRESS(2,COLUMN())),OFFSET($BN$2,0,0,ROW()-1,60),ROW()-1,FALSE)) -> 21717.171 | AD3: =IF(AND(ISNUMBER($AD$38),$B$31=1),$AD$38,HLOOKUP(INDIRECT(ADDRESS(2,COLUMN())),OFFSET($BN$2,0,0,ROW()-1,60),ROW()-1,FALSE)) -> 21397.938 | AE3: =IF(AND(ISNUMBER($AE$38),$B$31=1),$AE$38,HLOOKUP(INDIRECT(ADDRESS(2,COLUMN())),OFFSET($BN$2,0,0,ROW()-1,60),ROW()-1,FALSE)) -> 21111.6 | AF3: =IF(AND(ISNUMBER($AF$38),$B$31=1),$AF$38,HLOOKUP(INDIRECT(ADDRESS(2,COLUMN())),OFFSET($BN$2,0,0,ROW()-1,60),ROW()-1,FALSE)) -> 20917.867 | AG3: =IF(AND(ISNUMBER($AG$38),$B$31=1),$AG$38,HLOOKUP(INDIRECT(ADDRESS(2,COLUMN())),OFFSET($BN$2,0,0,ROW()-1,60),ROW()-1,FALSE)) -> 20798.73 | AH3: =IF(AND(ISNUMBER($AH$38),$B$31=1),$AH$38,HLOOKUP(INDIRECT(ADDRESS(2,COLUMN())),OFFSET($BN$2,0,0,ROW()-1,60),ROW()-1,FALSE)) -> 20580.912 | AI3: =IF(AND(ISNUMBER($AI$38),$B$31=1),$AI$38,HLOOKUP(INDIRECT(ADDRESS(2,COLUMN())),OFFSET($BN$2,0,0,ROW()-1,60),ROW()-1,FALSE)) -> 20328.553 | AJ3: =IF(AND(ISNUMBER($AJ$38),$B$31=1),$AJ$38,HLOOKUP(INDIRECT(ADDRESS(2,COLUMN())),OFFSET($BN$2,0,0,ROW()-1,60),ROW()-1,FALSE)) -> 20037.088 | AK3: =IF(AND(ISNUMBER($AK$38),$B$31=1),$AK$38,HLOOKUP(INDIRECT(ADDRESS(2,COLUMN())),OFFSET($BN$2,0,0,ROW()-1,60),ROW()-1,FALSE)) -> 19692.595 | AL3: =IF(AND(ISNUMBER($AL$38),$B$31=1),$AL$38,HLOOKUP(INDIRECT(ADDRESS(2,COLUMN())),OFFSET($BN$2,0,0,ROW()-1,60),ROW()-1,FALSE)) -> 19438.643 | AM3: =IF(AND(ISNUMBER($AM$38),$B$31=1),$AM$38,HLOOKUP(INDIRECT(ADDRESS(2,COLUMN())),OFFSET($BN$2,0,0,ROW()-1,60),ROW()-1,FALSE)) -> 19280.084 | AN3: =IF(AND(ISNUMBER($AN$38),$B$31=1),$AN$38,HLOOKUP(INDIRECT(ADDRESS(2,COLUMN())),OFFSET($BN$2,0,0,ROW()-1,60),ROW()-1,FALSE)) -> 19089.379 | AO3: =IF(AND(ISNUMBER($AO$38),$B$31=1),$AO$38,HLOOKUP(INDIRECT(ADDRESS(2,COLUMN())),OFFSET($BN$2,0,0,ROW()-1,60),ROW()-1,FALSE)) -> 18892.639 | AP3: =IF(AND(ISNUMBER($AP$38),$B$31=1),$AP$38,HLOOKUP(INDIRECT(ADDRESS(2,COLUMN())),OFFSET($BN$2,0,0,ROW()-1,60),ROW()-1,FALSE)) -> 18711.702 | AQ3: =IF(AND(ISNUMBER($AQ$38),$B$31=1),$AQ$38,HLOOKUP(INDIRECT(ADDRESS(2,COLUMN())),OFFSET($BN$2,0,0,ROW()-1,60),ROW()-1,FALSE)) -> 18525.933 | AR3: =IF(AND(ISNUMBER($AR$38),$B$31=1),$AR$38,HLOOKUP(INDIRECT(ADDRESS(2,COLUMN())),OFFSET($BN$2,0,0,ROW()-1,60),ROW()-1,FALSE)) -> 18435.137 | AS3: =IF(AND(ISNUMBER($AS$38),$B$31=1),$AS$38,HLOOKUP(INDIRECT(ADDRESS(2,COLUMN())),OFFSET($BN$2,0,0,ROW()-1,60),ROW()-1,FALSE)) -> 18401.626 | AT3: =IF(AND(ISNUMBER($AT$38),$B$31=1),$AT$38,HLOOKUP(INDIRECT(ADDRESS(2,COLUMN())),OFFSET($BN$2,0,0,ROW()-1,60),ROW()-1,FALSE)) -> 18279.784 | AU3: =IF(AND(ISNUMBER($AU$38),$B$31=1),$AU$38,HLOOKUP(INDIRECT(ADDRESS(2,COLUMN())),OFFSET($BN$2,0,0,ROW()-1,60),ROW()-1,FALSE)) -> 18063.529 | AV3: =IF(AND(ISNUMBER($AV$38),$B$31=1),$AV$38,HLOOKUP(INDIRECT(ADDRESS(2,COLUMN())),OFFSET($BN$2,0,0,ROW()-1,60),ROW()-1,FALSE)) -> 17912.079 | AW3: =IF(AND(ISNUMBER($AW$38),$B$31=1),$AW$38,HLOOKUP(INDIRECT(ADDRESS(2,COLUMN())),OFFSET($BN$2,0,0,ROW()-1,60),ROW()-1,FALSE)) -> 17804.228 | AX3: =IF(AND(ISNUMBER($AX$38),$B$31=1),$AX$38,HLOOKUP(INDIRECT(ADDRESS(2,COLUMN())),OFFSET($BN$2,0,0,ROW()-1,60),ROW()-1,FALSE)) -> 17518.508 | AY3: =IF(AND(ISNUMBER($AY$38),$B$31=1),$AY$38,HLOOKUP(INDIRECT(ADDRESS(2,COLUMN())),OFFSET($BN$2,0,0,ROW()-1,60),ROW()-1,FALSE)) -> 17197.738 | AZ3: =IF(AND(ISNUMBER($AZ$38),$B$31=1),$AZ$38,HLOOKUP(INDIRECT(ADDRESS(2,COLUMN())),OFFSET($BN$2,0,0,ROW()-1,60),ROW()-1,FALSE)) -> 17192.019 | BA3: =IF(AND(ISNUMBER($BA$38),$B$31=1),$BA$38,HLOOKUP(INDIRECT(ADDRESS(2,COLUMN())),OFFSET($BN$2,0,0,ROW()-1,60),ROW()-1,FALSE)) -> 16953.838 | BB3: =IF(AND(ISNUMBER($BB$38),$B$31=1),$BB$38,HLOOKUP(INDIRECT(ADDRESS(2,COLUMN())),OFFSET($BN$2,0,0,ROW()-1,60),ROW()-1,FALSE)) -> 16728.687 | BC3: =IF(AND(ISNUMBER($BC$38),$B$31=1),$BC$38,HLOOKUP(INDIRECT(ADDRESS(2,COLUMN())),OFFSET($BN$2,0,0,ROW()-1,60),ROW()-1,FALSE)) -> 16648.189 | BD3: =IF(AND(ISNUMBER($BD$38),$B$31=1),$BD$38,HLOOKUP(INDIRECT(ADDRESS(2,COLUMN())),OFFSET($BN$2,0,0,ROW()-1,60),ROW()-1,FALSE)) -> 16420.419 | BE3: =IF(AND(ISNUMBER($BE$38),$B$31=1),$BE$38,HLOOKUP(INDIRECT(ADDRESS(2,COLUMN())),OFFSET($BN$2,0,0,ROW()-1,60),ROW()-1,FALSE)) -> 16319.54 | BF3: =IF(AND(ISNUMBER($BF$38),$B$31=1),$BF$38,HLOOKUP(INDIRECT(ADDRESS(2,COLUMN())),OFFSET($BN$2,0,0,ROW()-1,60),ROW()-1,FALSE)) -> 16207.115 | BG3: =IF(AND(ISNUMBER($BG$38),$B$31=1),$BG$38,HLOOKUP(INDIRECT(ADDRESS(2,COLUMN())),OFFSET($BN$2,0,0,ROW()-1,60),ROW()-1,FALSE)) -> 16068.805 | BH3: =IF(AND(ISNUMBER($BH$38),$B$31=1),$BH$38,HLOOKUP(INDIRECT(ADDRESS(2,COLUMN())),OFFSET($BN$2,0,0,ROW()-1,60),ROW()-1,FALSE)) -> 15842.259 | BI3: =IF(AND(ISNUMBER($BI$38),$B$31=1),$BI$38,HLOOKUP(INDIRECT(ADDRESS(2,COLUMN())),OFFSET($BN$2,0,0,ROW()-1,60),ROW()-1,FALSE)) -> 15647.681 | BJ3: =IF(AND(ISNUMBER($BJ$38),$B$31=1),$BJ$38,HLOOKUP(INDIRECT(ADDRESS(2,COLUMN())),OFFSET($BN$2,0,0,ROW()-1,60),ROW()-1,FALSE)) -> 15557.539 | BK3: =IF(AND(ISNUMBER($BK$38),$B$31=1),$BK$38,HLOOKUP(INDIRECT(ADDRESS(2,COLUMN())),OFFSET($BN$2,0,0,ROW()-1,60),ROW()-1,FALSE)) -> 15351.448 | BL3: =IF(AND(ISNUMBER($BL$38),$B$31=1),$BL$38,HLOOKUP(INDIRECT(ADDRESS(2,COLUMN())),OFFSET($BN$2,0,0,ROW()-1,60),ROW()-1,FALSE)) -> 15309.474 | BM3: =IF(AND(ISNUMBER($BM$38),$B$31=1),$BM$38,HLOOKUP(INDIRECT(ADDRESS(2,COLUMN())),OFFSET($BN$2,0,0,ROW()-1,60),ROW()-1,FALSE)) -> 15141.607 | BN3: =30331.117 -> 30331.117 | BO3: =29962.047 -> 29962.047 | BP3: =29723.864 -> 29723.864 | BQ3: =29374.914 -> 29374.914 | BR3: =29016.714 -> 29016.714 | BS3: =28624.069 -> 28624.069 | BT3: =28296.967 -> 28296.967 | BU3: =27967.697 -> 27967.697 | BV3: =27453.815 -> 27453.815 | BW3: =27164.359 -> 27164.359 | BX3: =26734.277 -> 26734.277 | BY3: =26272.011 -> 26272.011 | BZ3: =25805.791 -> 25805.791 | CA3: =25215.491 -> 25215.491 | CB3: =24777.038 -> 24777.038 | CC3: =23921.991 -> 23921.991 | CD3: =23368.861 -> 23368.861 | CE3: =22656.793 -> 22656.793 | CF3: =22068.767 -> 22068.767 | CG3: =21684.551 -> 21684.551 | CH3: =19935.444 -> 19935.444 | CI3: =21727.657 -> 21727.657 | CJ3: =21933.217 -> 21933.217 | CK3: =21717.171 -> 21717.171 | CL3: =21397.938 -> 21397.938 | CM3: =21111.6 -> 21111.6 | CN3: =20917.867 -> 20917.867 | CO3: =20798.73 -> 20798.73 | CP3: =20580.912 -> 20580.912 | CQ3: =20328.553 -> 20328.553 | CR3: =20037.088 -> 20037.088 | CS3: =19692.595 -> 19692.595 | CT3: =19438.643 -> 19438.643 | CU3: =19280.084 -> 19280.084 | CV3: =19089.379 -> 19089.379 | CW3: =18892.639 -> 18892.639 | CX3: =18711.702 -> 18711.702 | CY3: =18525.933 -> 18525.933 | CZ3: =18435.137 -> 18435.137 | DA3: =18401.626 -> 18401.626 | DB3: =18279.784 -> 18279.784 | DC3: =18063.529 -> 18063.529 | DD3: =17912.079 -> 17912.079 | DE3: =17804.228 -> 17804.228 | DF3: =17518.508 -> 17518.508 | DG3: =17197.738 -> 17197.738 | DH3: =17192.019 -> 17192.019 | DI3: =16953.838 -> 16953.838 | DJ3: =16728.687 -> 16728.687 | DK3: =16648.189 -> 16648.189 | DL3: =16420.419 -> 16420.419 | DM3: =16319.54 -> 16319.54 | DN3: =16207.115 -> 16207.115 | DO3: =16068.805 -> 16068.805 | DP3: =15842.259 -> 15842.259 | DQ3: =15647.681 -> 15647.681 | DR3: =15557.539 -> 15557.539 | DS3: =15351.448 -> 15351.448 | DT3: =15309.474 -> 15309.474 | DU3: =15141.607 -> 15141.607
A4: =" Personal Consumption Expenditures" -> Personal Consumption Expenditures | B4: ="GDP$PCE Index" -> GDP$PCE Index | C4: ="PR005" -> PR005 | D4: ="PX_LAST" -> PX_LAST | E4: ="Dynamic" -> Dynamic | F4: =IF(AND(ISNUMBER($F$39),$B$31=1),$F$39,HLOOKUP(INDIRECT(ADDRESS(2,COLUMN())),OFFSET($BN$2,0,0,ROW()-1,60),ROW()-1,FALSE)) -> 20640.878 | G4: =IF(AND(ISNUMBER($G$39),$B$31=1),$G$39,HLOOKUP(INDIRECT(ADDRESS(2,COLUMN())),OFFSET($BN$2,0,0,ROW()-1,60),ROW()-1,FALSE)) -> 20461.602 | H4: =IF(AND(ISNUMBER($H$39),$B$31=1),$H$39,HLOOKUP(INDIRECT(ADDRESS(2,COLUMN())),OFFSET($BN$2,0,0,ROW()-1,60),ROW()-1,FALSE)) -> 20255.455 | I4: =IF(AND(ISNUMBER($I$39),$B$31=1),$I$39,HLOOKUP(INDIRECT(ADDRESS(2,COLUMN())),OFFSET($BN$2,0,0,ROW()-1,60),ROW()-1,FALSE)) -> 19938.425 | J4: =IF(AND(ISNUMBER($J$39),$B$31=1),$J$39,HLOOKUP(INDIRECT(ADDRESS(2,COLUMN())),OFFSET($BN$2,0,0,ROW()-1,60),ROW()-1,FALSE)) -> 19682.699 | K4: =IF(AND(ISNUMBER($K$39),$B$31=1),$K$39,HLOOKUP(INDIRECT(ADDRESS(2,COLUMN())),OFFSET($BN$2,0,0,ROW()-1,60),ROW()-1,FALSE)) -> 19424.775 | L4: =IF(AND(ISNUMBER($L$39),$B$31=1),$L$39,HLOOKUP(INDIRECT(ADDRESS(2,COLUMN())),OFFSET($BN$2,0,0,ROW()-1,60),ROW()-1,FALSE)) -> 19170.154 | M4: =IF(AND(ISNUMBER($M$39),$B$31=1),$M$39,HLOOKUP(INDIRECT(ADDRESS(2,COLUMN())),OFFSET($BN$2,0,0,ROW()-1,60),ROW()-1,FALSE)) -> 18928.987 | N4: =IF(AND(ISNUMBER($N$39),$B$31=1),$N$39,HLOOKUP(INDIRECT(ADDRESS(2,COLUMN())),OFFSET($BN$2,0,0,ROW()-1,60),ROW()-1,FALSE)) -> 18685.724 | O4: =IF(AND(ISNUMBER($O$39),$B$31=1),$O$39,HLOOKUP(INDIRECT(ADDRESS(2,COLUMN())),OFFSET($BN$2,0,0,ROW()-1,60),ROW()-1,FALSE)) -> 18506.211 | P4: =IF(AND(ISNUMBER($P$39),$B$31=1),$P$39,HLOOKUP(INDIRECT(ADDRESS(2,COLUMN())),OFFSET($BN$2,0,0,ROW()-1,60),ROW()-1,FALSE)) -> 18108.27 | Q4: =IF(AND(ISNUMBER($Q$39),$B$31=1),$Q$39,HLOOKUP(INDIRECT(ADDRESS(2,COLUMN())),OFFSET($BN$2,0,0,ROW()-1,60),ROW()-1,FALSE)) -> 17876.234 | R4: =IF(AND(ISNUMBER($R$39),$B$31=1),$R$39,HLOOKUP(INDIRECT(ADDRESS(2,COLUMN())),OFFSET($BN$2,0,0,ROW()-1,60),ROW()-1,FALSE)) -> 17603.753 | S4: =IF(AND(ISNUMBER($S$39),$B$31=1),$S$39,HLOOKUP(INDIRECT(ADDRESS(2,COLUMN())),OFFSET($BN$2,0,0,ROW()-1,60),ROW()-1,FALSE)) -> 17175.105 | T4: =IF(AND(ISNUMBER($T$39),$B$31=1),$T$39,HLOOKUP(INDIRECT(ADDRESS(2,COLUMN())),OFFSET($BN$2,0,0,ROW()-1,60),ROW()-1,FALSE)) -> 16816.132 | U4: =IF(AND(ISNUMBER($U$39),$B$31=1),$U$39,HLOOKUP(INDIRECT(ADDRESS(2,COLUMN())),OFFSET($BN$2,0,0,ROW()-1,60),ROW()-1,FALSE)) -> 16363.876 | V4: =IF(AND(ISNUMBER($V$39),$B$31=1),$V$39,HLOOKUP(INDIRECT(ADDRESS(2,COLUMN())),OFFSET($BN$2,0,0,ROW()-1,60),ROW()-1,FALSE)) -> 16016.346 | W4: =IF(AND(ISNUMBER($W$39),$B$31=1),$W$39,HLOOKUP(INDIRECT(ADDRESS(2,COLUMN())),OFFSET($BN$2,0,0,ROW()-1,60),ROW()-1,FALSE)) -> 15259.427 | X4: =IF(AND(ISNUMBER($X$39),$B$31=1),$X$39,HLOOKUP(INDIRECT(ADDRESS(2,COLUMN())),OFFSET($BN$2,0,0,ROW()-1,60),ROW()-1,FALSE)) -> 14752.732 | Y4: =IF(AND(ISNUMBER($Y$39),$B$31=1),$Y$39,HLOOKUP(INDIRECT(ADDRESS(2,COLUMN())),OFFSET($BN$2,0,0,ROW()-1,60),ROW()-1,FALSE)) -> 14478.033 | Z4: =IF(AND(ISNUMBER($Z$39),$B$31=1),$Z$39,HLOOKUP(INDIRECT(ADDRESS(2,COLUMN())),OFFSET($BN$2,0,0,ROW()-1,60),ROW()-1,FALSE)) -> 13175.637 | AA4: =IF(AND(ISNUMBER($AA$39),$B$31=1),$AA$39,HLOOKUP(INDIRECT(ADDRESS(2,COLUMN())),OFFSET($BN$2,0,0,ROW()-1,60),ROW()-1,FALSE)) -> 14496.227 | AB4: =IF(AND(ISNUMBER($AB$39),$B$31=1),$AB$39,HLOOKUP(INDIRECT(ADDRESS(2,COLUMN())),OFFSET($BN$2,0,0,ROW()-1,60),ROW()-1,FALSE)) -> 14701.038 | AC4: =IF(AND(ISNUMBER($AC$39),$B$31=1),$AC$39,HLOOKUP(INDIRECT(ADDRESS(2,COLUMN())),OFFSET($BN$2,0,0,ROW()-1,60),ROW()-1,FALSE)) -> 14548.282 | AD4: =IF(AND(ISNUMBER($AD$39),$B$31=1),$AD$39,HLOOKUP(INDIRECT(ADDRESS(2,COLUMN())),OFFSET($BN$2,0,0,ROW()-1,60),ROW()-1,FALSE)) -> 14350.662 | AE4: =IF(AND(ISNUMBER($AE$39),$B$31=1),$AE$39,HLOOKUP(INDIRECT(ADDRESS(2,COLUMN())),OFFSET($BN$2,0,0,ROW()-1,60),ROW()-1,FALSE)) -> 14150.191 | AF4: =IF(AND(ISNUMBER($AF$39),$B$31=1),$AF$39,HLOOKUP(INDIRECT(ADDRESS(2,COLUMN())),OFFSET($BN$2,0,0,ROW()-1,60),ROW()-1,FALSE)) -> 14099.199 | AG4: =IF(AND(ISNUMBER($AG$39),$B$31=1),$AG$39,HLOOKUP(INDIRECT(ADDRESS(2,COLUMN())),OFFSET($BN$2,0,0,ROW()-1,60),ROW()-1,FALSE)) -> 14002.199 | AH4: =IF(AND(ISNUMBER($AH$39),$B$31=1),$AH$39,HLOOKUP(INDIRECT(ADDRESS(2,COLUMN())),OFFSET($BN$2,0,0,ROW()-1,60),ROW()-1,FALSE)) -> 13891.294 | AI4: =IF(AND(ISNUMBER($AI$39),$B$31=1),$AI$39,HLOOKUP(INDIRECT(ADDRESS(2,COLUMN())),OFFSET($BN$2,0,0,ROW()-1,60),ROW()-1,FALSE)) -> 13745.074 | AJ4: =IF(AND(ISNUMBER($AJ$39),$B$31=1),$AJ$39,HLOOKUP(INDIRECT(ADDRESS(2,COLUMN())),OFFSET($BN$2,0,0,ROW()-1,60),ROW()-1,FALSE)) -> 13551.401 | AK4: =IF(AND(ISNUMBER($AK$39),$B$31=1),$AK$39,HLOOKUP(INDIRECT(ADDRESS(2,COLUMN())),OFFSET($BN$2,0,0,ROW()-1,60),ROW()-1,FALSE)) -> 13325.065 | AL4: =IF(AND(ISNUMBER($AL$39),$B$31=1),$AL$39,HLOOKUP(INDIRECT(ADDRESS(2,COLUMN())),OFFSET($BN$2,0,0,ROW()-1,60),ROW()-1,FALSE)) -> 13188.73 | AM4: =IF(AND(ISNUMBER($AM$39),$B$31=1),$AM$39,HLOOKUP(INDIRECT(ADDRESS(2,COLUMN())),OFFSET($BN$2,0,0,ROW()-1,60),ROW()-1,FALSE)) -> 13097.306 | AN4: =IF(AND(ISNUMBER($AN$39),$B$31=1),$AN$39,HLOOKUP(INDIRECT(ADDRESS(2,COLUMN())),OFFSET($BN$2,0,0,ROW()-1,60),ROW()-1,FALSE)) -> 12921.989 | AO4: =IF(AND(ISNUMBER($AO$39),$B$31=1),$AO$39,HLOOKUP(INDIRECT(ADDRESS(2,COLUMN())),OFFSET($BN$2,0,0,ROW()-1,60),ROW()-1,FALSE)) -> 12797.126 | AP4: =IF(AND(ISNUMBER($AP$39),$B$31=1),$AP$39,HLOOKUP(INDIRECT(ADDRESS(2,COLUMN())),OFFSET($BN$2,0,0,ROW()-1,60),ROW()-1,FALSE)) -> 12665.124 | AQ4: =IF(AND(ISNUMBER($AQ$39),$B$31=1),$AQ$39,HLOOKUP(INDIRECT(ADDRESS(2,COLUMN())),OFFSET($BN$2,0,0,ROW()-1,60),ROW()-1,FALSE)) -> 12523.156 | AR4: =IF(AND(ISNUMBER($AR$39),$B$31=1),$AR$39,HLOOKUP(INDIRECT(ADDRESS(2,COLUMN())),OFFSET($BN$2,0,0,ROW()-1,60),ROW()-1,FALSE)) -> 12423.353 | AS4: =IF(AND(ISNUMBER($AS$39),$B$31=1),$AS$39,HLOOKUP(INDIRECT(ADDRESS(2,COLUMN())),OFFSET($BN$2,0,0,ROW()-1,60),ROW()-1,FALSE)) -> 12382.494 | AT4: =IF(AND(ISNUMBER($AT$39),$B$31=1),$AT$39,HLOOKUP(INDIRECT(ADDRESS(2,COLUMN())),OFFSET($BN$2,0,0,ROW()-1,60),ROW()-1,FALSE)) -> 12264.14 | AU4: =IF(AND(ISNUMBER($AU$39),$B$31=1),$AU$39,HLOOKUP(INDIRECT(ADDRESS(2,COLUMN())),OFFSET($BN$2,0,0,ROW()-1,60),ROW()-1,FALSE)) -> 12119.763 | AV4: =IF(AND(ISNUMBER($AV$39),$B$31=1),$AV$39,HLOOKUP(INDIRECT(ADDRESS(2,COLUMN())),OFFSET($BN$2,0,0,ROW()-1,60),ROW()-1,FALSE)) -> 12081.561 | AW4: =IF(AND(ISNUMBER($AW$39),$B$31=1),$AW$39,HLOOKUP(INDIRECT(ADDRESS(2,COLUMN())),OFFSET($BN$2,0,0,ROW()-1,60),ROW()-1,FALSE)) -> 11959.79 | AX4: =IF(AND(ISNUMBER($AX$39),$B$31=1),$AX$39,HLOOKUP(INDIRECT(ADDRESS(2,COLUMN())),OFFSET($BN$2,0,0,ROW()-1,60),ROW()-1,FALSE)) -> 11810.451 | AY4: =IF(AND(ISNUMBER($AY$39),$B$31=1),$AY$39,HLOOKUP(INDIRECT(ADDRESS(2,COLUMN())),OFFSET($BN$2,0,0,ROW()-1,60),ROW()-1,FALSE)) -> 11646.001 | AZ4: =IF(AND(ISNUMBER($AZ$39),$B$31=1),$AZ$39,HLOOKUP(INDIRECT(ADDRESS(2,COLUMN())),OFFSET($BN$2,0,0,ROW()-1,60),ROW()-1,FALSE)) -> 11551.229 | BA4: =IF(AND(ISNUMBER($BA$39),$B$31=1),$BA$39,HLOOKUP(INDIRECT(ADDRESS(2,COLUMN())),OFFSET($BN$2,0,0,ROW()-1,60),ROW()-1,FALSE)) -> 11408.359 | BB4: =IF(AND(ISNUMBER($BB$39),$B$31=1),$BB$39,HLOOKUP(INDIRECT(ADDRESS(2,COLUMN())),OFFSET($BN$2,0,0,ROW()-1,60),ROW()-1,FALSE)) -> 11315.681 | BC4: =IF(AND(ISNUMBER($BC$39),$B$31=1),$BC$39,HLOOKUP(INDIRECT(ADDRESS(2,COLUMN())),OFFSET($BN$2,0,0,ROW()-1,60),ROW()-1,FALSE)) -> 11277.664 | BD4: =IF(AND(ISNUMBER($BD$39),$B$31=1),$BD$39,HLOOKUP(INDIRECT(ADDRESS(2,COLUMN())),OFFSET($BN$2,0,0,ROW()-1,60),ROW()-1,FALSE)) -> 11165.703 | BE4: =IF(AND(ISNUMBER($BE$39),$B$31=1),$BE$39,HLOOKUP(INDIRECT(ADDRESS(2,COLUMN())),OFFSET($BN$2,0,0,ROW()-1,60),ROW()-1,FALSE)) -> 11059.393 | BF4: =IF(AND(ISNUMBER($BF$39),$B$31=1),$BF$39,HLOOKUP(INDIRECT(ADDRESS(2,COLUMN())),OFFSET($BN$2,0,0,ROW()-1,60),ROW()-1,FALSE)) -> 11005.055 | BG4: =IF(AND(ISNUMBER($BG$39),$B$31=1),$BG$39,HLOOKUP(INDIRECT(ADDRESS(2,COLUMN())),OFFSET($BN$2,0,0,ROW()-1,60),ROW()-1,FALSE)) -> 10959.301 | BH4: =IF(AND(ISNUMBER($BH$39),$B$31=1),$BH$39,HLOOKUP(INDIRECT(ADDRESS(2,COLUMN())),OFFSET($BN$2,0,0,ROW()-1,60),ROW()-1,FALSE)) -> 10809.186 | BI4: =IF(AND(ISNUMBER($BI$39),$B$31=1),$BI$39,HLOOKUP(INDIRECT(ADDRESS(2,COLUMN())),OFFSET($BN$2,0,0,ROW()-1,60),ROW()-1,FALSE)) -> 10755.029 | BJ4: =IF(AND(ISNUMBER($BJ$39),$B$31=1),$BJ$39,HLOOKUP(INDIRECT(ADDRESS(2,COLUMN())),OFFSET($BN$2,0,0,ROW()-1,60),ROW()-1,FALSE)) -> 10673.018 | BK4: =IF(AND(ISNUMBER($BK$39),$B$31=1),$BK$39,HLOOKUP(INDIRECT(ADDRESS(2,COLUMN())),OFFSET($BN$2,0,0,ROW()-1,60),ROW()-1,FALSE)) -> 10558.195 | BL4: =IF(AND(ISNUMBER($BL$39),$B$31=1),$BL$39,HLOOKUP(INDIRECT(ADDRESS(2,COLUMN())),OFFSET($BN$2,0,0,ROW()-1,60),ROW()-1,FALSE)) -> 10430.304 | BM4: =IF(AND(ISNUMBER($BM$39),$B$31=1),$BM$39,HLOOKUP(INDIRECT(ADDRESS(2,COLUMN())),OFFSET($BN$2,0,0,ROW()-1,60),ROW()-1,FALSE)) -> 10300.754 | BN4: =20640.878 -> 20640.878 | BO4: =20461.602 -> 20461.602 | BP4: =20255.455 -> 20255.455 | BQ4: =19938.425 -> 19938.425 | BR4: =19682.699 -> 19682.699 | BS4: =19424.775 -> 19424.775 | BT4: =19170.154 -> 19170.154 | BU4: =18928.987 -> 18928.987 | BV4: =18685.724 -> 18685.724 | BW4: =18506.211 -> 18506.211 | BX4: =18108.27 -> 18108.27 | BY4: =17876.234 -> 17876.234 | BZ4: =17603.753 -> 17603.753 | CA4: =17175.105 -> 17175.105 | CB4: =16816.132 -> 16816.132 | CC4: =16363.876 -> 16363.876 | CD4: =16016.346 -> 16016.346 | CE4: =15259.427 -> 15259.427 | CF4: =14752.732 -> 14752.732 | CG4: =14478.033 -> 14478.033 | CH4: =13175.637 -> 13175.637 | CI4: =14496.227 -> 14496.227 | CJ4: =14701.038 -> 14701.038 | CK4: =14548.282 -> 14548.282 | CL4: =14350.662 -> 14350.662 | CM4: =14150.191 -> 14150.191 | CN4: =14099.199 -> 14099.199 | CO4: =14002.199 -> 14002.199 | CP4: =13891.294 -> 13891.294 | CQ4: =13745.074 -> 13745.074 | CR4: =13551.401 -> 13551.401 | CS4: =13325.065 -> 13325.065 | CT4: =13188.73 -> 13188.73 | CU4: =13097.306 -> 13097.306 | CV4: =12921.989 -> 12921.989 | CW4: =12797.126 -> 12797.126 | CX4: =12665.124 -> 12665.124 | CY4: =12523.156 -> 12523.156 | CZ4: =12423.353 -> 12423.353 | DA4: =12382.494 -> 12382.494 | DB4: =12264.14 -> 12264.14 | DC4: =12119.763 -> 12119.763 | DD4: =12081.561 -> 12081.561 | DE4: =11959.79 -> 11959.79 | DF4: =11810.451 -> 11810.451 | DG4: =11646.001 -> 11646.001 | DH4: =11551.229 -> 11551.229 | DI4: =11408.359 -> 11408.359 | DJ4: =11315.681 -> 11315.681 | DK4: =11277.664 -> 11277.664 | DL4: =11165.703 -> 11165.703 | DM4: =11059.393 -> 11059.393 | DN4: =11005.055 -> 11005.055 | DO4: =10959.301 -> 10959.301 | DP4: =10809.186 -> 10809.186 | DQ4: =10755.029 -> 10755.029 | DR4: =10673.018 -> 10673.018 | DS4: =10558.195 -> 10558.195 | DT4: =10430.304 -> 10430.304 | DU4: =10300.754 -> 10300.754
A5: =" Fixed Investment" -> Fixed Investment | B5: ="GPDIFXIN Index" -> GPDIFXIN Index | C5: ="PR005" -> PR005 | D5: ="PX_LAST" -> PX_LAST | E5: ="Dynamic" -> Dynamic | F5: =IF(AND(ISNUMBER($F$40),$B$31=1),$F$40,HLOOKUP(INDIRECT(ADDRESS(2,COLUMN())),OFFSET($BN$2,0,0,ROW()-1,60),ROW()-1,FALSE)) -> 5402.683 | G5: =IF(AND(ISNUMBER($G$40),$B$31=1),$G$40,HLOOKUP(INDIRECT(ADDRESS(2,COLUMN())),OFFSET($BN$2,0,0,ROW()-1,60),ROW()-1,FALSE)) -> 5388.729 | H5: =IF(AND(ISNUMBER($H$40),$B$31=1),$H$40,HLOOKUP(INDIRECT(ADDRESS(2,COLUMN())),OFFSET($BN$2,0,0,ROW()-1,60),ROW()-1,FALSE)) -> 5275.129 | I5: =IF(AND(ISNUMBER($I$40),$B$31=1),$I$40,HLOOKUP(INDIRECT(ADDRESS(2,COLUMN())),OFFSET($BN$2,0,0,ROW()-1,60),ROW()-1,FALSE)) -> 5269.195 | J5: =IF(AND(ISNUMBER($J$40),$B$31=1),$J$40,HLOOKUP(INDIRECT(ADDRESS(2,COLUMN())),OFFSET($BN$2,0,0,ROW()-1,60),ROW()-1,FALSE)) -> 5201.053 | K5: =IF(AND(ISNUMBER($K$40),$B$31=1),$K$40,HLOOKUP(INDIRECT(ADDRESS(2,COLUMN())),OFFSET($BN$2,0,0,ROW()-1,60),ROW()-1,FALSE)) -> 5138.499 | L5: =IF(AND(ISNUMBER($L$40),$B$31=1),$L$40,HLOOKUP(INDIRECT(ADDRESS(2,COLUMN())),OFFSET($BN$2,0,0,ROW()-1,60),ROW()-1,FALSE)) -> 5046.126 | M5: =IF(AND(ISNUMBER($M$40),$B$31=1),$M$40,HLOOKUP(INDIRECT(ADDRESS(2,COLUMN())),OFFSET($BN$2,0,0,ROW()-1,60),ROW()-1,FALSE)) -> 4974.163 | N5: =IF(AND(ISNUMBER($N$40),$B$31=1),$N$40,HLOOKUP(INDIRECT(ADDRESS(2,COLUMN())),OFFSET($BN$2,0,0,ROW()-1,60),ROW()-1,FALSE)) -> 4925.655 | O5: =IF(AND(ISNUMBER($O$40),$B$31=1),$O$40,HLOOKUP(INDIRECT(ADDRESS(2,COLUMN())),OFFSET($BN$2,0,0,ROW()-1,60),ROW()-1,FALSE)) -> 4826.317 | P5: =IF(AND(ISNUMBER($P$40),$B$31=1),$P$40,HLOOKUP(INDIRECT(ADDRESS(2,COLUMN())),OFFSET($BN$2,0,0,ROW()-1,60),ROW()-1,FALSE)) -> 4749.042 | Q5: =IF(AND(ISNUMBER($Q$40),$B$31=1),$Q$40,HLOOKUP(INDIRECT(ADDRESS(2,COLUMN())),OFFSET($BN$2,0,0,ROW()-1,60),ROW()-1,FALSE)) -> 4727.803 | R5: =IF(AND(ISNUMBER($R$40),$B$31=1),$R$40,HLOOKUP(INDIRECT(ADDRESS(2,COLUMN())),OFFSET($BN$2,0,0,ROW()-1,60),ROW()-1,FALSE)) -> 4669.571 | S5: =IF(AND(ISNUMBER($S$40),$B$31=1),$S$40,HLOOKUP(INDIRECT(ADDRESS(2,COLUMN())),OFFSET($BN$2,0,0,ROW()-1,60),ROW()-1,FALSE)) -> 4539.883 | T5: =IF(AND(ISNUMBER($T$40),$B$31=1),$T$40,HLOOKUP(INDIRECT(ADDRESS(2,COLUMN())),OFFSET($BN$2,0,0,ROW()-1,60),ROW()-1,FALSE)) -> 4346.39 | U5: =IF(AND(ISNUMBER($U$40),$B$31=1),$U$40,HLOOKUP(INDIRECT(ADDRESS(2,COLUMN())),OFFSET($BN$2,0,0,ROW()-1,60),ROW()-1,FALSE)) -> 4231.018 | V5: =IF(AND(ISNUMBER($V$40),$B$31=1),$V$40,HLOOKUP(INDIRECT(ADDRESS(2,COLUMN())),OFFSET($BN$2,0,0,ROW()-1,60),ROW()-1,FALSE)) -> 4182.192 | W5: =IF(AND(ISNUMBER($W$40),$B$31=1),$W$40,HLOOKUP(INDIRECT(ADDRESS(2,COLUMN())),OFFSET($BN$2,0,0,ROW()-1,60),ROW()-1,FALSE)) -> 4086.717 | X5: =IF(AND(ISNUMBER($X$40),$B$31=1),$X$40,HLOOKUP(INDIRECT(ADDRESS(2,COLUMN())),OFFSET($BN$2,0,0,ROW()-1,60),ROW()-1,FALSE)) -> 3968.294 | Y5: =IF(AND(ISNUMBER($Y$40),$B$31=1),$Y$40,HLOOKUP(INDIRECT(ADDRESS(2,COLUMN())),OFFSET($BN$2,0,0,ROW()-1,60),ROW()-1,FALSE)) -> 3802.372 | Z5: =IF(AND(ISNUMBER($Z$40),$B$31=1),$Z$40,HLOOKUP(INDIRECT(ADDRESS(2,COLUMN())),OFFSET($BN$2,0,0,ROW()-1,60),ROW()-1,FALSE)) -> 3552.634 | AA5: =IF(AND(ISNUMBER($AA$40),$B$31=1),$AA$40,HLOOKUP(INDIRECT(ADDRESS(2,COLUMN())),OFFSET($BN$2,0,0,ROW()-1,60),ROW()-1,FALSE)) -> 3841.036 | AB5: =IF(AND(ISNUMBER($AB$40),$B$31=1),$AB$40,HLOOKUP(INDIRECT(ADDRESS(2,COLUMN())),OFFSET($BN$2,0,0,ROW()-1,60),ROW()-1,FALSE)) -> 3857.115 | AC5: =IF(AND(ISNUMBER($AC$40),$B$31=1),$AC$40,HLOOKUP(INDIRECT(ADDRESS(2,COLUMN())),OFFSET($BN$2,0,0,ROW()-1,60),ROW()-1,FALSE)) -> 3869.365 | AD5: =IF(AND(ISNUMBER($AD$40),$B$31=1),$AD$40,HLOOKUP(INDIRECT(ADDRESS(2,COLUMN())),OFFSET($BN$2,0,0,ROW()-1,60),ROW()-1,FALSE)) -> 3820.789 | AE5: =IF(AND(ISNUMBER($AE$40),$B$31=1),$AE$40,HLOOKUP(INDIRECT(ADDRESS(2,COLUMN())),OFFSET($BN$2,0,0,ROW()-1,60),ROW()-1,FALSE)) -> 3735.845 | AF5: =IF(AND(ISNUMBER($AF$40),$B$31=1),$AF$40,HLOOKUP(INDIRECT(ADDRESS(2,COLUMN())),OFFSET($BN$2,0,0,ROW()-1,60),ROW()-1,FALSE)) -> 3706.704 | AG5: =IF(AND(ISNUMBER($AG$40),$B$31=1),$AG$40,HLOOKUP(INDIRECT(ADDRESS(2,COLUMN())),OFFSET($BN$2,0,0,ROW()-1,60),ROW()-1,FALSE)) -> 3690.028 | AH5: =IF(AND(ISNUMBER($AH$40),$B$31=1),$AH$40,HLOOKUP(INDIRECT(ADDRESS(2,COLUMN())),OFFSET($BN$2,0,0,ROW()-1,60),ROW()-1,FALSE)) -> 3666.129 | AI5: =IF(AND(ISNUMBER($AI$40),$B$31=1),$AI$40,HLOOKUP(INDIRECT(ADDRESS(2,COLUMN())),OFFSET($BN$2,0,0,ROW()-1,60),ROW()-1,FALSE)) -> 3610.589 | AJ5: =IF(AND(ISNUMBER($AJ$40),$B$31=1),$AJ$40,HLOOKUP(INDIRECT(ADDRESS(2,COLUMN())),OFFSET($BN$2,0,0,ROW()-1,60),ROW()-1,FALSE)) -> 3530.448 | AK5: =IF(AND(ISNUMBER($AK$40),$B$31=1),$AK$40,HLOOKUP(INDIRECT(ADDRESS(2,COLUMN())),OFFSET($BN$2,0,0,ROW()-1,60),ROW()-1,FALSE)) -> 3445.283 | AL5: =IF(AND(ISNUMBER($AL$40),$B$31=1),$AL$40,HLOOKUP(INDIRECT(ADDRESS(2,COLUMN())),OFFSET($BN$2,0,0,ROW()-1,60),ROW()-1,FALSE)) -> 3407.44 | AM5: =IF(AND(ISNUMBER($AM$40),$B$31=1),$AM$40,HLOOKUP(INDIRECT(ADDRESS(2,COLUMN())),OFFSET($BN$2,0,0,ROW()-1,60),ROW()-1,FALSE)) -> 3356.791 | AN5: =IF(AND(ISNUMBER($AN$40),$B$31=1),$AN$40,HLOOKUP(INDIRECT(ADDRESS(2,COLUMN())),OFFSET($BN$2,0,0,ROW()-1,60),ROW()-1,FALSE)) -> 3302.805 | AO5: =IF(AND(ISNUMBER($AO$40),$B$31=1),$AO$40,HLOOKUP(INDIRECT(ADDRESS(2,COLUMN())),OFFSET($BN$2,0,0,ROW()-1,60),ROW()-1,FALSE)) -> 3256.247 | AP5: =IF(AND(ISNUMBER($AP$40),$B$31=1),$AP$40,HLOOKUP(INDIRECT(ADDRESS(2,COLUMN())),OFFSET($BN$2,0,0,ROW()-1,60),ROW()-1,FALSE)) -> 3215.897 | AQ5: =IF(AND(ISNUMBER($AQ$40),$B$31=1),$AQ$40,HLOOKUP(INDIRECT(ADDRESS(2,COLUMN())),OFFSET($BN$2,0,0,ROW()-1,60),ROW()-1,FALSE)) -> 3181.999 | AR5: =IF(AND(ISNUMBER($AR$40),$B$31=1),$AR$40,HLOOKUP(INDIRECT(ADDRESS(2,COLUMN())),OFFSET($BN$2,0,0,ROW()-1,60),ROW()-1,FALSE)) -> 3169.729 | AS5: =IF(AND(ISNUMBER($AS$40),$B$31=1),$AS$40,HLOOKUP(INDIRECT(ADDRESS(2,COLUMN())),OFFSET($BN$2,0,0,ROW()-1,60),ROW()-1,FALSE)) -> 3176.809 | AT5: =IF(AND(ISNUMBER($AT$40),$B$31=1),$AT$40,HLOOKUP(INDIRECT(ADDRESS(2,COLUMN())),OFFSET($BN$2,0,0,ROW()-1,60),ROW()-1,FALSE)) -> 3139.856 | AU5: =IF(AND(ISNUMBER($AU$40),$B$31=1),$AU$40,HLOOKUP(INDIRECT(ADDRESS(2,COLUMN())),OFFSET($BN$2,0,0,ROW()-1,60),ROW()-1,FALSE)) -> 3107.041 | AV5: =IF(AND(ISNUMBER($AV$40),$B$31=1),$AV$40,HLOOKUP(INDIRECT(ADDRESS(2,COLUMN())),OFFSET($BN$2,0,0,ROW()-1,60),ROW()-1,FALSE)) -> 3086.53 | AW5: =IF(AND(ISNUMBER($AW$40),$B$31=1),$AW$40,HLOOKUP(INDIRECT(ADDRESS(2,COLUMN())),OFFSET($BN$2,0,0,ROW()-1,60),ROW()-1,FALSE)) -> 3038.113 | AX5: =IF(AND(ISNUMBER($AX$40),$B$31=1),$AX$40,HLOOKUP(INDIRECT(ADDRESS(2,COLUMN())),OFFSET($BN$2,0,0,ROW()-1,60),ROW()-1,FALSE)) -> 2961.343 | AY5: =IF(AND(ISNUMBER($AY$40),$B$31=1),$AY$40,HLOOKUP(INDIRECT(ADDRESS(2,COLUMN())),OFFSET($BN$2,0,0,ROW()-1,60),ROW()-1,FALSE)) -> 2870.77 | AZ5: =IF(AND(ISNUMBER($AZ$40),$B$31=1),$AZ$40,HLOOKUP(INDIRECT(ADDRESS(2,COLUMN())),OFFSET($BN$2,0,0,ROW()-1,60),ROW()-1,FALSE)) -> 2816.948 | BA5: =IF(AND(ISNUMBER($BA$40),$B$31=1),$BA$40,HLOOKUP(INDIRECT(ADDRESS(2,COLUMN())),OFFSET($BN$2,0,0,ROW()-1,60),ROW()-1,FALSE)) -> 2755.705 | BB5: =IF(AND(ISNUMBER($BB$40),$B$31=1),$BB$40,HLOOKUP(INDIRECT(ADDRESS(2,COLUMN())),OFFSET($BN$2,0,0,ROW()-1,60),ROW()-1,FALSE)) -> 2697.549 | BC5: =IF(AND(ISNUMBER($BC$40),$B$31=1),$BC$40,HLOOKUP(INDIRECT(ADDRESS(2,COLUMN())),OFFSET($BN$2,0,0,ROW()-1,60),ROW()-1,FALSE)) -> 2661.196 | BD5: =IF(AND(ISNUMBER($BD$40),$B$31=1),$BD$40,HLOOKUP(INDIRECT(ADDRESS(2,COLUMN())),OFFSET($BN$2,0,0,ROW()-1,60),ROW()-1,FALSE)) -> 2609.548 | BE5: =IF(AND(ISNUMBER($BE$40),$B$31=1),$BE$40,HLOOKUP(INDIRECT(ADDRESS(2,COLUMN())),OFFSET($BN$2,0,0,ROW()-1,60),ROW()-1,FALSE)) -> 2559.69 | BF5: =IF(AND(ISNUMBER($BF$40),$B$31=1),$BF$40,HLOOKUP(INDIRECT(ADDRESS(2,COLUMN())),OFFSET($BN$2,0,0,ROW()-1,60),ROW()-1,FALSE)) -> 2545.458 | BG5: =IF(AND(ISNUMBER($BG$40),$B$31=1),$BG$40,HLOOKUP(INDIRECT(ADDRESS(2,COLUMN())),OFFSET($BN$2,0,0,ROW()-1,60),ROW()-1,FALSE)) -> 2487.473 | BH5: =IF(AND(ISNUMBER($BH$40),$B$31=1),$BH$40,HLOOKUP(INDIRECT(ADDRESS(2,COLUMN())),OFFSET($BN$2,0,0,ROW()-1,60),ROW()-1,FALSE)) -> 2400.138 | BI5: =IF(AND(ISNUMBER($BI$40),$B$31=1),$BI$40,HLOOKUP(INDIRECT(ADDRESS(2,COLUMN())),OFFSET($BN$2,0,0,ROW()-1,60),ROW()-1,FALSE)) -> 2334.873 | BJ5: =IF(AND(ISNUMBER($BJ$40),$B$31=1),$BJ$40,HLOOKUP(INDIRECT(ADDRESS(2,COLUMN())),OFFSET($BN$2,0,0,ROW()-1,60),ROW()-1,FALSE)) -> 2236.305 | BK5: =IF(AND(ISNUMBER($BK$40),$B$31=1),$BK$40,HLOOKUP(INDIRECT(ADDRESS(2,COLUMN())),OFFSET($BN$2,0,0,ROW()-1,60),ROW()-1,FALSE)) -> 2173.885 | BL5: =IF(AND(ISNUMBER($BL$40),$B$31=1),$BL$40,HLOOKUP(INDIRECT(ADDRESS(2,COLUMN())),OFFSET($BN$2,0,0,ROW()-1,60),ROW()-1,FALSE)) -> 2171.138 | BM5: =IF(AND(ISNUMBER($BM$40),$B$31=1),$BM$40,HLOOKUP(INDIRECT(ADDRESS(2,COLUMN())),OFFSET($BN$2,0,0,ROW()-1,60),ROW()-1,FALSE)) -> 2123.598 | BN5: =5402.683 -> 5402.683 | BO5: =5388.729 -> 5388.729 | BP5: =5275.129 -> 5275.129 | BQ5: =5269.195 -> 5269.195 | BR5: =5201.053 -> 5201.053 | BS5: =5138.499 -> 5138.499 | BT5: =5046.126 -> 5046.126 | BU5: =4974.163 -> 4974.163 | BV5: =4925.655 -> 4925.655 | BW5: =4826.317 -> 4826.317 | BX5: =4749.042 -> 4749.042 | BY5: =4727.803 -> 4727.803 | BZ5: =4669.571 -> 4669.571 | CA5: =4539.883 -> 4539.883 | CB5: =4346.39 -> 4346.39 | CC5: =4231.018 -> 4231.018 | CD5: =4182.192 -> 4182.192 | CE5: =4086.717 -> 4086.717 | CF5: =3968.294 -> 3968.294 | CG5: =3802.372 -> 3802.372 | CH5: =3552.634 -> 3552.634 | CI5: =3841.036 -> 3841.036 | CJ5: =3857.115 -> 3857.115 | CK5: =3869.365 -> 3869.365 | CL5: =3820.789 -> 3820.789 | CM5: =3735.845 -> 3735.845 | CN5: =3706.704 -> 3706.704 | CO5: =3690.028 -> 3690.028 | CP5: =3666.129 -> 3666.129 | CQ5: =3610.589 -> 3610.589 | CR5: =3530.448 -> 3530.448 | CS5: =3445.283 -> 3445.283 | CT5: =3407.44 -> 3407.44 | CU5: =3356.791 -> 3356.791 | CV5: =3302.805 -> 3302.805 | CW5: =3256.247 -> 3256.247 | CX5: =3215.897 -> 3215.897 | CY5: =3181.999 -> 3181.999 | CZ5: =3169.729 -> 3169.729 | DA5: =3176.809 -> 3176.809 | DB5: =3139.856 -> 3139.856 | DC5: =3107.041 -> 3107.041 | DD5: =3086.53 -> 3086.53 | DE5: =3038.113 -> 3038.113 | DF5: =2961.343 -> 2961.343 | DG5: =2870.77 -> 2870.77 | DH5: =2816.948 -> 2816.948 | DI5: =2755.705 -> 2755.705 | DJ5: =2697.549 -> 2697.549 | DK5: =2661.196 -> 2661.196 | DL5: =2609.548 -> 2609.548 | DM5: =2559.69 -> 2559.69 | DN5: =2545.458 -> 2545.458 | DO5: =2487.473 -> 2487.473 | DP5: =2400.138 -> 2400.138 | DQ5: =2334.873 -> 2334.873 | DR5: =2236.305 -> 2236.305 | DS5: =2173.885 -> 2173.885 | DT5: =2171.138 -> 2171.138 | DU5: =2123.598 -> 2123.598
A6: =" Change in Private Inventories" -> Change in Private Inventories | B6: ="GDP$PICG Index" -> GDP$PICG Index | C6: ="PR005" -> PR005 | D6: ="PX_LAST" -> PX_LAST | E6: ="Dynamic" -> Dynamic | F6: =IF(AND(ISNUMBER($F$41),$B$31=1),$F$41,HLOOKUP(INDIRECT(ADDRESS(2,COLUMN())),OFFSET($BN$2,0,0,ROW()-1,60),ROW()-1,FALSE)) -> -29.716 | G6: =IF(AND(ISNUMBER($G$41),$B$31=1),$G$41,HLOOKUP(INDIRECT(ADDRESS(2,COLUMN())),OFFSET($BN$2,0,0,ROW()-1,60),ROW()-1,FALSE)) -> 206.965 | H6: =IF(AND(ISNUMBER($H$41),$B$31=1),$H$41,HLOOKUP(INDIRECT(ADDRESS(2,COLUMN())),OFFSET($BN$2,0,0,ROW()-1,60),ROW()-1,FALSE)) -> 13.634 | I6: =IF(AND(ISNUMBER($I$41),$B$31=1),$I$41,HLOOKUP(INDIRECT(ADDRESS(2,COLUMN())),OFFSET($BN$2,0,0,ROW()-1,60),ROW()-1,FALSE)) -> 75.97 | J6: =IF(AND(ISNUMBER($J$41),$B$31=1),$J$41,HLOOKUP(INDIRECT(ADDRESS(2,COLUMN())),OFFSET($BN$2,0,0,ROW()-1,60),ROW()-1,FALSE)) -> 96.792 | K6: =IF(AND(ISNUMBER($K$41),$B$31=1),$K$41,HLOOKUP(INDIRECT(ADDRESS(2,COLUMN())),OFFSET($BN$2,0,0,ROW()-1,60),ROW()-1,FALSE)) -> 21.404 | L6: =IF(AND(ISNUMBER($L$41),$B$31=1),$L$41,HLOOKUP(INDIRECT(ADDRESS(2,COLUMN())),OFFSET($BN$2,0,0,ROW()-1,60),ROW()-1,FALSE)) -> 56.688 | M6: =IF(AND(ISNUMBER($M$41),$B$31=1),$M$41,HLOOKUP(INDIRECT(ADDRESS(2,COLUMN())),OFFSET($BN$2,0,0,ROW()-1,60),ROW()-1,FALSE)) -> 89.189 | N6: =IF(AND(ISNUMBER($N$41),$B$31=1),$N$41,HLOOKUP(INDIRECT(ADDRESS(2,COLUMN())),OFFSET($BN$2,0,0,ROW()-1,60),ROW()-1,FALSE)) -> 0.01 | O6: =IF(AND(ISNUMBER($O$41),$B$31=1),$O$41,HLOOKUP(INDIRECT(ADDRESS(2,COLUMN())),OFFSET($BN$2,0,0,ROW()-1,60),ROW()-1,FALSE)) -> 20.894 | P6: =IF(AND(ISNUMBER($P$41),$B$31=1),$P$41,HLOOKUP(INDIRECT(ADDRESS(2,COLUMN())),OFFSET($BN$2,0,0,ROW()-1,60),ROW()-1,FALSE)) -> 162.858 | Q6: =IF(AND(ISNUMBER($Q$41),$B$31=1),$Q$41,HLOOKUP(INDIRECT(ADDRESS(2,COLUMN())),OFFSET($BN$2,0,0,ROW()-1,60),ROW()-1,FALSE)) -> 73.821 | R6: =IF(AND(ISNUMBER($R$41),$B$31=1),$R$41,HLOOKUP(INDIRECT(ADDRESS(2,COLUMN())),OFFSET($BN$2,0,0,ROW()-1,60),ROW()-1,FALSE)) -> 116.971 | S6: =IF(AND(ISNUMBER($S$41),$B$31=1),$S$41,HLOOKUP(INDIRECT(ADDRESS(2,COLUMN())),OFFSET($BN$2,0,0,ROW()-1,60),ROW()-1,FALSE)) -> 244.937 | T6: =IF(AND(ISNUMBER($T$41),$B$31=1),$T$41,HLOOKUP(INDIRECT(ADDRESS(2,COLUMN())),OFFSET($BN$2,0,0,ROW()-1,60),ROW()-1,FALSE)) -> 252.794 | U6: =IF(AND(ISNUMBER($U$41),$B$31=1),$U$41,HLOOKUP(INDIRECT(ADDRESS(2,COLUMN())),OFFSET($BN$2,0,0,ROW()-1,60),ROW()-1,FALSE)) -> 1.807 | V6: =IF(AND(ISNUMBER($V$41),$B$31=1),$V$41,HLOOKUP(INDIRECT(ADDRESS(2,COLUMN())),OFFSET($BN$2,0,0,ROW()-1,60),ROW()-1,FALSE)) -> -164.611 | W6: =IF(AND(ISNUMBER($W$41),$B$31=1),$W$41,HLOOKUP(INDIRECT(ADDRESS(2,COLUMN())),OFFSET($BN$2,0,0,ROW()-1,60),ROW()-1,FALSE)) -> -41.219 | X6: =IF(AND(ISNUMBER($X$41),$B$31=1),$X$41,HLOOKUP(INDIRECT(ADDRESS(2,COLUMN())),OFFSET($BN$2,0,0,ROW()-1,60),ROW()-1,FALSE)) -> 78.055 | Y6: =IF(AND(ISNUMBER($Y$41),$B$31=1),$Y$41,HLOOKUP(INDIRECT(ADDRESS(2,COLUMN())),OFFSET($BN$2,0,0,ROW()-1,60),ROW()-1,FALSE)) -> 98.975 | Z6: =IF(AND(ISNUMBER($Z$41),$B$31=1),$Z$41,HLOOKUP(INDIRECT(ADDRESS(2,COLUMN())),OFFSET($BN$2,0,0,ROW()-1,60),ROW()-1,FALSE)) -> -282.276 | AA6: =IF(AND(ISNUMBER($AA$41),$B$31=1),$AA$41,HLOOKUP(INDIRECT(ADDRESS(2,COLUMN())),OFFSET($BN$2,0,0,ROW()-1,60),ROW()-1,FALSE)) -> -39.039 | AB6: =IF(AND(ISNUMBER($AB$41),$B$31=1),$AB$41,HLOOKUP(INDIRECT(ADDRESS(2,COLUMN())),OFFSET($BN$2,0,0,ROW()-1,60),ROW()-1,FALSE)) -> 23.455 | AC6: =IF(AND(ISNUMBER($AC$41),$B$31=1),$AC$41,HLOOKUP(INDIRECT(ADDRESS(2,COLUMN())),OFFSET($BN$2,0,0,ROW()-1,60),ROW()-1,FALSE)) -> 70.234 | AD6: =IF(AND(ISNUMBER($AD$41),$B$31=1),$AD$41,HLOOKUP(INDIRECT(ADDRESS(2,COLUMN())),OFFSET($BN$2,0,0,ROW()-1,60),ROW()-1,FALSE)) -> 83.207 | AE6: =IF(AND(ISNUMBER($AE$41),$B$31=1),$AE$41,HLOOKUP(INDIRECT(ADDRESS(2,COLUMN())),OFFSET($BN$2,0,0,ROW()-1,60),ROW()-1,FALSE)) -> 114.925 | AF6: =IF(AND(ISNUMBER($AF$41),$B$31=1),$AF$41,HLOOKUP(INDIRECT(ADDRESS(2,COLUMN())),OFFSET($BN$2,0,0,ROW()-1,60),ROW()-1,FALSE)) -> 95.324 | AG6: =IF(AND(ISNUMBER($AG$41),$B$31=1),$AG$41,HLOOKUP(INDIRECT(ADDRESS(2,COLUMN())),OFFSET($BN$2,0,0,ROW()-1,60),ROW()-1,FALSE)) -> 98.664 | AH6: =IF(AND(ISNUMBER($AH$41),$B$31=1),$AH$41,HLOOKUP(INDIRECT(ADDRESS(2,COLUMN())),OFFSET($BN$2,0,0,ROW()-1,60),ROW()-1,FALSE)) -> -3.402 | AI6: =IF(AND(ISNUMBER($AI$41),$B$31=1),$AI$41,HLOOKUP(INDIRECT(ADDRESS(2,COLUMN())),OFFSET($BN$2,0,0,ROW()-1,60),ROW()-1,FALSE)) -> 35.045 | AJ6: =IF(AND(ISNUMBER($AJ$41),$B$31=1),$AJ$41,HLOOKUP(INDIRECT(ADDRESS(2,COLUMN())),OFFSET($BN$2,0,0,ROW()-1,60),ROW()-1,FALSE)) -> 43.998 | AK6: =IF(AND(ISNUMBER($AK$41),$B$31=1),$AK$41,HLOOKUP(INDIRECT(ADDRESS(2,COLUMN())),OFFSET($BN$2,0,0,ROW()-1,60),ROW()-1,FALSE)) -> 54.859 | AL6: =IF(AND(ISNUMBER($AL$41),$B$31=1),$AL$41,HLOOKUP(INDIRECT(ADDRESS(2,COLUMN())),OFFSET($BN$2,0,0,ROW()-1,60),ROW()-1,FALSE)) -> 25.528 | AM6: =IF(AND(ISNUMBER($AM$41),$B$31=1),$AM$41,HLOOKUP(INDIRECT(ADDRESS(2,COLUMN())),OFFSET($BN$2,0,0,ROW()-1,60),ROW()-1,FALSE)) -> 6.311 | AN6: =IF(AND(ISNUMBER($AN$41),$B$31=1),$AN$41,HLOOKUP(INDIRECT(ADDRESS(2,COLUMN())),OFFSET($BN$2,0,0,ROW()-1,60),ROW()-1,FALSE)) -> 58.147 | AO6: =IF(AND(ISNUMBER($AO$41),$B$31=1),$AO$41,HLOOKUP(INDIRECT(ADDRESS(2,COLUMN())),OFFSET($BN$2,0,0,ROW()-1,60),ROW()-1,FALSE)) -> 5.324 | AP6: =IF(AND(ISNUMBER($AP$41),$B$31=1),$AP$41,HLOOKUP(INDIRECT(ADDRESS(2,COLUMN())),OFFSET($BN$2,0,0,ROW()-1,60),ROW()-1,FALSE)) -> 30.484 | AQ6: =IF(AND(ISNUMBER($AQ$41),$B$31=1),$AQ$41,HLOOKUP(INDIRECT(ADDRESS(2,COLUMN())),OFFSET($BN$2,0,0,ROW()-1,60),ROW()-1,FALSE)) -> 62.318 | AR6: =IF(AND(ISNUMBER($AR$41),$B$31=1),$AR$41,HLOOKUP(INDIRECT(ADDRESS(2,COLUMN())),OFFSET($BN$2,0,0,ROW()-1,60),ROW()-1,FALSE)) -> 107.15 | AS6: =IF(AND(ISNUMBER($AS$41),$B$31=1),$AS$41,HLOOKUP(INDIRECT(ADDRESS(2,COLUMN())),OFFSET($BN$2,0,0,ROW()-1,60),ROW()-1,FALSE)) -> 126.851 | AT6: =IF(AND(ISNUMBER($AT$41),$B$31=1),$AT$41,HLOOKUP(INDIRECT(ADDRESS(2,COLUMN())),OFFSET($BN$2,0,0,ROW()-1,60),ROW()-1,FALSE)) -> 151.248 | AU6: =IF(AND(ISNUMBER($AU$41),$B$31=1),$AU$41,HLOOKUP(INDIRECT(ADDRESS(2,COLUMN())),OFFSET($BN$2,0,0,ROW()-1,60),ROW()-1,FALSE)) -> 175.242 | AV6: =IF(AND(ISNUMBER($AV$41),$B$31=1),$AV$41,HLOOKUP(INDIRECT(ADDRESS(2,COLUMN())),OFFSET($BN$2,0,0,ROW()-1,60),ROW()-1,FALSE)) -> 85.485 | AW6: =IF(AND(ISNUMBER($AW$41),$B$31=1),$AW$41,HLOOKUP(INDIRECT(ADDRESS(2,COLUMN())),OFFSET($BN$2,0,0,ROW()-1,60),ROW()-1,FALSE)) -> 103.934 | AX6: =IF(AND(ISNUMBER($AX$41),$B$31=1),$AX$41,HLOOKUP(INDIRECT(ADDRESS(2,COLUMN())),OFFSET($BN$2,0,0,ROW()-1,60),ROW()-1,FALSE)) -> 97.753 | AY6: =IF(AND(ISNUMBER($AY$41),$B$31=1),$AY$41,HLOOKUP(INDIRECT(ADDRESS(2,COLUMN())),OFFSET($BN$2,0,0,ROW()-1,60),ROW()-1,FALSE)) -> 51.995 | AZ6: =IF(AND(ISNUMBER($AZ$41),$B$31=1),$AZ$41,HLOOKUP(INDIRECT(ADDRESS(2,COLUMN())),OFFSET($BN$2,0,0,ROW()-1,60),ROW()-1,FALSE)) -> 117.343 | BA6: =IF(AND(ISNUMBER($BA$41),$B$31=1),$BA$41,HLOOKUP(INDIRECT(ADDRESS(2,COLUMN())),OFFSET($BN$2,0,0,ROW()-1,60),ROW()-1,FALSE)) -> 136.649 | BB6: =IF(AND(ISNUMBER($BB$41),$B$31=1),$BB$41,HLOOKUP(INDIRECT(ADDRESS(2,COLUMN())),OFFSET($BN$2,0,0,ROW()-1,60),ROW()-1,FALSE)) -> 82.693 | BC6: =IF(AND(ISNUMBER($BC$41),$B$31=1),$BC$41,HLOOKUP(INDIRECT(ADDRESS(2,COLUMN())),OFFSET($BN$2,0,0,ROW()-1,60),ROW()-1,FALSE)) -> 85.223 | BD6: =IF(AND(ISNUMBER($BD$41),$B$31=1),$BD$41,HLOOKUP(INDIRECT(ADDRESS(2,COLUMN())),OFFSET($BN$2,0,0,ROW()-1,60),ROW()-1,FALSE)) -> 28.734 | BE6: =IF(AND(ISNUMBER($BE$41),$B$31=1),$BE$41,HLOOKUP(INDIRECT(ADDRESS(2,COLUMN())),OFFSET($BN$2,0,0,ROW()-1,60),ROW()-1,FALSE)) -> 84.429 | BF6: =IF(AND(ISNUMBER($BF$41),$B$31=1),$BF$41,HLOOKUP(INDIRECT(ADDRESS(2,COLUMN())),OFFSET($BN$2,0,0,ROW()-1,60),ROW()-1,FALSE)) -> 91.406 | BG6: =IF(AND(ISNUMBER($BG$41),$B$31=1),$BG$41,HLOOKUP(INDIRECT(ADDRESS(2,COLUMN())),OFFSET($BN$2,0,0,ROW()-1,60),ROW()-1,FALSE)) -> 80.278 | BH6: =IF(AND(ISNUMBER($BH$41),$B$31=1),$BH$41,HLOOKUP(INDIRECT(ADDRESS(2,COLUMN())),OFFSET($BN$2,0,0,ROW()-1,60),ROW()-1,FALSE)) -> 103.956 | BI6: =IF(AND(ISNUMBER($BI$41),$B$31=1),$BI$41,HLOOKUP(INDIRECT(ADDRESS(2,COLUMN())),OFFSET($BN$2,0,0,ROW()-1,60),ROW()-1,FALSE)) -> -12.033 | BJ6: =IF(AND(ISNUMBER($BJ$41),$B$31=1),$BJ$41,HLOOKUP(INDIRECT(ADDRESS(2,COLUMN())),OFFSET($BN$2,0,0,ROW()-1,60),ROW()-1,FALSE)) -> 61.047 | BK6: =IF(AND(ISNUMBER($BK$41),$B$31=1),$BK$41,HLOOKUP(INDIRECT(ADDRESS(2,COLUMN())),OFFSET($BN$2,0,0,ROW()-1,60),ROW()-1,FALSE)) -> 32.078 | BL6: =IF(AND(ISNUMBER($BL$41),$B$31=1),$BL$41,HLOOKUP(INDIRECT(ADDRESS(2,COLUMN())),OFFSET($BN$2,0,0,ROW()-1,60),ROW()-1,FALSE)) -> 67.301 | BM6: =IF(AND(ISNUMBER($BM$41),$B$31=1),$BM$41,HLOOKUP(INDIRECT(ADDRESS(2,COLUMN())),OFFSET($BN$2,0,0,ROW()-1,60),ROW()-1,FALSE)) -> 112.897 | BN6: =-29.716 -> -29.716 | BO6: =206.965 -> 206.965 | BP6: =13.634 -> 13.634 | BQ6: =75.97 -> 75.97 | BR6: =96.792 -> 96.792 | BS6: =21.404 -> 21.404 | BT6: =56.688 -> 56.688 | BU6: =89.189 -> 89.189 | BV6: =0.01 -> 0.01 | BW6: =20.894 -> 20.894 | BX6: =162.858 -> 162.858 | BY6: =73.821 -> 73.821 | BZ6: =116.971 -> 116.971 | CA6: =244.937 -> 244.937 | CB6: =252.794 -> 252.794 | CC6: =1.807 -> 1.807 | CD6: =-164.611 -> -164.611 | CE6: =-41.219 -> -41.219 | CF6: =78.055 -> 78.055 | CG6: =98.975 -> 98.975 | CH6: =-282.276 -> -282.276 | CI6: =-39.039 -> -39.039 | CJ6: =23.455 -> 23.455 | CK6: =70.234 -> 70.234 | CL6: =83.207 -> 83.207 | CM6: =114.925 -> 114.925 | CN6: =95.324 -> 95.324 | CO6: =98.664 -> 98.664 | CP6: =-3.402 -> -3.402 | CQ6: =35.045 -> 35.045 | CR6: =43.998 -> 43.998 | CS6: =54.859 -> 54.859 | CT6: =25.528 -> 25.528 | CU6: =6.311 -> 6.311 | CV6: =58.147 -> 58.147 | CW6: =5.324 -> 5.324 | CX6: =30.484 -> 30.484 | CY6: =62.318 -> 62.318 | CZ6: =107.15 -> 107.15 | DA6: =126.851 -> 126.851 | DB6: =151.248 -> 151.248 | DC6: =175.242 -> 175.242 | DD6: =85.485 -> 85.485 | DE6: =103.934 -> 103.934 | DF6: =97.753 -> 97.753 | DG6: =51.995 -> 51.995 | DH6: =117.343 -> 117.343 | DI6: =136.649 -> 136.649 | DJ6: =82.693 -> 82.693 | DK6: =85.223 -> 85.223 | DL6: =28.734 -> 28.734 | DM6: =84.429 -> 84.429 | DN6: =91.406 -> 91.406 | DO6: =80.278 -> 80.278 | DP6: =103.956 -> 103.956 | DQ6: =-12.033 -> -12.033 | DR6: =61.047 -> 61.047 | DS6: =32.078 -> 32.078 | DT6: =67.301 -> 67.301 | DU6: =112.897 -> 112.897
A7: =" Government: Consumption Expenditure" -> Government: Consumption Expenditure | B7: ="GCEXCONE Index" -> GCEXCONE Index | C7: ="PR005" -> PR005 | D7: ="PX_LAST" -> PX_LAST | E7: ="Dynamic" -> Dynamic | F7: =IF(AND(ISNUMBER($F$42),$B$31=1),$F$42,HLOOKUP(INDIRECT(ADDRESS(2,COLUMN())),OFFSET($BN$2,0,0,ROW()-1,60),ROW()-1,FALSE)) -> 4054.615 | G7: =IF(AND(ISNUMBER($G$42),$B$31=1),$G$42,HLOOKUP(INDIRECT(ADDRESS(2,COLUMN())),OFFSET($BN$2,0,0,ROW()-1,60),ROW()-1,FALSE)) -> 4030.962 | H7: =IF(AND(ISNUMBER($H$42),$B$31=1),$H$42,HLOOKUP(INDIRECT(ADDRESS(2,COLUMN())),OFFSET($BN$2,0,0,ROW()-1,60),ROW()-1,FALSE)) -> 3996.878 | I7: =IF(AND(ISNUMBER($I$42),$B$31=1),$I$42,HLOOKUP(INDIRECT(ADDRESS(2,COLUMN())),OFFSET($BN$2,0,0,ROW()-1,60),ROW()-1,FALSE)) -> 3947.656 | J7: =IF(AND(ISNUMBER($J$42),$B$31=1),$J$42,HLOOKUP(INDIRECT(ADDRESS(2,COLUMN())),OFFSET($BN$2,0,0,ROW()-1,60),ROW()-1,FALSE)) -> 3882.139 | K7: =IF(AND(ISNUMBER($K$42),$B$31=1),$K$42,HLOOKUP(INDIRECT(ADDRESS(2,COLUMN())),OFFSET($BN$2,0,0,ROW()-1,60),ROW()-1,FALSE)) -> 3840.088 | L7: =IF(AND(ISNUMBER($L$42),$B$31=1),$L$42,HLOOKUP(INDIRECT(ADDRESS(2,COLUMN())),OFFSET($BN$2,0,0,ROW()-1,60),ROW()-1,FALSE)) -> 3781.725 | M7: =IF(AND(ISNUMBER($M$42),$B$31=1),$M$42,HLOOKUP(INDIRECT(ADDRESS(2,COLUMN())),OFFSET($BN$2,0,0,ROW()-1,60),ROW()-1,FALSE)) -> 3758.931 | N7: =IF(AND(ISNUMBER($N$42),$B$31=1),$N$42,HLOOKUP(INDIRECT(ADDRESS(2,COLUMN())),OFFSET($BN$2,0,0,ROW()-1,60),ROW()-1,FALSE)) -> 3674.318 | O7: =IF(AND(ISNUMBER($O$42),$B$31=1),$O$42,HLOOKUP(INDIRECT(ADDRESS(2,COLUMN())),OFFSET($BN$2,0,0,ROW()-1,60),ROW()-1,FALSE)) -> 3680.844 | P7: =IF(AND(ISNUMBER($P$42),$B$31=1),$P$42,HLOOKUP(INDIRECT(ADDRESS(2,COLUMN())),OFFSET($BN$2,0,0,ROW()-1,60),ROW()-1,FALSE)) -> 3641.91 | Q7: =IF(AND(ISNUMBER($Q$42),$B$31=1),$Q$42,HLOOKUP(INDIRECT(ADDRESS(2,COLUMN())),OFFSET($BN$2,0,0,ROW()-1,60),ROW()-1,FALSE)) -> 3590.272 | R7: =IF(AND(ISNUMBER($R$42),$B$31=1),$R$42,HLOOKUP(INDIRECT(ADDRESS(2,COLUMN())),OFFSET($BN$2,0,0,ROW()-1,60),ROW()-1,FALSE)) -> 3560.032 | S7: =IF(AND(ISNUMBER($S$42),$B$31=1),$S$42,HLOOKUP(INDIRECT(ADDRESS(2,COLUMN())),OFFSET($BN$2,0,0,ROW()-1,60),ROW()-1,FALSE)) -> 3473.916 | T7: =IF(AND(ISNUMBER($T$42),$B$31=1),$T$42,HLOOKUP(INDIRECT(ADDRESS(2,COLUMN())),OFFSET($BN$2,0,0,ROW()-1,60),ROW()-1,FALSE)) -> 3440.748 | U7: =IF(AND(ISNUMBER($U$42),$B$31=1),$U$42,HLOOKUP(INDIRECT(ADDRESS(2,COLUMN())),OFFSET($BN$2,0,0,ROW()-1,60),ROW()-1,FALSE)) -> 3386.91 | V7: =IF(AND(ISNUMBER($V$42),$B$31=1),$V$42,HLOOKUP(INDIRECT(ADDRESS(2,COLUMN())),OFFSET($BN$2,0,0,ROW()-1,60),ROW()-1,FALSE)) -> 3348.272 | W7: =IF(AND(ISNUMBER($W$42),$B$31=1),$W$42,HLOOKUP(INDIRECT(ADDRESS(2,COLUMN())),OFFSET($BN$2,0,0,ROW()-1,60),ROW()-1,FALSE)) -> 3325.207 | X7: =IF(AND(ISNUMBER($X$42),$B$31=1),$X$42,HLOOKUP(INDIRECT(ADDRESS(2,COLUMN())),OFFSET($BN$2,0,0,ROW()-1,60),ROW()-1,FALSE)) -> 3195.54 | Y7: =IF(AND(ISNUMBER($Y$42),$B$31=1),$Y$42,HLOOKUP(INDIRECT(ADDRESS(2,COLUMN())),OFFSET($BN$2,0,0,ROW()-1,60),ROW()-1,FALSE)) -> 3182.435 | Z7: =IF(AND(ISNUMBER($Z$42),$B$31=1),$Z$42,HLOOKUP(INDIRECT(ADDRESS(2,COLUMN())),OFFSET($BN$2,0,0,ROW()-1,60),ROW()-1,FALSE)) -> 3209.423 | AA7: =IF(AND(ISNUMBER($AA$42),$B$31=1),$AA$42,HLOOKUP(INDIRECT(ADDRESS(2,COLUMN())),OFFSET($BN$2,0,0,ROW()-1,60),ROW()-1,FALSE)) -> 3136.014 | AB7: =IF(AND(ISNUMBER($AB$42),$B$31=1),$AB$42,HLOOKUP(INDIRECT(ADDRESS(2,COLUMN())),OFFSET($BN$2,0,0,ROW()-1,60),ROW()-1,FALSE)) -> 3080.936 | AC7: =IF(AND(ISNUMBER($AC$42),$B$31=1),$AC$42,HLOOKUP(INDIRECT(ADDRESS(2,COLUMN())),OFFSET($BN$2,0,0,ROW()-1,60),ROW()-1,FALSE)) -> 3034.139 | AD7: =IF(AND(ISNUMBER($AD$42),$B$31=1),$AD$42,HLOOKUP(INDIRECT(ADDRESS(2,COLUMN())),OFFSET($BN$2,0,0,ROW()-1,60),ROW()-1,FALSE)) -> 2994.223 | AE7: =IF(AND(ISNUMBER($AE$42),$B$31=1),$AE$42,HLOOKUP(INDIRECT(ADDRESS(2,COLUMN())),OFFSET($BN$2,0,0,ROW()-1,60),ROW()-1,FALSE)) -> 2938.925 | AF7: =IF(AND(ISNUMBER($AF$42),$B$31=1),$AF$42,HLOOKUP(INDIRECT(ADDRESS(2,COLUMN())),OFFSET($BN$2,0,0,ROW()-1,60),ROW()-1,FALSE)) -> 2912.96 | AG7: =IF(AND(ISNUMBER($AG$42),$B$31=1),$AG$42,HLOOKUP(INDIRECT(ADDRESS(2,COLUMN())),OFFSET($BN$2,0,0,ROW()-1,60),ROW()-1,FALSE)) -> 2885.521 | AH7: =IF(AND(ISNUMBER($AH$42),$B$31=1),$AH$42,HLOOKUP(INDIRECT(ADDRESS(2,COLUMN())),OFFSET($BN$2,0,0,ROW()-1,60),ROW()-1,FALSE)) -> 2839.147 | AI7: =IF(AND(ISNUMBER($AI$42),$B$31=1),$AI$42,HLOOKUP(INDIRECT(ADDRESS(2,COLUMN())),OFFSET($BN$2,0,0,ROW()-1,60),ROW()-1,FALSE)) -> 2801.299 | AJ7: =IF(AND(ISNUMBER($AJ$42),$B$31=1),$AJ$42,HLOOKUP(INDIRECT(ADDRESS(2,COLUMN())),OFFSET($BN$2,0,0,ROW()-1,60),ROW()-1,FALSE)) -> 2761.375 | AK7: =IF(AND(ISNUMBER($AK$42),$B$31=1),$AK$42,HLOOKUP(INDIRECT(ADDRESS(2,COLUMN())),OFFSET($BN$2,0,0,ROW()-1,60),ROW()-1,FALSE)) -> 2715.851 | AL7: =IF(AND(ISNUMBER($AL$42),$B$31=1),$AL$42,HLOOKUP(INDIRECT(ADDRESS(2,COLUMN())),OFFSET($BN$2,0,0,ROW()-1,60),ROW()-1,FALSE)) -> 2695.724 | AM7: =IF(AND(ISNUMBER($AM$42),$B$31=1),$AM$42,HLOOKUP(INDIRECT(ADDRESS(2,COLUMN())),OFFSET($BN$2,0,0,ROW()-1,60),ROW()-1,FALSE)) -> 2689.905 | AN7: =IF(AND(ISNUMBER($AN$42),$B$31=1),$AN$42,HLOOKUP(INDIRECT(ADDRESS(2,COLUMN())),OFFSET($BN$2,0,0,ROW()-1,60),ROW()-1,FALSE)) -> 2680.996 | AO7: =IF(AND(ISNUMBER($AO$42),$B$31=1),$AO$42,HLOOKUP(INDIRECT(ADDRESS(2,COLUMN())),OFFSET($BN$2,0,0,ROW()-1,60),ROW()-1,FALSE)) -> 2668.281 | AP7: =IF(AND(ISNUMBER($AP$42),$B$31=1),$AP$42,HLOOKUP(INDIRECT(ADDRESS(2,COLUMN())),OFFSET($BN$2,0,0,ROW()-1,60),ROW()-1,FALSE)) -> 2642.923 | AQ7: =IF(AND(ISNUMBER($AQ$42),$B$31=1),$AQ$42,HLOOKUP(INDIRECT(ADDRESS(2,COLUMN())),OFFSET($BN$2,0,0,ROW()-1,60),ROW()-1,FALSE)) -> 2621.296 | AR7: =IF(AND(ISNUMBER($AR$42),$B$31=1),$AR$42,HLOOKUP(INDIRECT(ADDRESS(2,COLUMN())),OFFSET($BN$2,0,0,ROW()-1,60),ROW()-1,FALSE)) -> 2624.356 | AS7: =IF(AND(ISNUMBER($AS$42),$B$31=1),$AS$42,HLOOKUP(INDIRECT(ADDRESS(2,COLUMN())),OFFSET($BN$2,0,0,ROW()-1,60),ROW()-1,FALSE)) -> 2615.896 | AT7: =IF(AND(ISNUMBER($AT$42),$B$31=1),$AT$42,HLOOKUP(INDIRECT(ADDRESS(2,COLUMN())),OFFSET($BN$2,0,0,ROW()-1,60),ROW()-1,FALSE)) -> 2601.375 | AU7: =IF(AND(ISNUMBER($AU$42),$B$31=1),$AU$42,HLOOKUP(INDIRECT(ADDRESS(2,COLUMN())),OFFSET($BN$2,0,0,ROW()-1,60),ROW()-1,FALSE)) -> 2574.327 | AV7: =IF(AND(ISNUMBER($AV$42),$B$31=1),$AV$42,HLOOKUP(INDIRECT(ADDRESS(2,COLUMN())),OFFSET($BN$2,0,0,ROW()-1,60),ROW()-1,FALSE)) -> 2571.889 | AW7: =IF(AND(ISNUMBER($AW$42),$B$31=1),$AW$42,HLOOKUP(INDIRECT(ADDRESS(2,COLUMN())),OFFSET($BN$2,0,0,ROW()-1,60),ROW()-1,FALSE)) -> 2581.399 | AX7: =IF(AND(ISNUMBER($AX$42),$B$31=1),$AX$42,HLOOKUP(INDIRECT(ADDRESS(2,COLUMN())),OFFSET($BN$2,0,0,ROW()-1,60),ROW()-1,FALSE)) -> 2548.426 | AY7: =IF(AND(ISNUMBER($AY$42),$B$31=1),$AY$42,HLOOKUP(INDIRECT(ADDRESS(2,COLUMN())),OFFSET($BN$2,0,0,ROW()-1,60),ROW()-1,FALSE)) -> 2547.392 | AZ7: =IF(AND(ISNUMBER($AZ$42),$B$31=1),$AZ$42,HLOOKUP(INDIRECT(ADDRESS(2,COLUMN())),OFFSET($BN$2,0,0,ROW()-1,60),ROW()-1,FALSE)) -> 2536.463 | BA7: =IF(AND(ISNUMBER($BA$42),$B$31=1),$BA$42,HLOOKUP(INDIRECT(ADDRESS(2,COLUMN())),OFFSET($BN$2,0,0,ROW()-1,60),ROW()-1,FALSE)) -> 2530.734 | BB7: =IF(AND(ISNUMBER($BB$42),$B$31=1),$BB$42,HLOOKUP(INDIRECT(ADDRESS(2,COLUMN())),OFFSET($BN$2,0,0,ROW()-1,60),ROW()-1,FALSE)) -> 2531.613 | BC7: =IF(AND(ISNUMBER($BC$42),$B$31=1),$BC$42,HLOOKUP(INDIRECT(ADDRESS(2,COLUMN())),OFFSET($BN$2,0,0,ROW()-1,60),ROW()-1,FALSE)) -> 2524.169 | BD7: =IF(AND(ISNUMBER($BD$42),$B$31=1),$BD$42,HLOOKUP(INDIRECT(ADDRESS(2,COLUMN())),OFFSET($BN$2,0,0,ROW()-1,60),ROW()-1,FALSE)) -> 2521.55 | BE7: =IF(AND(ISNUMBER($BE$42),$B$31=1),$BE$42,HLOOKUP(INDIRECT(ADDRESS(2,COLUMN())),OFFSET($BN$2,0,0,ROW()-1,60),ROW()-1,FALSE)) -> 2519.684 | BF7: =IF(AND(ISNUMBER($BF$42),$B$31=1),$BF$42,HLOOKUP(INDIRECT(ADDRESS(2,COLUMN())),OFFSET($BN$2,0,0,ROW()-1,60),ROW()-1,FALSE)) -> 2503.34 | BG7: =IF(AND(ISNUMBER($BG$42),$B$31=1),$BG$42,HLOOKUP(INDIRECT(ADDRESS(2,COLUMN())),OFFSET($BN$2,0,0,ROW()-1,60),ROW()-1,FALSE)) -> 2517.184 | BH7: =IF(AND(ISNUMBER($BH$42),$B$31=1),$BH$42,HLOOKUP(INDIRECT(ADDRESS(2,COLUMN())),OFFSET($BN$2,0,0,ROW()-1,60),ROW()-1,FALSE)) -> 2495.035 | BI7: =IF(AND(ISNUMBER($BI$42),$B$31=1),$BI$42,HLOOKUP(INDIRECT(ADDRESS(2,COLUMN())),OFFSET($BN$2,0,0,ROW()-1,60),ROW()-1,FALSE)) -> 2501.81 | BJ7: =IF(AND(ISNUMBER($BJ$42),$B$31=1),$BJ$42,HLOOKUP(INDIRECT(ADDRESS(2,COLUMN())),OFFSET($BN$2,0,0,ROW()-1,60),ROW()-1,FALSE)) -> 2531.982 | BK7: =IF(AND(ISNUMBER($BK$42),$B$31=1),$BK$42,HLOOKUP(INDIRECT(ADDRESS(2,COLUMN())),OFFSET($BN$2,0,0,ROW()-1,60),ROW()-1,FALSE)) -> 2516.417 | BL7: =IF(AND(ISNUMBER($BL$42),$B$31=1),$BL$42,HLOOKUP(INDIRECT(ADDRESS(2,COLUMN())),OFFSET($BN$2,0,0,ROW()-1,60),ROW()-1,FALSE)) -> 2516.921 | BM7: =IF(AND(ISNUMBER($BM$42),$B$31=1),$BM$42,HLOOKUP(INDIRECT(ADDRESS(2,COLUMN())),OFFSET($BN$2,0,0,ROW()-1,60),ROW()-1,FALSE)) -> 2508.885 | BN7: =4054.615 -> 4054.615 | BO7: =4030.962 -> 4030.962 | BP7: =3996.878 -> 3996.878 | BQ7: =3947.656 -> 3947.656 | BR7: =3882.139 -> 3882.139 | BS7: =3840.088 -> 3840.088 | BT7: =3781.725 -> 3781.725 | BU7: =3758.931 -> 3758.931 | BV7: =3674.318 -> 3674.318 | BW7: =3680.844 -> 3680.844 | BX7: =3641.91 -> 3641.91 | BY7: =3590.272 -> 3590.272 | BZ7: =3560.032 -> 3560.032 | CA7: =3473.916 -> 3473.916 | CB7: =3440.748 -> 3440.748 | CC7: =3386.91 -> 3386.91 | CD7: =3348.272 -> 3348.272 | CE7: =3325.207 -> 3325.207 | CF7: =3195.54 -> 3195.54 | CG7: =3182.435 -> 3182.435 | CH7: =3209.423 -> 3209.423 | CI7: =3136.014 -> 3136.014 | CJ7: =3080.936 -> 3080.936 | CK7: =3034.139 -> 3034.139 | CL7: =2994.223 -> 2994.223 | CM7: =2938.925 -> 2938.925 | CN7: =2912.96 -> 2912.96 | CO7: =2885.521 -> 2885.521 | CP7: =2839.147 -> 2839.147 | CQ7: =2801.299 -> 2801.299 | CR7: =2761.375 -> 2761.375 | CS7: =2715.851 -> 2715.851 | CT7: =2695.724 -> 2695.724 | CU7: =2689.905 -> 2689.905 | CV7: =2680.996 -> 2680.996 | CW7: =2668.281 -> 2668.281 | CX7: =2642.923 -> 2642.923 | CY7: =2621.296 -> 2621.296 | CZ7: =2624.356 -> 2624.356 | DA7: =2615.896 -> 2615.896 | DB7: =2601.375 -> 2601.375 | DC7: =2574.327 -> 2574.327 | DD7: =2571.889 -> 2571.889 | DE7: =2581.399 -> 2581.399 | DF7: =2548.426 -> 2548.426 | DG7: =2547.392 -> 2547.392 | DH7: =2536.463 -> 2536.463 | DI7: =2530.734 -> 2530.734 | DJ7: =2531.613 -> 2531.613 | DK7: =2524.169 -> 2524.169 | DL7: =2521.55 -> 2521.55 | DM7: =2519.684 -> 2519.684 | DN7: =2503.34 -> 2503.34 | DO7: =2517.184 -> 2517.184 | DP7: =2495.035 -> 2495.035 | DQ7: =2501.81 -> 2501.81 | DR7: =2531.982 -> 2531.982 | DS7: =2516.417 -> 2516.417 | DT7: =2516.921 -> 2516.921 | DU7: =2508.885 -> 2508.885
A8: =" Government: Gross Investment" -> Government: Gross Investment | B8: ="GCEXGRSS Index" -> GCEXGRSS Index | C8: ="PR005" -> PR005 | D8: ="PX_LAST" -> PX_LAST | E8: ="Dynamic" -> Dynamic | F8: =IF(AND(ISNUMBER($F$43),$B$31=1),$F$43,HLOOKUP(INDIRECT(ADDRESS(2,COLUMN())),OFFSET($BN$2,0,0,ROW()-1,60),ROW()-1,FALSE)) -> 1135.041 | G8: =IF(AND(ISNUMBER($G$43),$B$31=1),$G$43,HLOOKUP(INDIRECT(ADDRESS(2,COLUMN())),OFFSET($BN$2,0,0,ROW()-1,60),ROW()-1,FALSE)) -> 1118.93 | H8: =IF(AND(ISNUMBER($H$43),$B$31=1),$H$43,HLOOKUP(INDIRECT(ADDRESS(2,COLUMN())),OFFSET($BN$2,0,0,ROW()-1,60),ROW()-1,FALSE)) -> 1102.851 | I8: =IF(AND(ISNUMBER($I$43),$B$31=1),$I$43,HLOOKUP(INDIRECT(ADDRESS(2,COLUMN())),OFFSET($BN$2,0,0,ROW()-1,60),ROW()-1,FALSE)) -> 1087.352 | J8: =IF(AND(ISNUMBER($J$43),$B$31=1),$J$43,HLOOKUP(INDIRECT(ADDRESS(2,COLUMN())),OFFSET($BN$2,0,0,ROW()-1,60),ROW()-1,FALSE)) -> 1060.902 | K8: =IF(AND(ISNUMBER($K$43),$B$31=1),$K$43,HLOOKUP(INDIRECT(ADDRESS(2,COLUMN())),OFFSET($BN$2,0,0,ROW()-1,60),ROW()-1,FALSE)) -> 1040.872 | L8: =IF(AND(ISNUMBER($L$43),$B$31=1),$L$43,HLOOKUP(INDIRECT(ADDRESS(2,COLUMN())),OFFSET($BN$2,0,0,ROW()-1,60),ROW()-1,FALSE)) -> 1033.426 | M8: =IF(AND(ISNUMBER($M$43),$B$31=1),$M$43,HLOOKUP(INDIRECT(ADDRESS(2,COLUMN())),OFFSET($BN$2,0,0,ROW()-1,60),ROW()-1,FALSE)) -> 997.517 | N8: =IF(AND(ISNUMBER($N$43),$B$31=1),$N$43,HLOOKUP(INDIRECT(ADDRESS(2,COLUMN())),OFFSET($BN$2,0,0,ROW()-1,60),ROW()-1,FALSE)) -> 971.587 | O8: =IF(AND(ISNUMBER($O$43),$B$31=1),$O$43,HLOOKUP(INDIRECT(ADDRESS(2,COLUMN())),OFFSET($BN$2,0,0,ROW()-1,60),ROW()-1,FALSE)) -> 943.742 | P8: =IF(AND(ISNUMBER($P$43),$B$31=1),$P$43,HLOOKUP(INDIRECT(ADDRESS(2,COLUMN())),OFFSET($BN$2,0,0,ROW()-1,60),ROW()-1,FALSE)) -> 922.882 | Q8: =IF(AND(ISNUMBER($Q$43),$B$31=1),$Q$43,HLOOKUP(INDIRECT(ADDRESS(2,COLUMN())),OFFSET($BN$2,0,0,ROW()-1,60),ROW()-1,FALSE)) -> 889.778 | R8: =IF(AND(ISNUMBER($R$43),$B$31=1),$R$43,HLOOKUP(INDIRECT(ADDRESS(2,COLUMN())),OFFSET($BN$2,0,0,ROW()-1,60),ROW()-1,FALSE)) -> 877.577 | S8: =IF(AND(ISNUMBER($S$43),$B$31=1),$S$43,HLOOKUP(INDIRECT(ADDRESS(2,COLUMN())),OFFSET($BN$2,0,0,ROW()-1,60),ROW()-1,FALSE)) -> 858.694 | T8: =IF(AND(ISNUMBER($T$43),$B$31=1),$T$43,HLOOKUP(INDIRECT(ADDRESS(2,COLUMN())),OFFSET($BN$2,0,0,ROW()-1,60),ROW()-1,FALSE)) -> 841.57 | U8: =IF(AND(ISNUMBER($U$43),$B$31=1),$U$43,HLOOKUP(INDIRECT(ADDRESS(2,COLUMN())),OFFSET($BN$2,0,0,ROW()-1,60),ROW()-1,FALSE)) -> 827.06 | V8: =IF(AND(ISNUMBER($V$43),$B$31=1),$V$43,HLOOKUP(INDIRECT(ADDRESS(2,COLUMN())),OFFSET($BN$2,0,0,ROW()-1,60),ROW()-1,FALSE)) -> 821.744 | W8: =IF(AND(ISNUMBER($W$43),$B$31=1),$W$43,HLOOKUP(INDIRECT(ADDRESS(2,COLUMN())),OFFSET($BN$2,0,0,ROW()-1,60),ROW()-1,FALSE)) -> 822.419 | X8: =IF(AND(ISNUMBER($X$43),$B$31=1),$X$43,HLOOKUP(INDIRECT(ADDRESS(2,COLUMN())),OFFSET($BN$2,0,0,ROW()-1,60),ROW()-1,FALSE)) -> 832.455 | Y8: =IF(AND(ISNUMBER($Y$43),$B$31=1),$Y$43,HLOOKUP(INDIRECT(ADDRESS(2,COLUMN())),OFFSET($BN$2,0,0,ROW()-1,60),ROW()-1,FALSE)) -> 819.135 | Z8: =IF(AND(ISNUMBER($Z$43),$B$31=1),$Z$43,HLOOKUP(INDIRECT(ADDRESS(2,COLUMN())),OFFSET($BN$2,0,0,ROW()-1,60),ROW()-1,FALSE)) -> 816.551 | AA8: =IF(AND(ISNUMBER($AA$43),$B$31=1),$AA$43,HLOOKUP(INDIRECT(ADDRESS(2,COLUMN())),OFFSET($BN$2,0,0,ROW()-1,60),ROW()-1,FALSE)) -> 806.998 | AB8: =IF(AND(ISNUMBER($AB$43),$B$31=1),$AB$43,HLOOKUP(INDIRECT(ADDRESS(2,COLUMN())),OFFSET($BN$2,0,0,ROW()-1,60),ROW()-1,FALSE)) -> 784.032 | AC8: =IF(AND(ISNUMBER($AC$43),$B$31=1),$AC$43,HLOOKUP(INDIRECT(ADDRESS(2,COLUMN())),OFFSET($BN$2,0,0,ROW()-1,60),ROW()-1,FALSE)) -> 780.698 | AD8: =IF(AND(ISNUMBER($AD$43),$B$31=1),$AD$43,HLOOKUP(INDIRECT(ADDRESS(2,COLUMN())),OFFSET($BN$2,0,0,ROW()-1,60),ROW()-1,FALSE)) -> 767.02 | AE8: =IF(AND(ISNUMBER($AE$43),$B$31=1),$AE$43,HLOOKUP(INDIRECT(ADDRESS(2,COLUMN())),OFFSET($BN$2,0,0,ROW()-1,60),ROW()-1,FALSE)) -> 764.009 | AF8: =IF(AND(ISNUMBER($AF$43),$B$31=1),$AF$43,HLOOKUP(INDIRECT(ADDRESS(2,COLUMN())),OFFSET($BN$2,0,0,ROW()-1,60),ROW()-1,FALSE)) -> 737.888 | AG8: =IF(AND(ISNUMBER($AG$43),$B$31=1),$AG$43,HLOOKUP(INDIRECT(ADDRESS(2,COLUMN())),OFFSET($BN$2,0,0,ROW()-1,60),ROW()-1,FALSE)) -> 740.565 | AH8: =IF(AND(ISNUMBER($AH$43),$B$31=1),$AH$43,HLOOKUP(INDIRECT(ADDRESS(2,COLUMN())),OFFSET($BN$2,0,0,ROW()-1,60),ROW()-1,FALSE)) -> 731.567 | AI8: =IF(AND(ISNUMBER($AI$43),$B$31=1),$AI$43,HLOOKUP(INDIRECT(ADDRESS(2,COLUMN())),OFFSET($BN$2,0,0,ROW()-1,60),ROW()-1,FALSE)) -> 712.577 | AJ8: =IF(AND(ISNUMBER($AJ$43),$B$31=1),$AJ$43,HLOOKUP(INDIRECT(ADDRESS(2,COLUMN())),OFFSET($BN$2,0,0,ROW()-1,60),ROW()-1,FALSE)) -> 704.762 | AK8: =IF(AND(ISNUMBER($AK$43),$B$31=1),$AK$43,HLOOKUP(INDIRECT(ADDRESS(2,COLUMN())),OFFSET($BN$2,0,0,ROW()-1,60),ROW()-1,FALSE)) -> 683.035 | AL8: =IF(AND(ISNUMBER($AL$43),$B$31=1),$AL$43,HLOOKUP(INDIRECT(ADDRESS(2,COLUMN())),OFFSET($BN$2,0,0,ROW()-1,60),ROW()-1,FALSE)) -> 674.72 | AM8: =IF(AND(ISNUMBER($AM$43),$B$31=1),$AM$43,HLOOKUP(INDIRECT(ADDRESS(2,COLUMN())),OFFSET($BN$2,0,0,ROW()-1,60),ROW()-1,FALSE)) -> 663.191 | AN8: =IF(AND(ISNUMBER($AN$43),$B$31=1),$AN$43,HLOOKUP(INDIRECT(ADDRESS(2,COLUMN())),OFFSET($BN$2,0,0,ROW()-1,60),ROW()-1,FALSE)) -> 656.249 | AO8: =IF(AND(ISNUMBER($AO$43),$B$31=1),$AO$43,HLOOKUP(INDIRECT(ADDRESS(2,COLUMN())),OFFSET($BN$2,0,0,ROW()-1,60),ROW()-1,FALSE)) -> 646.89 | AP8: =IF(AND(ISNUMBER($AP$43),$B$31=1),$AP$43,HLOOKUP(INDIRECT(ADDRESS(2,COLUMN())),OFFSET($BN$2,0,0,ROW()-1,60),ROW()-1,FALSE)) -> 646.644 | AQ8: =IF(AND(ISNUMBER($AQ$43),$B$31=1),$AQ$43,HLOOKUP(INDIRECT(ADDRESS(2,COLUMN())),OFFSET($BN$2,0,0,ROW()-1,60),ROW()-1,FALSE)) -> 648.845 | AR8: =IF(AND(ISNUMBER($AR$43),$B$31=1),$AR$43,HLOOKUP(INDIRECT(ADDRESS(2,COLUMN())),OFFSET($BN$2,0,0,ROW()-1,60),ROW()-1,FALSE)) -> 633.787 | AS8: =IF(AND(ISNUMBER($AS$43),$B$31=1),$AS$43,HLOOKUP(INDIRECT(ADDRESS(2,COLUMN())),OFFSET($BN$2,0,0,ROW()-1,60),ROW()-1,FALSE)) -> 637.658 | AT8: =IF(AND(ISNUMBER($AT$43),$B$31=1),$AT$43,HLOOKUP(INDIRECT(ADDRESS(2,COLUMN())),OFFSET($BN$2,0,0,ROW()-1,60),ROW()-1,FALSE)) -> 632.692 | AU8: =IF(AND(ISNUMBER($AU$43),$B$31=1),$AU$43,HLOOKUP(INDIRECT(ADDRESS(2,COLUMN())),OFFSET($BN$2,0,0,ROW()-1,60),ROW()-1,FALSE)) -> 613.588 | AV8: =IF(AND(ISNUMBER($AV$43),$B$31=1),$AV$43,HLOOKUP(INDIRECT(ADDRESS(2,COLUMN())),OFFSET($BN$2,0,0,ROW()-1,60),ROW()-1,FALSE)) -> 617.364 | AW8: =IF(AND(ISNUMBER($AW$43),$B$31=1),$AW$43,HLOOKUP(INDIRECT(ADDRESS(2,COLUMN())),OFFSET($BN$2,0,0,ROW()-1,60),ROW()-1,FALSE)) -> 610.35 | AX8: =IF(AND(ISNUMBER($AX$43),$B$31=1),$AX$43,HLOOKUP(INDIRECT(ADDRESS(2,COLUMN())),OFFSET($BN$2,0,0,ROW()-1,60),ROW()-1,FALSE)) -> 605.94 | AY8: =IF(AND(ISNUMBER($AY$43),$B$31=1),$AY$43,HLOOKUP(INDIRECT(ADDRESS(2,COLUMN())),OFFSET($BN$2,0,0,ROW()-1,60),ROW()-1,FALSE)) -> 591.669 | AZ8: =IF(AND(ISNUMBER($AZ$43),$B$31=1),$AZ$43,HLOOKUP(INDIRECT(ADDRESS(2,COLUMN())),OFFSET($BN$2,0,0,ROW()-1,60),ROW()-1,FALSE)) -> 604.054 | BA8: =IF(AND(ISNUMBER($BA$43),$B$31=1),$BA$43,HLOOKUP(INDIRECT(ADDRESS(2,COLUMN())),OFFSET($BN$2,0,0,ROW()-1,60),ROW()-1,FALSE)) -> 604.458 | BB8: =IF(AND(ISNUMBER($BB$43),$B$31=1),$BB$43,HLOOKUP(INDIRECT(ADDRESS(2,COLUMN())),OFFSET($BN$2,0,0,ROW()-1,60),ROW()-1,FALSE)) -> 599.53 | BC8: =IF(AND(ISNUMBER($BC$43),$B$31=1),$BC$43,HLOOKUP(INDIRECT(ADDRESS(2,COLUMN())),OFFSET($BN$2,0,0,ROW()-1,60),ROW()-1,FALSE)) -> 599.285 | BD8: =IF(AND(ISNUMBER($BD$43),$B$31=1),$BD$43,HLOOKUP(INDIRECT(ADDRESS(2,COLUMN())),OFFSET($BN$2,0,0,ROW()-1,60),ROW()-1,FALSE)) -> 610.758 | BE8: =IF(AND(ISNUMBER($BE$43),$B$31=1),$BE$43,HLOOKUP(INDIRECT(ADDRESS(2,COLUMN())),OFFSET($BN$2,0,0,ROW()-1,60),ROW()-1,FALSE)) -> 619.428 | BF8: =IF(AND(ISNUMBER($BF$43),$B$31=1),$BF$43,HLOOKUP(INDIRECT(ADDRESS(2,COLUMN())),OFFSET($BN$2,0,0,ROW()-1,60),ROW()-1,FALSE)) -> 627.098 | BG8: =IF(AND(ISNUMBER($BG$43),$B$31=1),$BG$43,HLOOKUP(INDIRECT(ADDRESS(2,COLUMN())),OFFSET($BN$2,0,0,ROW()-1,60),ROW()-1,FALSE)) -> 626.841 | BH8: =IF(AND(ISNUMBER($BH$43),$B$31=1),$BH$43,HLOOKUP(INDIRECT(ADDRESS(2,COLUMN())),OFFSET($BN$2,0,0,ROW()-1,60),ROW()-1,FALSE)) -> 635.731 | BI8: =IF(AND(ISNUMBER($BI$43),$B$31=1),$BI$43,HLOOKUP(INDIRECT(ADDRESS(2,COLUMN())),OFFSET($BN$2,0,0,ROW()-1,60),ROW()-1,FALSE)) -> 635.112 | BJ8: =IF(AND(ISNUMBER($BJ$43),$B$31=1),$BJ$43,HLOOKUP(INDIRECT(ADDRESS(2,COLUMN())),OFFSET($BN$2,0,0,ROW()-1,60),ROW()-1,FALSE)) -> 636.279 | BK8: =IF(AND(ISNUMBER($BK$43),$B$31=1),$BK$43,HLOOKUP(INDIRECT(ADDRESS(2,COLUMN())),OFFSET($BN$2,0,0,ROW()-1,60),ROW()-1,FALSE)) -> 639.351 | BL8: =IF(AND(ISNUMBER($BL$43),$B$31=1),$BL$43,HLOOKUP(INDIRECT(ADDRESS(2,COLUMN())),OFFSET($BN$2,0,0,ROW()-1,60),ROW()-1,FALSE)) -> 647.396 | BM8: =IF(AND(ISNUMBER($BM$43),$B$31=1),$BM$43,HLOOKUP(INDIRECT(ADDRESS(2,COLUMN())),OFFSET($BN$2,0,0,ROW()-1,60),ROW()-1,FALSE)) -> 649.416 | BN8: =1135.041 -> 1135.041 | BO8: =1118.93 -> 1118.93 | BP8: =1102.851 -> 1102.851 | BQ8: =1087.352 -> 1087.352 | BR8: =1060.902 -> 1060.902 | BS8: =1040.872 -> 1040.872 | BT8: =1033.426 -> 1033.426 | BU8: =997.517 -> 997.517 | BV8: =971.587 -> 971.587 | BW8: =943.742 -> 943.742 | BX8: =922.882 -> 922.882 | BY8: =889.778 -> 889.778 | BZ8: =877.577 -> 877.577 | CA8: =858.694 -> 858.694 | CB8: =841.57 -> 841.57 | CC8: =827.06 -> 827.06 | CD8: =821.744 -> 821.744 | CE8: =822.419 -> 822.419 | CF8: =832.455 -> 832.455 | CG8: =819.135 -> 819.135 | CH8: =816.551 -> 816.551 | CI8: =806.998 -> 806.998 | CJ8: =784.032 -> 784.032 | CK8: =780.698 -> 780.698 | CL8: =767.02 -> 767.02 | CM8: =764.009 -> 764.009 | CN8: =737.888 -> 737.888 | CO8: =740.565 -> 740.565 | CP8: =731.567 -> 731.567 | CQ8: =712.577 -> 712.577 | CR8: =704.762 -> 704.762 | CS8: =683.035 -> 683.035 | CT8: =674.72 -> 674.72 | CU8: =663.191 -> 663.191 | CV8: =656.249 -> 656.249 | CW8: =646.89 -> 646.89 | CX8: =646.644 -> 646.644 | CY8: =648.845 -> 648.845 | CZ8: =633.787 -> 633.787 | DA8: =637.658 -> 637.658 | DB8: =632.692 -> 632.692 | DC8: =613.588 -> 613.588 | DD8: =617.364 -> 617.364 | DE8: =610.35 -> 610.35 | DF8: =605.94 -> 605.94 | DG8: =591.669 -> 591.669 | DH8: =604.054 -> 604.054 | DI8: =604.458 -> 604.458 | DJ8: =599.53 -> 599.53 | DK8: =599.285 -> 599.285 | DL8: =610.758 -> 610.758 | DM8: =619.428 -> 619.428 | DN8: =627.098 -> 627.098 | DO8: =626.841 -> 626.841 | DP8: =635.731 -> 635.731 | DQ8: =635.112 -> 635.112 | DR8: =636.279 -> 636.279 | DS8: =639.351 -> 639.351 | DT8: =647.396 -> 647.396 | DU8: =649.416 -> 649.416
A9: =" Exports" -> Exports | B9: ="GDP$EXP Index" -> GDP$EXP Index | C9: ="PR005" -> PR005 | D9: ="PX_LAST" -> PX_LAST | E9: ="Dynamic" -> Dynamic | F9: =IF(AND(ISNUMBER($F$44),$B$31=1),$F$44,HLOOKUP(INDIRECT(ADDRESS(2,COLUMN())),OFFSET($BN$2,0,0,ROW()-1,60),ROW()-1,FALSE)) -> 3241.946 | G9: =IF(AND(ISNUMBER($G$44),$B$31=1),$G$44,HLOOKUP(INDIRECT(ADDRESS(2,COLUMN())),OFFSET($BN$2,0,0,ROW()-1,60),ROW()-1,FALSE)) -> 3266.413 | H9: =IF(AND(ISNUMBER($H$44),$B$31=1),$H$44,HLOOKUP(INDIRECT(ADDRESS(2,COLUMN())),OFFSET($BN$2,0,0,ROW()-1,60),ROW()-1,FALSE)) -> 3220.929 | I9: =IF(AND(ISNUMBER($I$44),$B$31=1),$I$44,HLOOKUP(INDIRECT(ADDRESS(2,COLUMN())),OFFSET($BN$2,0,0,ROW()-1,60),ROW()-1,FALSE)) -> 3220.292 | J9: =IF(AND(ISNUMBER($J$44),$B$31=1),$J$44,HLOOKUP(INDIRECT(ADDRESS(2,COLUMN())),OFFSET($BN$2,0,0,ROW()-1,60),ROW()-1,FALSE)) -> 3154.321 | K9: =IF(AND(ISNUMBER($K$44),$B$31=1),$K$44,HLOOKUP(INDIRECT(ADDRESS(2,COLUMN())),OFFSET($BN$2,0,0,ROW()-1,60),ROW()-1,FALSE)) -> 3125.421 | L9: =IF(AND(ISNUMBER($L$44),$B$31=1),$L$44,HLOOKUP(INDIRECT(ADDRESS(2,COLUMN())),OFFSET($BN$2,0,0,ROW()-1,60),ROW()-1,FALSE)) -> 3091.748 | M9: =IF(AND(ISNUMBER($M$44),$B$31=1),$M$44,HLOOKUP(INDIRECT(ADDRESS(2,COLUMN())),OFFSET($BN$2,0,0,ROW()-1,60),ROW()-1,FALSE)) -> 3062.041 | N9: =IF(AND(ISNUMBER($N$44),$B$31=1),$N$44,HLOOKUP(INDIRECT(ADDRESS(2,COLUMN())),OFFSET($BN$2,0,0,ROW()-1,60),ROW()-1,FALSE)) -> 2995.524 | O9: =IF(AND(ISNUMBER($O$44),$B$31=1),$O$44,HLOOKUP(INDIRECT(ADDRESS(2,COLUMN())),OFFSET($BN$2,0,0,ROW()-1,60),ROW()-1,FALSE)) -> 3060.562 | P9: =IF(AND(ISNUMBER($P$44),$B$31=1),$P$44,HLOOKUP(INDIRECT(ADDRESS(2,COLUMN())),OFFSET($BN$2,0,0,ROW()-1,60),ROW()-1,FALSE)) -> 3046.718 | Q9: =IF(AND(ISNUMBER($Q$44),$B$31=1),$Q$44,HLOOKUP(INDIRECT(ADDRESS(2,COLUMN())),OFFSET($BN$2,0,0,ROW()-1,60),ROW()-1,FALSE)) -> 3102.55 | R9: =IF(AND(ISNUMBER($R$44),$B$31=1),$R$44,HLOOKUP(INDIRECT(ADDRESS(2,COLUMN())),OFFSET($BN$2,0,0,ROW()-1,60),ROW()-1,FALSE)) -> 3071.551 | S9: =IF(AND(ISNUMBER($S$44),$B$31=1),$S$44,HLOOKUP(INDIRECT(ADDRESS(2,COLUMN())),OFFSET($BN$2,0,0,ROW()-1,60),ROW()-1,FALSE)) -> 2848.698 | T9: =IF(AND(ISNUMBER($T$44),$B$31=1),$T$44,HLOOKUP(INDIRECT(ADDRESS(2,COLUMN())),OFFSET($BN$2,0,0,ROW()-1,60),ROW()-1,FALSE)) -> 2765.36 | U9: =IF(AND(ISNUMBER($U$44),$B$31=1),$U$44,HLOOKUP(INDIRECT(ADDRESS(2,COLUMN())),OFFSET($BN$2,0,0,ROW()-1,60),ROW()-1,FALSE)) -> 2570.103 | V9: =IF(AND(ISNUMBER($V$44),$B$31=1),$V$44,HLOOKUP(INDIRECT(ADDRESS(2,COLUMN())),OFFSET($BN$2,0,0,ROW()-1,60),ROW()-1,FALSE)) -> 2505.032 | W9: =IF(AND(ISNUMBER($W$44),$B$31=1),$W$44,HLOOKUP(INDIRECT(ADDRESS(2,COLUMN())),OFFSET($BN$2,0,0,ROW()-1,60),ROW()-1,FALSE)) -> 2381.224 | X9: =IF(AND(ISNUMBER($X$44),$B$31=1),$X$44,HLOOKUP(INDIRECT(ADDRESS(2,COLUMN())),OFFSET($BN$2,0,0,ROW()-1,60),ROW()-1,FALSE)) -> 2268.891 | Y9: =IF(AND(ISNUMBER($Y$44),$B$31=1),$Y$44,HLOOKUP(INDIRECT(ADDRESS(2,COLUMN())),OFFSET($BN$2,0,0,ROW()-1,60),ROW()-1,FALSE)) -> 2105.083 | Z9: =IF(AND(ISNUMBER($Z$44),$B$31=1),$Z$44,HLOOKUP(INDIRECT(ADDRESS(2,COLUMN())),OFFSET($BN$2,0,0,ROW()-1,60),ROW()-1,FALSE)) -> 1814.401 | AA9: =IF(AND(ISNUMBER($AA$44),$B$31=1),$AA$44,HLOOKUP(INDIRECT(ADDRESS(2,COLUMN())),OFFSET($BN$2,0,0,ROW()-1,60),ROW()-1,FALSE)) -> 2416.181 | AB9: =IF(AND(ISNUMBER($AB$44),$B$31=1),$AB$44,HLOOKUP(INDIRECT(ADDRESS(2,COLUMN())),OFFSET($BN$2,0,0,ROW()-1,60),ROW()-1,FALSE)) -> 2537.466 | AC9: =IF(AND(ISNUMBER($AC$44),$B$31=1),$AC$44,HLOOKUP(INDIRECT(ADDRESS(2,COLUMN())),OFFSET($BN$2,0,0,ROW()-1,60),ROW()-1,FALSE)) -> 2532.405 | AD9: =IF(AND(ISNUMBER($AD$44),$B$31=1),$AD$44,HLOOKUP(INDIRECT(ADDRESS(2,COLUMN())),OFFSET($BN$2,0,0,ROW()-1,60),ROW()-1,FALSE)) -> 2547.448 | AE9: =IF(AND(ISNUMBER($AE$44),$B$31=1),$AE$44,HLOOKUP(INDIRECT(ADDRESS(2,COLUMN())),OFFSET($BN$2,0,0,ROW()-1,60),ROW()-1,FALSE)) -> 2540.244 | AF9: =IF(AND(ISNUMBER($AF$44),$B$31=1),$AF$44,HLOOKUP(INDIRECT(ADDRESS(2,COLUMN())),OFFSET($BN$2,0,0,ROW()-1,60),ROW()-1,FALSE)) -> 2537.415 | AG9: =IF(AND(ISNUMBER($AG$44),$B$31=1),$AG$44,HLOOKUP(INDIRECT(ADDRESS(2,COLUMN())),OFFSET($BN$2,0,0,ROW()-1,60),ROW()-1,FALSE)) -> 2535.501 | AH9: =IF(AND(ISNUMBER($AH$44),$B$31=1),$AH$44,HLOOKUP(INDIRECT(ADDRESS(2,COLUMN())),OFFSET($BN$2,0,0,ROW()-1,60),ROW()-1,FALSE)) -> 2562.172 | AI9: =IF(AND(ISNUMBER($AI$44),$B$31=1),$AI$44,HLOOKUP(INDIRECT(ADDRESS(2,COLUMN())),OFFSET($BN$2,0,0,ROW()-1,60),ROW()-1,FALSE)) -> 2517.268 | AJ9: =IF(AND(ISNUMBER($AJ$44),$B$31=1),$AJ$44,HLOOKUP(INDIRECT(ADDRESS(2,COLUMN())),OFFSET($BN$2,0,0,ROW()-1,60),ROW()-1,FALSE)) -> 2479.107 | AK9: =IF(AND(ISNUMBER($AK$44),$B$31=1),$AK$44,HLOOKUP(INDIRECT(ADDRESS(2,COLUMN())),OFFSET($BN$2,0,0,ROW()-1,60),ROW()-1,FALSE)) -> 2384.524 | AL9: =IF(AND(ISNUMBER($AL$44),$B$31=1),$AL$44,HLOOKUP(INDIRECT(ADDRESS(2,COLUMN())),OFFSET($BN$2,0,0,ROW()-1,60),ROW()-1,FALSE)) -> 2349.681 | AM9: =IF(AND(ISNUMBER($AM$44),$B$31=1),$AM$44,HLOOKUP(INDIRECT(ADDRESS(2,COLUMN())),OFFSET($BN$2,0,0,ROW()-1,60),ROW()-1,FALSE)) -> 2339.728 | AN9: =IF(AND(ISNUMBER($AN$44),$B$31=1),$AN$44,HLOOKUP(INDIRECT(ADDRESS(2,COLUMN())),OFFSET($BN$2,0,0,ROW()-1,60),ROW()-1,FALSE)) -> 2268.339 | AO9: =IF(AND(ISNUMBER($AO$44),$B$31=1),$AO$44,HLOOKUP(INDIRECT(ADDRESS(2,COLUMN())),OFFSET($BN$2,0,0,ROW()-1,60),ROW()-1,FALSE)) -> 2270 | AP9: =IF(AND(ISNUMBER($AP$44),$B$31=1),$AP$44,HLOOKUP(INDIRECT(ADDRESS(2,COLUMN())),OFFSET($BN$2,0,0,ROW()-1,60),ROW()-1,FALSE)) -> 2221.936 | AQ9: =IF(AND(ISNUMBER($AQ$44),$B$31=1),$AQ$44,HLOOKUP(INDIRECT(ADDRESS(2,COLUMN())),OFFSET($BN$2,0,0,ROW()-1,60),ROW()-1,FALSE)) -> 2181.957 | AR9: =IF(AND(ISNUMBER($AR$44),$B$31=1),$AR$44,HLOOKUP(INDIRECT(ADDRESS(2,COLUMN())),OFFSET($BN$2,0,0,ROW()-1,60),ROW()-1,FALSE)) -> 2222.279 | AS9: =IF(AND(ISNUMBER($AS$44),$B$31=1),$AS$44,HLOOKUP(INDIRECT(ADDRESS(2,COLUMN())),OFFSET($BN$2,0,0,ROW()-1,60),ROW()-1,FALSE)) -> 2260.724 | AT9: =IF(AND(ISNUMBER($AT$44),$B$31=1),$AT$44,HLOOKUP(INDIRECT(ADDRESS(2,COLUMN())),OFFSET($BN$2,0,0,ROW()-1,60),ROW()-1,FALSE)) -> 2300.441 | AU9: =IF(AND(ISNUMBER($AU$44),$B$31=1),$AU$44,HLOOKUP(INDIRECT(ADDRESS(2,COLUMN())),OFFSET($BN$2,0,0,ROW()-1,60),ROW()-1,FALSE)) -> 2299.045 | AV9: =IF(AND(ISNUMBER($AV$44),$B$31=1),$AV$44,HLOOKUP(INDIRECT(ADDRESS(2,COLUMN())),OFFSET($BN$2,0,0,ROW()-1,60),ROW()-1,FALSE)) -> 2376.218 | AW9: =IF(AND(ISNUMBER($AW$44),$B$31=1),$AW$44,HLOOKUP(INDIRECT(ADDRESS(2,COLUMN())),OFFSET($BN$2,0,0,ROW()-1,60),ROW()-1,FALSE)) -> 2399.191 | AX9: =IF(AND(ISNUMBER($AX$44),$B$31=1),$AX$44,HLOOKUP(INDIRECT(ADDRESS(2,COLUMN())),OFFSET($BN$2,0,0,ROW()-1,60),ROW()-1,FALSE)) -> 2395.168 | AY9: =IF(AND(ISNUMBER($AY$44),$B$31=1),$AY$44,HLOOKUP(INDIRECT(ADDRESS(2,COLUMN())),OFFSET($BN$2,0,0,ROW()-1,60),ROW()-1,FALSE)) -> 2343.602 | AZ9: =IF(AND(ISNUMBER($AZ$44),$B$31=1),$AZ$44,HLOOKUP(INDIRECT(ADDRESS(2,COLUMN())),OFFSET($BN$2,0,0,ROW()-1,60),ROW()-1,FALSE)) -> 2349.24 | BA9: =IF(AND(ISNUMBER($BA$44),$B$31=1),$BA$44,HLOOKUP(INDIRECT(ADDRESS(2,COLUMN())),OFFSET($BN$2,0,0,ROW()-1,60),ROW()-1,FALSE)) -> 2285.116 | BB9: =IF(AND(ISNUMBER($BB$44),$B$31=1),$BB$44,HLOOKUP(INDIRECT(ADDRESS(2,COLUMN())),OFFSET($BN$2,0,0,ROW()-1,60),ROW()-1,FALSE)) -> 2261.403 | BC9: =IF(AND(ISNUMBER($BC$44),$B$31=1),$BC$44,HLOOKUP(INDIRECT(ADDRESS(2,COLUMN())),OFFSET($BN$2,0,0,ROW()-1,60),ROW()-1,FALSE)) -> 2255.929 | BD9: =IF(AND(ISNUMBER($BD$44),$B$31=1),$BD$44,HLOOKUP(INDIRECT(ADDRESS(2,COLUMN())),OFFSET($BN$2,0,0,ROW()-1,60),ROW()-1,FALSE)) -> 2237.498 | BE9: =IF(AND(ISNUMBER($BE$44),$B$31=1),$BE$44,HLOOKUP(INDIRECT(ADDRESS(2,COLUMN())),OFFSET($BN$2,0,0,ROW()-1,60),ROW()-1,FALSE)) -> 2227.734 | BF9: =IF(AND(ISNUMBER($BF$44),$B$31=1),$BF$44,HLOOKUP(INDIRECT(ADDRESS(2,COLUMN())),OFFSET($BN$2,0,0,ROW()-1,60),ROW()-1,FALSE)) -> 2215.586 | BG9: =IF(AND(ISNUMBER($BG$44),$B$31=1),$BG$44,HLOOKUP(INDIRECT(ADDRESS(2,COLUMN())),OFFSET($BN$2,0,0,ROW()-1,60),ROW()-1,FALSE)) -> 2189.981 | BH9: =IF(AND(ISNUMBER($BH$44),$B$31=1),$BH$44,HLOOKUP(INDIRECT(ADDRESS(2,COLUMN())),OFFSET($BN$2,0,0,ROW()-1,60),ROW()-1,FALSE)) -> 2150.123 | BI9: =IF(AND(ISNUMBER($BI$44),$B$31=1),$BI$44,HLOOKUP(INDIRECT(ADDRESS(2,COLUMN())),OFFSET($BN$2,0,0,ROW()-1,60),ROW()-1,FALSE)) -> 2156.793 | BJ9: =IF(AND(ISNUMBER($BJ$44),$B$31=1),$BJ$44,HLOOKUP(INDIRECT(ADDRESS(2,COLUMN())),OFFSET($BN$2,0,0,ROW()-1,60),ROW()-1,FALSE)) -> 2116.132 | BK9: =IF(AND(ISNUMBER($BK$44),$B$31=1),$BK$44,HLOOKUP(INDIRECT(ADDRESS(2,COLUMN())),OFFSET($BN$2,0,0,ROW()-1,60),ROW()-1,FALSE)) -> 2040.407 | BL9: =IF(AND(ISNUMBER($BL$44),$B$31=1),$BL$44,HLOOKUP(INDIRECT(ADDRESS(2,COLUMN())),OFFSET($BN$2,0,0,ROW()-1,60),ROW()-1,FALSE)) -> 1972.116 | BM9: =IF(AND(ISNUMBER($BM$44),$B$31=1),$BM$44,HLOOKUP(INDIRECT(ADDRESS(2,COLUMN())),OFFSET($BN$2,0,0,ROW()-1,60),ROW()-1,FALSE)) -> 1877.253 | BN9: =3241.946 -> 3241.946 | BO9: =3266.413 -> 3266.413 | BP9: =3220.929 -> 3220.929 | BQ9: =3220.292 -> 3220.292 | BR9: =3154.321 -> 3154.321 | BS9: =3125.421 -> 3125.421 | BT9: =3091.748 -> 3091.748 | BU9: =3062.041 -> 3062.041 | BV9: =2995.524 -> 2995.524 | BW9: =3060.562 -> 3060.562 | BX9: =3046.718 -> 3046.718 | BY9: =3102.55 -> 3102.55 | BZ9: =3071.551 -> 3071.551 | CA9: =2848.698 -> 2848.698 | CB9: =2765.36 -> 2765.36 | CC9: =2570.103 -> 2570.103 | CD9: =2505.032 -> 2505.032 | CE9: =2381.224 -> 2381.224 | CF9: =2268.891 -> 2268.891 | CG9: =2105.083 -> 2105.083 | CH9: =1814.401 -> 1814.401 | CI9: =2416.181 -> 2416.181 | CJ9: =2537.466 -> 2537.466 | CK9: =2532.405 -> 2532.405 | CL9: =2547.448 -> 2547.448 | CM9: =2540.244 -> 2540.244 | CN9: =2537.415 -> 2537.415 | CO9: =2535.501 -> 2535.501 | CP9: =2562.172 -> 2562.172 | CQ9: =2517.268 -> 2517.268 | CR9: =2479.107 -> 2479.107 | CS9: =2384.524 -> 2384.524 | CT9: =2349.681 -> 2349.681 | CU9: =2339.728 -> 2339.728 | CV9: =2268.339 -> 2268.339 | CW9: =2270 -> 2270 | CX9: =2221.936 -> 2221.936 | CY9: =2181.957 -> 2181.957 | CZ9: =2222.279 -> 2222.279 | DA9: =2260.724 -> 2260.724 | DB9: =2300.441 -> 2300.441 | DC9: =2299.045 -> 2299.045 | DD9: =2376.218 -> 2376.218 | DE9: =2399.191 -> 2399.191 | DF9: =2395.168 -> 2395.168 | DG9: =2343.602 -> 2343.602 | DH9: =2349.24 -> 2349.24 | DI9: =2285.116 -> 2285.116 | DJ9: =2261.403 -> 2261.403 | DK9: =2255.929 -> 2255.929 | DL9: =2237.498 -> 2237.498 | DM9: =2227.734 -> 2227.734 | DN9: =2215.586 -> 2215.586 | DO9: =2189.981 -> 2189.981 | DP9: =2150.123 -> 2150.123 | DQ9: =2156.793 -> 2156.793 | DR9: =2116.132 -> 2116.132 | DS9: =2040.407 -> 2040.407 | DT9: =1972.116 -> 1972.116 | DU9: =1877.253 -> 1877.253
A10: =" Imports" -> Imports | B10: ="GDP$IMP Index" -> GDP$IMP Index | C10: ="PR005" -> PR005 | D10: ="PX_LAST" -> PX_LAST | E10: ="Dynamic" -> Dynamic | F10: =IF(AND(ISNUMBER($F$45),$B$31=1),$F$45,HLOOKUP(INDIRECT(ADDRESS(2,COLUMN())),OFFSET($BN$2,0,0,ROW()-1,60),ROW()-1,FALSE)) -> 4114.33 | G10: =IF(AND(ISNUMBER($G$45),$B$31=1),$G$45,HLOOKUP(INDIRECT(ADDRESS(2,COLUMN())),OFFSET($BN$2,0,0,ROW()-1,60),ROW()-1,FALSE)) -> 4511.554 | H10: =IF(AND(ISNUMBER($H$45),$B$31=1),$H$45,HLOOKUP(INDIRECT(ADDRESS(2,COLUMN())),OFFSET($BN$2,0,0,ROW()-1,60),ROW()-1,FALSE)) -> 4141.013 | I10: =IF(AND(ISNUMBER($I$45),$B$31=1),$I$45,HLOOKUP(INDIRECT(ADDRESS(2,COLUMN())),OFFSET($BN$2,0,0,ROW()-1,60),ROW()-1,FALSE)) -> 4163.975 | J10: =IF(AND(ISNUMBER($J$45),$B$31=1),$J$45,HLOOKUP(INDIRECT(ADDRESS(2,COLUMN())),OFFSET($BN$2,0,0,ROW()-1,60),ROW()-1,FALSE)) -> 4061.192 | K10: =IF(AND(ISNUMBER($K$45),$B$31=1),$K$45,HLOOKUP(INDIRECT(ADDRESS(2,COLUMN())),OFFSET($BN$2,0,0,ROW()-1,60),ROW()-1,FALSE)) -> 3966.989 | L10: =IF(AND(ISNUMBER($L$45),$B$31=1),$L$45,HLOOKUP(INDIRECT(ADDRESS(2,COLUMN())),OFFSET($BN$2,0,0,ROW()-1,60),ROW()-1,FALSE)) -> 3882.899 | M10: =IF(AND(ISNUMBER($M$45),$B$31=1),$M$45,HLOOKUP(INDIRECT(ADDRESS(2,COLUMN())),OFFSET($BN$2,0,0,ROW()-1,60),ROW()-1,FALSE)) -> 3843.132 | N10: =IF(AND(ISNUMBER($N$45),$B$31=1),$N$45,HLOOKUP(INDIRECT(ADDRESS(2,COLUMN())),OFFSET($BN$2,0,0,ROW()-1,60),ROW()-1,FALSE)) -> 3799.003 | O10: =IF(AND(ISNUMBER($O$45),$B$31=1),$O$45,HLOOKUP(INDIRECT(ADDRESS(2,COLUMN())),OFFSET($BN$2,0,0,ROW()-1,60),ROW()-1,FALSE)) -> 3874.21 | P10: =IF(AND(ISNUMBER($P$45),$B$31=1),$P$45,HLOOKUP(INDIRECT(ADDRESS(2,COLUMN())),OFFSET($BN$2,0,0,ROW()-1,60),ROW()-1,FALSE)) -> 3897.402 | Q10: =IF(AND(ISNUMBER($Q$45),$B$31=1),$Q$45,HLOOKUP(INDIRECT(ADDRESS(2,COLUMN())),OFFSET($BN$2,0,0,ROW()-1,60),ROW()-1,FALSE)) -> 3988.447 | R10: =IF(AND(ISNUMBER($R$45),$B$31=1),$R$45,HLOOKUP(INDIRECT(ADDRESS(2,COLUMN())),OFFSET($BN$2,0,0,ROW()-1,60),ROW()-1,FALSE)) -> 4093.663 | S10: =IF(AND(ISNUMBER($S$45),$B$31=1),$S$45,HLOOKUP(INDIRECT(ADDRESS(2,COLUMN())),OFFSET($BN$2,0,0,ROW()-1,60),ROW()-1,FALSE)) -> 3925.742 | T10: =IF(AND(ISNUMBER($T$45),$B$31=1),$T$45,HLOOKUP(INDIRECT(ADDRESS(2,COLUMN())),OFFSET($BN$2,0,0,ROW()-1,60),ROW()-1,FALSE)) -> 3685.956 | U10: =IF(AND(ISNUMBER($U$45),$B$31=1),$U$45,HLOOKUP(INDIRECT(ADDRESS(2,COLUMN())),OFFSET($BN$2,0,0,ROW()-1,60),ROW()-1,FALSE)) -> 3458.783 | V10: =IF(AND(ISNUMBER($V$45),$B$31=1),$V$45,HLOOKUP(INDIRECT(ADDRESS(2,COLUMN())),OFFSET($BN$2,0,0,ROW()-1,60),ROW()-1,FALSE)) -> 3340.114 | W10: =IF(AND(ISNUMBER($W$45),$B$31=1),$W$45,HLOOKUP(INDIRECT(ADDRESS(2,COLUMN())),OFFSET($BN$2,0,0,ROW()-1,60),ROW()-1,FALSE)) -> 3176.982 | X10: =IF(AND(ISNUMBER($X$45),$B$31=1),$X$45,HLOOKUP(INDIRECT(ADDRESS(2,COLUMN())),OFFSET($BN$2,0,0,ROW()-1,60),ROW()-1,FALSE)) -> 3027.199 | Y10: =IF(AND(ISNUMBER($Y$45),$B$31=1),$Y$45,HLOOKUP(INDIRECT(ADDRESS(2,COLUMN())),OFFSET($BN$2,0,0,ROW()-1,60),ROW()-1,FALSE)) -> 2801.482 | Z10: =IF(AND(ISNUMBER($Z$45),$B$31=1),$Z$45,HLOOKUP(INDIRECT(ADDRESS(2,COLUMN())),OFFSET($BN$2,0,0,ROW()-1,60),ROW()-1,FALSE)) -> 2350.926 | AA10: =IF(AND(ISNUMBER($AA$45),$B$31=1),$AA$45,HLOOKUP(INDIRECT(ADDRESS(2,COLUMN())),OFFSET($BN$2,0,0,ROW()-1,60),ROW()-1,FALSE)) -> 2929.759 | AB10: =IF(AND(ISNUMBER($AB$45),$B$31=1),$AB$45,HLOOKUP(INDIRECT(ADDRESS(2,COLUMN())),OFFSET($BN$2,0,0,ROW()-1,60),ROW()-1,FALSE)) -> 3050.824 | AC10: =IF(AND(ISNUMBER($AC$45),$B$31=1),$AC$45,HLOOKUP(INDIRECT(ADDRESS(2,COLUMN())),OFFSET($BN$2,0,0,ROW()-1,60),ROW()-1,FALSE)) -> 3117.952 | AD10: =IF(AND(ISNUMBER($AD$45),$B$31=1),$AD$45,HLOOKUP(INDIRECT(ADDRESS(2,COLUMN())),OFFSET($BN$2,0,0,ROW()-1,60),ROW()-1,FALSE)) -> 3165.41 | AE10: =IF(AND(ISNUMBER($AE$45),$B$31=1),$AE$45,HLOOKUP(INDIRECT(ADDRESS(2,COLUMN())),OFFSET($BN$2,0,0,ROW()-1,60),ROW()-1,FALSE)) -> 3132.539 | AF10: =IF(AND(ISNUMBER($AF$45),$B$31=1),$AF$45,HLOOKUP(INDIRECT(ADDRESS(2,COLUMN())),OFFSET($BN$2,0,0,ROW()-1,60),ROW()-1,FALSE)) -> 3171.622 | AG10: =IF(AND(ISNUMBER($AG$45),$B$31=1),$AG$45,HLOOKUP(INDIRECT(ADDRESS(2,COLUMN())),OFFSET($BN$2,0,0,ROW()-1,60),ROW()-1,FALSE)) -> 3153.747 | AH10: =IF(AND(ISNUMBER($AH$45),$B$31=1),$AH$45,HLOOKUP(INDIRECT(ADDRESS(2,COLUMN())),OFFSET($BN$2,0,0,ROW()-1,60),ROW()-1,FALSE)) -> 3105.995 | AI10: =IF(AND(ISNUMBER($AI$45),$B$31=1),$AI$45,HLOOKUP(INDIRECT(ADDRESS(2,COLUMN())),OFFSET($BN$2,0,0,ROW()-1,60),ROW()-1,FALSE)) -> 3093.299 | AJ10: =IF(AND(ISNUMBER($AJ$45),$B$31=1),$AJ$45,HLOOKUP(INDIRECT(ADDRESS(2,COLUMN())),OFFSET($BN$2,0,0,ROW()-1,60),ROW()-1,FALSE)) -> 3034.004 | AK10: =IF(AND(ISNUMBER($AK$45),$B$31=1),$AK$45,HLOOKUP(INDIRECT(ADDRESS(2,COLUMN())),OFFSET($BN$2,0,0,ROW()-1,60),ROW()-1,FALSE)) -> 2916.022 | AL10: =IF(AND(ISNUMBER($AL$45),$B$31=1),$AL$45,HLOOKUP(INDIRECT(ADDRESS(2,COLUMN())),OFFSET($BN$2,0,0,ROW()-1,60),ROW()-1,FALSE)) -> 2903.18 | AM10: =IF(AND(ISNUMBER($AM$45),$B$31=1),$AM$45,HLOOKUP(INDIRECT(ADDRESS(2,COLUMN())),OFFSET($BN$2,0,0,ROW()-1,60),ROW()-1,FALSE)) -> 2873.148 | AN10: =IF(AND(ISNUMBER($AN$45),$B$31=1),$AN$45,HLOOKUP(INDIRECT(ADDRESS(2,COLUMN())),OFFSET($BN$2,0,0,ROW()-1,60),ROW()-1,FALSE)) -> 2799.145 | AO10: =IF(AND(ISNUMBER($AO$45),$B$31=1),$AO$45,HLOOKUP(INDIRECT(ADDRESS(2,COLUMN())),OFFSET($BN$2,0,0,ROW()-1,60),ROW()-1,FALSE)) -> 2751.229 | AP10: =IF(AND(ISNUMBER($AP$45),$B$31=1),$AP$45,HLOOKUP(INDIRECT(ADDRESS(2,COLUMN())),OFFSET($BN$2,0,0,ROW()-1,60),ROW()-1,FALSE)) -> 2711.306 | AQ10: =IF(AND(ISNUMBER($AQ$45),$B$31=1),$AQ$45,HLOOKUP(INDIRECT(ADDRESS(2,COLUMN())),OFFSET($BN$2,0,0,ROW()-1,60),ROW()-1,FALSE)) -> 2693.639 | AR10: =IF(AND(ISNUMBER($AR$45),$B$31=1),$AR$45,HLOOKUP(INDIRECT(ADDRESS(2,COLUMN())),OFFSET($BN$2,0,0,ROW()-1,60),ROW()-1,FALSE)) -> 2745.517 | AS10: =IF(AND(ISNUMBER($AS$45),$B$31=1),$AS$45,HLOOKUP(INDIRECT(ADDRESS(2,COLUMN())),OFFSET($BN$2,0,0,ROW()-1,60),ROW()-1,FALSE)) -> 2798.806 | AT10: =IF(AND(ISNUMBER($AT$45),$B$31=1),$AT$45,HLOOKUP(INDIRECT(ADDRESS(2,COLUMN())),OFFSET($BN$2,0,0,ROW()-1,60),ROW()-1,FALSE)) -> 2809.968 | AU10: =IF(AND(ISNUMBER($AU$45),$B$31=1),$AU$45,HLOOKUP(INDIRECT(ADDRESS(2,COLUMN())),OFFSET($BN$2,0,0,ROW()-1,60),ROW()-1,FALSE)) -> 2825.476 | AV10: =IF(AND(ISNUMBER($AV$45),$B$31=1),$AV$45,HLOOKUP(INDIRECT(ADDRESS(2,COLUMN())),OFFSET($BN$2,0,0,ROW()-1,60),ROW()-1,FALSE)) -> 2906.969 | AW10: =IF(AND(ISNUMBER($AW$45),$B$31=1),$AW$45,HLOOKUP(INDIRECT(ADDRESS(2,COLUMN())),OFFSET($BN$2,0,0,ROW()-1,60),ROW()-1,FALSE)) -> 2888.549 | AX10: =IF(AND(ISNUMBER($AX$45),$B$31=1),$AX$45,HLOOKUP(INDIRECT(ADDRESS(2,COLUMN())),OFFSET($BN$2,0,0,ROW()-1,60),ROW()-1,FALSE)) -> 2900.572 | AY10: =IF(AND(ISNUMBER($AY$45),$B$31=1),$AY$45,HLOOKUP(INDIRECT(ADDRESS(2,COLUMN())),OFFSET($BN$2,0,0,ROW()-1,60),ROW()-1,FALSE)) -> 2853.69 | AZ10: =IF(AND(ISNUMBER($AZ$45),$B$31=1),$AZ$45,HLOOKUP(INDIRECT(ADDRESS(2,COLUMN())),OFFSET($BN$2,0,0,ROW()-1,60),ROW()-1,FALSE)) -> 2783.259 | BA10: =IF(AND(ISNUMBER($BA$45),$B$31=1),$BA$45,HLOOKUP(INDIRECT(ADDRESS(2,COLUMN())),OFFSET($BN$2,0,0,ROW()-1,60),ROW()-1,FALSE)) -> 2767.183 | BB10: =IF(AND(ISNUMBER($BB$45),$B$31=1),$BB$45,HLOOKUP(INDIRECT(ADDRESS(2,COLUMN())),OFFSET($BN$2,0,0,ROW()-1,60),ROW()-1,FALSE)) -> 2759.783 | BC10: =IF(AND(ISNUMBER($BC$45),$B$31=1),$BC$45,HLOOKUP(INDIRECT(ADDRESS(2,COLUMN())),OFFSET($BN$2,0,0,ROW()-1,60),ROW()-1,FALSE)) -> 2755.277 | BD10: =IF(AND(ISNUMBER($BD$45),$B$31=1),$BD$45,HLOOKUP(INDIRECT(ADDRESS(2,COLUMN())),OFFSET($BN$2,0,0,ROW()-1,60),ROW()-1,FALSE)) -> 2753.373 | BE10: =IF(AND(ISNUMBER($BE$45),$B$31=1),$BE$45,HLOOKUP(INDIRECT(ADDRESS(2,COLUMN())),OFFSET($BN$2,0,0,ROW()-1,60),ROW()-1,FALSE)) -> 2750.817 | BF10: =IF(AND(ISNUMBER($BF$45),$B$31=1),$BF$45,HLOOKUP(INDIRECT(ADDRESS(2,COLUMN())),OFFSET($BN$2,0,0,ROW()-1,60),ROW()-1,FALSE)) -> 2780.827 | BG10: =IF(AND(ISNUMBER($BG$45),$B$31=1),$BG$45,HLOOKUP(INDIRECT(ADDRESS(2,COLUMN())),OFFSET($BN$2,0,0,ROW()-1,60),ROW()-1,FALSE)) -> 2792.253 | BH10: =IF(AND(ISNUMBER($BH$45),$B$31=1),$BH$45,HLOOKUP(INDIRECT(ADDRESS(2,COLUMN())),OFFSET($BN$2,0,0,ROW()-1,60),ROW()-1,FALSE)) -> 2751.911 | BI10: =IF(AND(ISNUMBER($BI$45),$B$31=1),$BI$45,HLOOKUP(INDIRECT(ADDRESS(2,COLUMN())),OFFSET($BN$2,0,0,ROW()-1,60),ROW()-1,FALSE)) -> 2723.903 | BJ10: =IF(AND(ISNUMBER($BJ$45),$B$31=1),$BJ$45,HLOOKUP(INDIRECT(ADDRESS(2,COLUMN())),OFFSET($BN$2,0,0,ROW()-1,60),ROW()-1,FALSE)) -> 2697.224 | BK10: =IF(AND(ISNUMBER($BK$45),$B$31=1),$BK$45,HLOOKUP(INDIRECT(ADDRESS(2,COLUMN())),OFFSET($BN$2,0,0,ROW()-1,60),ROW()-1,FALSE)) -> 2608.884 | BL10: =IF(AND(ISNUMBER($BL$45),$B$31=1),$BL$45,HLOOKUP(INDIRECT(ADDRESS(2,COLUMN())),OFFSET($BN$2,0,0,ROW()-1,60),ROW()-1,FALSE)) -> 2495.702 | BM10: =IF(AND(ISNUMBER($BM$45),$B$31=1),$BM$45,HLOOKUP(INDIRECT(ADDRESS(2,COLUMN())),OFFSET($BN$2,0,0,ROW()-1,60),ROW()-1,FALSE)) -> 2431.195 | BN10: =4114.33 -> 4114.33 | BO10: =4511.554 -> 4511.554 | BP10: =4141.013 -> 4141.013 | BQ10: =4163.975 -> 4163.975 | BR10: =4061.192 -> 4061.192 | BS10: =3966.989 -> 3966.989 | BT10: =3882.899 -> 3882.899 | BU10: =3843.132 -> 3843.132 | BV10: =3799.003 -> 3799.003 | BW10: =3874.21 -> 3874.21 | BX10: =3897.402 -> 3897.402 | BY10: =3988.447 -> 3988.447 | BZ10: =4093.663 -> 4093.663 | CA10: =3925.742 -> 3925.742 | CB10: =3685.956 -> 3685.956 | CC10: =3458.783 -> 3458.783 | CD10: =3340.114 -> 3340.114 | CE10: =3176.982 -> 3176.982 | CF10: =3027.199 -> 3027.199 | CG10: =2801.482 -> 2801.482 | CH10: =2350.926 -> 2350.926 | CI10: =2929.759 -> 2929.759 | CJ10: =3050.824 -> 3050.824 | CK10: =3117.952 -> 3117.952 | CL10: =3165.41 -> 3165.41 | CM10: =3132.539 -> 3132.539 | CN10: =3171.622 -> 3171.622 | CO10: =3153.747 -> 3153.747 | CP10: =3105.995 -> 3105.995 | CQ10: =3093.299 -> 3093.299 | CR10: =3034.004 -> 3034.004 | CS10: =2916.022 -> 2916.022 | CT10: =2903.18 -> 2903.18 | CU10: =2873.148 -> 2873.148 | CV10: =2799.145 -> 2799.145 | CW10: =2751.229 -> 2751.229 | CX10: =2711.306 -> 2711.306 | CY10: =2693.639 -> 2693.639 | CZ10: =2745.517 -> 2745.517 | DA10: =2798.806 -> 2798.806 | DB10: =2809.968 -> 2809.968 | DC10: =2825.476 -> 2825.476 | DD10: =2906.969 -> 2906.969 | DE10: =2888.549 -> 2888.549 | DF10: =2900.572 -> 2900.572 | DG10: =2853.69 -> 2853.69 | DH10: =2783.259 -> 2783.259 | DI10: =2767.183 -> 2767.183 | DJ10: =2759.783 -> 2759.783 | DK10: =2755.277 -> 2755.277 | DL10: =2753.373 -> 2753.373 | DM10: =2750.817 -> 2750.817 | DN10: =2780.827 -> 2780.827 | DO10: =2792.253 -> 2792.253 | DP10: =2751.911 -> 2751.911 | DQ10: =2723.903 -> 2723.903 | DR10: =2697.224 -> 2697.224 | DS10: =2608.884 -> 2608.884 | DT10: =2495.702 -> 2495.702 | DU10: =2431.195 -> 2431.195
A11: ="Western Europe (Bil.) - Euro Area (EUR)" -> Western Europe (Bil.) - Euro Area (EUR) | B11: ="EUGDEMU Index" -> EUGDEMU Index | E11: ="Expression" -> Expression | F11: =IF(AND($B$31=1,LEN($F$33)>0),$F$33/1000,HLOOKUP(INDIRECT(ADDRESS(2,COLUMN())),OFFSET($BN$2,0,0,ROW()-1,60),ROW()-1,FALSE)) | G11: =IF(AND($B$31=1,LEN($G$33)>0),$G$33/1000,HLOOKUP(INDIRECT(ADDRESS(2,COLUMN())),OFFSET($BN$2,0,0,ROW()-1,60),ROW()-1,FALSE)) -> 3885.9885 | H11: =IF(AND($B$31=1,LEN($H$33)>0),$H$33/1000,HLOOKUP(INDIRECT(ADDRESS(2,COLUMN())),OFFSET($BN$2,0,0,ROW()-1,60),ROW()-1,FALSE)) -> 3852.702 | I11: =IF(AND($B$31=1,LEN($I$33)>0),$I$33/1000,HLOOKUP(INDIRECT(ADDRESS(2,COLUMN())),OFFSET($BN$2,0,0,ROW()-1,60),ROW()-1,FALSE)) -> 3807.5193 | J11: =IF(AND($B$31=1,LEN($J$33)>0),$J$33/1000,HLOOKUP(INDIRECT(ADDRESS(2,COLUMN())),OFFSET($BN$2,0,0,ROW()-1,60),ROW()-1,FALSE)) -> 3772.4073 | K11: =IF(AND($B$31=1,LEN($K$33)>0),$K$33/1000,HLOOKUP(INDIRECT(ADDRESS(2,COLUMN())),OFFSET($BN$2,0,0,ROW()-1,60),ROW()-1,FALSE)) -> 3743.2065 | L11: =IF(AND($B$31=1,LEN($L$33)>0),$L$33/1000,HLOOKUP(INDIRECT(ADDRESS(2,COLUMN())),OFFSET($BN$2,0,0,ROW()-1,60),ROW()-1,FALSE)) -> 3708.097 | M11: =IF(AND($B$31=1,LEN($M$33)>0),$M$33/1000,HLOOKUP(INDIRECT(ADDRESS(2,COLUMN())),OFFSET($BN$2,0,0,ROW()-1,60),ROW()-1,FALSE)) -> 3667.9545 | N11: =IF(AND($B$31=1,LEN($N$33)>0),$N$33/1000,HLOOKUP(INDIRECT(ADDRESS(2,COLUMN())),OFFSET($BN$2,0,0,ROW()-1,60),ROW()-1,FALSE)) -> 3640.3645 | O11: =IF(AND($B$31=1,LEN($O$33)>0),$O$33/1000,HLOOKUP(INDIRECT(ADDRESS(2,COLUMN())),OFFSET($BN$2,0,0,ROW()-1,60),ROW()-1,FALSE)) -> 3592.8278 | P11: =IF(AND($B$31=1,LEN($P$33)>0),$P$33/1000,HLOOKUP(INDIRECT(ADDRESS(2,COLUMN())),OFFSET($BN$2,0,0,ROW()-1,60),ROW()-1,FALSE)) -> 3527.2652 | Q11: =IF(AND($B$31=1,LEN($Q$33)>0),$Q$33/1000,HLOOKUP(INDIRECT(ADDRESS(2,COLUMN())),OFFSET($BN$2,0,0,ROW()-1,60),ROW()-1,FALSE)) -> 3460.664 | R11: =IF(AND($B$31=1,LEN($R$33)>0),$R$33/1000,HLOOKUP(INDIRECT(ADDRESS(2,COLUMN())),OFFSET($BN$2,0,0,ROW()-1,60),ROW()-1,FALSE)) -> 3399.6503 | S11: =IF(AND($B$31=1,LEN($S$33)>0),$S$33/1000,HLOOKUP(INDIRECT(ADDRESS(2,COLUMN())),OFFSET($BN$2,0,0,ROW()-1,60),ROW()-1,FALSE)) -> 3326.8777 | T11: =IF(AND($B$31=1,LEN($T$33)>0),$T$33/1000,HLOOKUP(INDIRECT(ADDRESS(2,COLUMN())),OFFSET($BN$2,0,0,ROW()-1,60),ROW()-1,FALSE)) -> 3263.3072 | U11: =IF(AND($B$31=1,LEN($U$33)>0),$U$33/1000,HLOOKUP(INDIRECT(ADDRESS(2,COLUMN())),OFFSET($BN$2,0,0,ROW()-1,60),ROW()-1,FALSE)) -> 3199.6137 | V11: =IF(AND($B$31=1,LEN($V$33)>0),$V$33/1000,HLOOKUP(INDIRECT(ADDRESS(2,COLUMN())),OFFSET($BN$2,0,0,ROW()-1,60),ROW()-1,FALSE)) -> 3105.8169 | W11: =IF(AND($B$31=1,LEN($W$33)>0),$W$33/1000,HLOOKUP(INDIRECT(ADDRESS(2,COLUMN())),OFFSET($BN$2,0,0,ROW()-1,60),ROW()-1,FALSE)) -> 3028.6187 | X11: =IF(AND($B$31=1,LEN($X$33)>0),$X$33/1000,HLOOKUP(INDIRECT(ADDRESS(2,COLUMN())),OFFSET($BN$2,0,0,ROW()-1,60),ROW()-1,FALSE)) -> 2992.5549 | Y11: =IF(AND($B$31=1,LEN($Y$33)>0),$Y$33/1000,HLOOKUP(INDIRECT(ADDRESS(2,COLUMN())),OFFSET($BN$2,0,0,ROW()-1,60),ROW()-1,FALSE)) -> 2958.6418 | Z11: =IF(AND($B$31=1,LEN($Z$33)>0),$Z$33/1000,HLOOKUP(INDIRECT(ADDRESS(2,COLUMN())),OFFSET($BN$2,0,0,ROW()-1,60),ROW()-1,FALSE)) -> 2678.0275 | AA11: =IF(AND($B$31=1,LEN($AA$33)>0),$AA$33/1000,HLOOKUP(INDIRECT(ADDRESS(2,COLUMN())),OFFSET($BN$2,0,0,ROW()-1,60),ROW()-1,FALSE)) -> 2976.8248 | AB11: =IF(AND($B$31=1,LEN($AB$33)>0),$AB$33/1000,HLOOKUP(INDIRECT(ADDRESS(2,COLUMN())),OFFSET($BN$2,0,0,ROW()-1,60),ROW()-1,FALSE)) -> 3065.2432 | AC11: =IF(AND($B$31=1,LEN($AC$33)>0),$AC$33/1000,HLOOKUP(INDIRECT(ADDRESS(2,COLUMN())),OFFSET($BN$2,0,0,ROW()-1,60),ROW()-1,FALSE)) -> 3048.1265 | AD11: =IF(AND($B$31=1,LEN($AD$33)>0),$AD$33/1000,HLOOKUP(INDIRECT(ADDRESS(2,COLUMN())),OFFSET($BN$2,0,0,ROW()-1,60),ROW()-1,FALSE)) -> 3027.6762 | AE11: =IF(AND($B$31=1,LEN($AE$33)>0),$AE$33/1000,HLOOKUP(INDIRECT(ADDRESS(2,COLUMN())),OFFSET($BN$2,0,0,ROW()-1,60),ROW()-1,FALSE)) -> 3006.5916 | AF11: =IF(AND($B$31=1,LEN($AF$33)>0),$AF$33/1000,HLOOKUP(INDIRECT(ADDRESS(2,COLUMN())),OFFSET($BN$2,0,0,ROW()-1,60),ROW()-1,FALSE)) -> 2975.5678 | AG11: =IF(AND($B$31=1,LEN($AG$33)>0),$AG$33/1000,HLOOKUP(INDIRECT(ADDRESS(2,COLUMN())),OFFSET($BN$2,0,0,ROW()-1,60),ROW()-1,FALSE)) -> 2943.8759 | AH11: =IF(AND($B$31=1,LEN($AH$33)>0),$AH$33/1000,HLOOKUP(INDIRECT(ADDRESS(2,COLUMN())),OFFSET($BN$2,0,0,ROW()-1,60),ROW()-1,FALSE)) -> 2926.8874 | AI11: =IF(AND($B$31=1,LEN($AI$33)>0),$AI$33/1000,HLOOKUP(INDIRECT(ADDRESS(2,COLUMN())),OFFSET($BN$2,0,0,ROW()-1,60),ROW()-1,FALSE)) -> 2904.8177 | AJ11: =IF(AND($B$31=1,LEN($AJ$33)>0),$AJ$33/1000,HLOOKUP(INDIRECT(ADDRESS(2,COLUMN())),OFFSET($BN$2,0,0,ROW()-1,60),ROW()-1,FALSE)) -> 2889.9533 | AK11: =IF(AND($B$31=1,LEN($AK$33)>0),$AK$33/1000,HLOOKUP(INDIRECT(ADDRESS(2,COLUMN())),OFFSET($BN$2,0,0,ROW()-1,60),ROW()-1,FALSE)) -> 2856.9899 | AL11: =IF(AND($B$31=1,LEN($AL$33)>0),$AL$33/1000,HLOOKUP(INDIRECT(ADDRESS(2,COLUMN())),OFFSET($BN$2,0,0,ROW()-1,60),ROW()-1,FALSE)) -> 2830.3412 | AM11: =IF(AND($B$31=1,LEN($AM$33)>0),$AM$33/1000,HLOOKUP(INDIRECT(ADDRESS(2,COLUMN())),OFFSET($BN$2,0,0,ROW()-1,60),ROW()-1,FALSE)) -> 2798.8087 | AN11: =IF(AND($B$31=1,LEN($AN$33)>0),$AN$33/1000,HLOOKUP(INDIRECT(ADDRESS(2,COLUMN())),OFFSET($BN$2,0,0,ROW()-1,60),ROW()-1,FALSE)) -> 2766.2286 | AO11: =IF(AND($B$31=1,LEN($AO$33)>0),$AO$33/1000,HLOOKUP(INDIRECT(ADDRESS(2,COLUMN())),OFFSET($BN$2,0,0,ROW()-1,60),ROW()-1,FALSE)) -> 2743.7322 | AP11: =IF(AND($B$31=1,LEN($AP$33)>0),$AP$33/1000,HLOOKUP(INDIRECT(ADDRESS(2,COLUMN())),OFFSET($BN$2,0,0,ROW()-1,60),ROW()-1,FALSE)) -> 2723.8741 | AQ11: =IF(AND($B$31=1,LEN($AQ$33)>0),$AQ$33/1000,HLOOKUP(INDIRECT(ADDRESS(2,COLUMN())),OFFSET($BN$2,0,0,ROW()-1,60),ROW()-1,FALSE)) -> 2713.3994 | AR11: =IF(AND($B$31=1,LEN($AR$33)>0),$AR$33/1000,HLOOKUP(INDIRECT(ADDRESS(2,COLUMN())),OFFSET($BN$2,0,0,ROW()-1,60),ROW()-1,FALSE)) -> 2693.0786 | AS11: =IF(AND($B$31=1,LEN($AS$33)>0),$AS$33/1000,HLOOKUP(INDIRECT(ADDRESS(2,COLUMN())),OFFSET($BN$2,0,0,ROW()-1,60),ROW()-1,FALSE)) -> 2676.4627 | AT11: =IF(AND($B$31=1,LEN($AT$33)>0),$AT$33/1000,HLOOKUP(INDIRECT(ADDRESS(2,COLUMN())),OFFSET($BN$2,0,0,ROW()-1,60),ROW()-1,FALSE)) -> 2656.2975 | AU11: =IF(AND($B$31=1,LEN($AU$33)>0),$AU$33/1000,HLOOKUP(INDIRECT(ADDRESS(2,COLUMN())),OFFSET($BN$2,0,0,ROW()-1,60),ROW()-1,FALSE)) -> 2633.1903 | AV11: =IF(AND($B$31=1,LEN($AV$33)>0),$AV$33/1000,HLOOKUP(INDIRECT(ADDRESS(2,COLUMN())),OFFSET($BN$2,0,0,ROW()-1,60),ROW()-1,FALSE)) -> 2601.3535 | AW11: =IF(AND($B$31=1,LEN($AW$33)>0),$AW$33/1000,HLOOKUP(INDIRECT(ADDRESS(2,COLUMN())),OFFSET($BN$2,0,0,ROW()-1,60),ROW()-1,FALSE)) -> 2583.9663 | AX11: =IF(AND($B$31=1,LEN($AX$33)>0),$AX$33/1000,HLOOKUP(INDIRECT(ADDRESS(2,COLUMN())),OFFSET($BN$2,0,0,ROW()-1,60),ROW()-1,FALSE)) -> 2567.4388 | AY11: =IF(AND($B$31=1,LEN($AY$33)>0),$AY$33/1000,HLOOKUP(INDIRECT(ADDRESS(2,COLUMN())),OFFSET($BN$2,0,0,ROW()-1,60),ROW()-1,FALSE)) -> 2555.6487 | AZ11: =IF(AND($B$31=1,LEN($AZ$33)>0),$AZ$33/1000,HLOOKUP(INDIRECT(ADDRESS(2,COLUMN())),OFFSET($BN$2,0,0,ROW()-1,60),ROW()-1,FALSE)) -> 2532.5553 | BA11: =IF(AND($B$31=1,LEN($BA$33)>0),$BA$33/1000,HLOOKUP(INDIRECT(ADDRESS(2,COLUMN())),OFFSET($BN$2,0,0,ROW()-1,60),ROW()-1,FALSE)) -> 2525.3384 | BB11: =IF(AND($B$31=1,LEN($BB$33)>0),$BB$33/1000,HLOOKUP(INDIRECT(ADDRESS(2,COLUMN())),OFFSET($BN$2,0,0,ROW()-1,60),ROW()-1,FALSE)) -> 2514.883 | BC11: =IF(AND($B$31=1,LEN($BC$33)>0),$BC$33/1000,HLOOKUP(INDIRECT(ADDRESS(2,COLUMN())),OFFSET($BN$2,0,0,ROW()-1,60),ROW()-1,FALSE)) -> 2492.6291 | BD11: =IF(AND($B$31=1,LEN($BD$33)>0),$BD$33/1000,HLOOKUP(INDIRECT(ADDRESS(2,COLUMN())),OFFSET($BN$2,0,0,ROW()-1,60),ROW()-1,FALSE)) -> 2486.918 | BE11: =IF(AND($B$31=1,LEN($BE$33)>0),$BE$33/1000,HLOOKUP(INDIRECT(ADDRESS(2,COLUMN())),OFFSET($BN$2,0,0,ROW()-1,60),ROW()-1,FALSE)) -> 2492.9426 | BF11: =IF(AND($B$31=1,LEN($BF$33)>0),$BF$33/1000,HLOOKUP(INDIRECT(ADDRESS(2,COLUMN())),OFFSET($BN$2,0,0,ROW()-1,60),ROW()-1,FALSE)) -> 2485.9026 | BG11: =IF(AND($B$31=1,LEN($BG$33)>0),$BG$33/1000,HLOOKUP(INDIRECT(ADDRESS(2,COLUMN())),OFFSET($BN$2,0,0,ROW()-1,60),ROW()-1,FALSE)) -> 2487.869 | BH11: =IF(AND($B$31=1,LEN($BH$33)>0),$BH$33/1000,HLOOKUP(INDIRECT(ADDRESS(2,COLUMN())),OFFSET($BN$2,0,0,ROW()-1,60),ROW()-1,FALSE)) -> 2484.4287 | BI11: =IF(AND($B$31=1,LEN($BI$33)>0),$BI$33/1000,HLOOKUP(INDIRECT(ADDRESS(2,COLUMN())),OFFSET($BN$2,0,0,ROW()-1,60),ROW()-1,FALSE)) -> 2485.1313 | BJ11: =IF(AND($B$31=1,LEN($BJ$33)>0),$BJ$33/1000,HLOOKUP(INDIRECT(ADDRESS(2,COLUMN())),OFFSET($BN$2,0,0,ROW()-1,60),ROW()-1,FALSE)) -> 2476.8837 | BK11: =IF(AND($B$31=1,LEN($BK$33)>0),$BK$33/1000,HLOOKUP(INDIRECT(ADDRESS(2,COLUMN())),OFFSET($BN$2,0,0,ROW()-1,60),ROW()-1,FALSE)) -> 2472.0133 | BL11: =IF(AND($B$31=1,LEN($BL$33)>0),$BL$33/1000,HLOOKUP(INDIRECT(ADDRESS(2,COLUMN())),OFFSET($BN$2,0,0,ROW()-1,60),ROW()-1,FALSE)) -> 2439.4036 | BM11: =IF(AND($B$31=1,LEN($BM$33)>0),$BM$33/1000,HLOOKUP(INDIRECT(ADDRESS(2,COLUMN())),OFFSET($BN$2,0,0,ROW()-1,60),ROW()-1,FALSE)) -> 2420.9213 | BN11: ="" | BO11: =3885.9885 -> 3885.9885 | BP11: =3852.702 -> 3852.702 | BQ11: =3807.5193 -> 3807.5193 | BR11: =3772.4073 -> 3772.4073 | BS11: =3743.2065 -> 3743.2065 | BT11: =3708.097 -> 3708.097 | BU11: =3667.9545 -> 3667.9545 | BV11: =3640.3645 -> 3640.3645 | BW11: =3592.8278 -> 3592.8278 | BX11: =3527.2652 -> 3527.2652 | BY11: =3460.664 -> 3460.664 | BZ11: =3399.6503 -> 3399.6503 | CA11: =3326.8777 -> 3326.8777 | CB11: =3263.3072 -> 3263.3072 | CC11: =3199.6137 -> 3199.6137 | CD11: =3105.8169 -> 3105.8169 | CE11: =3028.6187 -> 3028.6187 | CF11: =2992.5549 -> 2992.5549 | CG11: =2958.6418 -> 2958.6418 | CH11: =2678.0275 -> 2678.0275 | CI11: =2976.8248 -> 2976.8248 | CJ11: =3065.2432 -> 3065.2432 | CK11: =3048.1265 -> 3048.1265 | CL11: =3027.6762 -> 3027.6762 | CM11: =3006.5916 -> 3006.5916 | CN11: =2975.5678 -> 2975.5678 | CO11: =2943.8759 -> 2943.8759 | CP11: =2926.8874 -> 2926.8874 | CQ11: =2904.8177 -> 2904.8177 | CR11: =2889.9533 -> 2889.9533 | CS11: =2856.9899 -> 2856.9899 | CT11: =2830.3412 -> 2830.3412 | CU11: =2798.8087 -> 2798.8087 | CV11: =2766.2286 -> 2766.2286 | CW11: =2743.7322 -> 2743.7322 | CX11: =2723.8741 -> 2723.8741 | CY11: =2713.3994 -> 2713.3994 | CZ11: =2693.0786 -> 2693.0786 | DA11: =2676.4627 -> 2676.4627 | DB11: =2656.2975 -> 2656.2975 | DC11: =2633.1903 -> 2633.1903 | DD11: =2601.3535 -> 2601.3535 | DE11: =2583.9663 -> 2583.9663 | DF11: =2567.4388 -> 2567.4388 | DG11: =2555.6487 -> 2555.6487 | DH11: =2532.5553 -> 2532.5553 | DI11: =2525.3384 -> 2525.3384 | DJ11: =2514.883 -> 2514.883 | DK11: =2492.6291 -> 2492.6291 | DL11: =2486.918 -> 2486.918 | DM11: =2492.9426 -> 2492.9426 | DN11: =2485.9026 -> 2485.9026 | DO11: =2487.869 -> 2487.869 | DP11: =2484.4287 -> 2484.4287 | DQ11: =2485.1313 -> 2485.1313 | DR11: =2476.8837 -> 2476.8837 | DS11: =2472.0133 -> 2472.0133 | DT11: =2439.4036 -> 2439.4036 | DU11: =2420.9213 -> 2420.9213
A12: =" Final Consumption Expenditure" -> Final Consumption Expenditure | B12: ="ENFCEAS Index" -> ENFCEAS Index | E12: ="Expression" -> Expression | F12: =IF(AND($B$31=1,LEN($F$34)>0),$F$34/1000,HLOOKUP(INDIRECT(ADDRESS(2,COLUMN())),OFFSET($BN$2,0,0,ROW()-1,60),ROW()-1,FALSE)) | G12: =IF(AND($B$31=1,LEN($G$34)>0),$G$34/1000,HLOOKUP(INDIRECT(ADDRESS(2,COLUMN())),OFFSET($BN$2,0,0,ROW()-1,60),ROW()-1,FALSE)) -> 2888.1282 | H12: =IF(AND($B$31=1,LEN($H$34)>0),$H$34/1000,HLOOKUP(INDIRECT(ADDRESS(2,COLUMN())),OFFSET($BN$2,0,0,ROW()-1,60),ROW()-1,FALSE)) -> 2858.7927 | I12: =IF(AND($B$31=1,LEN($I$34)>0),$I$34/1000,HLOOKUP(INDIRECT(ADDRESS(2,COLUMN())),OFFSET($BN$2,0,0,ROW()-1,60),ROW()-1,FALSE)) -> 2834.7721 | J12: =IF(AND($B$31=1,LEN($J$34)>0),$J$34/1000,HLOOKUP(INDIRECT(ADDRESS(2,COLUMN())),OFFSET($BN$2,0,0,ROW()-1,60),ROW()-1,FALSE)) -> 2805.52 | K12: =IF(AND($B$31=1,LEN($K$34)>0),$K$34/1000,HLOOKUP(INDIRECT(ADDRESS(2,COLUMN())),OFFSET($BN$2,0,0,ROW()-1,60),ROW()-1,FALSE)) -> 2780.9173 | L12: =IF(AND($B$31=1,LEN($L$34)>0),$L$34/1000,HLOOKUP(INDIRECT(ADDRESS(2,COLUMN())),OFFSET($BN$2,0,0,ROW()-1,60),ROW()-1,FALSE)) -> 2752.5781 | M12: =IF(AND($B$31=1,LEN($M$34)>0),$M$34/1000,HLOOKUP(INDIRECT(ADDRESS(2,COLUMN())),OFFSET($BN$2,0,0,ROW()-1,60),ROW()-1,FALSE)) -> 2723.3114 | N12: =IF(AND($B$31=1,LEN($N$34)>0),$N$34/1000,HLOOKUP(INDIRECT(ADDRESS(2,COLUMN())),OFFSET($BN$2,0,0,ROW()-1,60),ROW()-1,FALSE)) -> 2693.8129 | O12: =IF(AND($B$31=1,LEN($O$34)>0),$O$34/1000,HLOOKUP(INDIRECT(ADDRESS(2,COLUMN())),OFFSET($BN$2,0,0,ROW()-1,60),ROW()-1,FALSE)) -> 2657.7057 | P12: =IF(AND($B$31=1,LEN($P$34)>0),$P$34/1000,HLOOKUP(INDIRECT(ADDRESS(2,COLUMN())),OFFSET($BN$2,0,0,ROW()-1,60),ROW()-1,FALSE)) -> 2620.6016 | Q12: =IF(AND($B$31=1,LEN($Q$34)>0),$Q$34/1000,HLOOKUP(INDIRECT(ADDRESS(2,COLUMN())),OFFSET($BN$2,0,0,ROW()-1,60),ROW()-1,FALSE)) -> 2576.7203 | R12: =IF(AND($B$31=1,LEN($R$34)>0),$R$34/1000,HLOOKUP(INDIRECT(ADDRESS(2,COLUMN())),OFFSET($BN$2,0,0,ROW()-1,60),ROW()-1,FALSE)) -> 2517.643 | S12: =IF(AND($B$31=1,LEN($S$34)>0),$S$34/1000,HLOOKUP(INDIRECT(ADDRESS(2,COLUMN())),OFFSET($BN$2,0,0,ROW()-1,60),ROW()-1,FALSE)) -> 2458.7145 | T12: =IF(AND($B$31=1,LEN($T$34)>0),$T$34/1000,HLOOKUP(INDIRECT(ADDRESS(2,COLUMN())),OFFSET($BN$2,0,0,ROW()-1,60),ROW()-1,FALSE)) -> 2401.025 | U12: =IF(AND($B$31=1,LEN($U$34)>0),$U$34/1000,HLOOKUP(INDIRECT(ADDRESS(2,COLUMN())),OFFSET($BN$2,0,0,ROW()-1,60),ROW()-1,FALSE)) -> 2360.2405 | V12: =IF(AND($B$31=1,LEN($V$34)>0),$V$34/1000,HLOOKUP(INDIRECT(ADDRESS(2,COLUMN())),OFFSET($BN$2,0,0,ROW()-1,60),ROW()-1,FALSE)) -> 2277.7042 | W12: =IF(AND($B$31=1,LEN($W$34)>0),$W$34/1000,HLOOKUP(INDIRECT(ADDRESS(2,COLUMN())),OFFSET($BN$2,0,0,ROW()-1,60),ROW()-1,FALSE)) -> 2196.5321 | X12: =IF(AND($B$31=1,LEN($X$34)>0),$X$34/1000,HLOOKUP(INDIRECT(ADDRESS(2,COLUMN())),OFFSET($BN$2,0,0,ROW()-1,60),ROW()-1,FALSE)) -> 2192.7202 | Y12: =IF(AND($B$31=1,LEN($Y$34)>0),$Y$34/1000,HLOOKUP(INDIRECT(ADDRESS(2,COLUMN())),OFFSET($BN$2,0,0,ROW()-1,60),ROW()-1,FALSE)) -> 2221.9214 | Z12: =IF(AND($B$31=1,LEN($Z$34)>0),$Z$34/1000,HLOOKUP(INDIRECT(ADDRESS(2,COLUMN())),OFFSET($BN$2,0,0,ROW()-1,60),ROW()-1,FALSE)) -> 2019.9591 | AA12: =IF(AND($B$31=1,LEN($AA$34)>0),$AA$34/1000,HLOOKUP(INDIRECT(ADDRESS(2,COLUMN())),OFFSET($BN$2,0,0,ROW()-1,60),ROW()-1,FALSE)) -> 2204.7461 | AB12: =IF(AND($B$31=1,LEN($AB$34)>0),$AB$34/1000,HLOOKUP(INDIRECT(ADDRESS(2,COLUMN())),OFFSET($BN$2,0,0,ROW()-1,60),ROW()-1,FALSE)) -> 2273.1355 | AC12: =IF(AND($B$31=1,LEN($AC$34)>0),$AC$34/1000,HLOOKUP(INDIRECT(ADDRESS(2,COLUMN())),OFFSET($BN$2,0,0,ROW()-1,60),ROW()-1,FALSE)) -> 2262.406 | AD12: =IF(AND($B$31=1,LEN($AD$34)>0),$AD$34/1000,HLOOKUP(INDIRECT(ADDRESS(2,COLUMN())),OFFSET($BN$2,0,0,ROW()-1,60),ROW()-1,FALSE)) -> 2243.8448 | AE12: =IF(AND($B$31=1,LEN($AE$34)>0),$AE$34/1000,HLOOKUP(INDIRECT(ADDRESS(2,COLUMN())),OFFSET($BN$2,0,0,ROW()-1,60),ROW()-1,FALSE)) -> 2223.8868 | AF12: =IF(AND($B$31=1,LEN($AF$34)>0),$AF$34/1000,HLOOKUP(INDIRECT(ADDRESS(2,COLUMN())),OFFSET($BN$2,0,0,ROW()-1,60),ROW()-1,FALSE)) -> 2211.9023 | AG12: =IF(AND($B$31=1,LEN($AG$34)>0),$AG$34/1000,HLOOKUP(INDIRECT(ADDRESS(2,COLUMN())),OFFSET($BN$2,0,0,ROW()-1,60),ROW()-1,FALSE)) -> 2192.1088 | AH12: =IF(AND($B$31=1,LEN($AH$34)>0),$AH$34/1000,HLOOKUP(INDIRECT(ADDRESS(2,COLUMN())),OFFSET($BN$2,0,0,ROW()-1,60),ROW()-1,FALSE)) -> 2179.0635 | AI12: =IF(AND($B$31=1,LEN($AI$34)>0),$AI$34/1000,HLOOKUP(INDIRECT(ADDRESS(2,COLUMN())),OFFSET($BN$2,0,0,ROW()-1,60),ROW()-1,FALSE)) -> 2162.9735 | AJ12: =IF(AND($B$31=1,LEN($AJ$34)>0),$AJ$34/1000,HLOOKUP(INDIRECT(ADDRESS(2,COLUMN())),OFFSET($BN$2,0,0,ROW()-1,60),ROW()-1,FALSE)) -> 2146.671 | AK12: =IF(AND($B$31=1,LEN($AK$34)>0),$AK$34/1000,HLOOKUP(INDIRECT(ADDRESS(2,COLUMN())),OFFSET($BN$2,0,0,ROW()-1,60),ROW()-1,FALSE)) -> 2127.6025 | AL12: =IF(AND($B$31=1,LEN($AL$34)>0),$AL$34/1000,HLOOKUP(INDIRECT(ADDRESS(2,COLUMN())),OFFSET($BN$2,0,0,ROW()-1,60),ROW()-1,FALSE)) -> 2115.5038 | AM12: =IF(AND($B$31=1,LEN($AM$34)>0),$AM$34/1000,HLOOKUP(INDIRECT(ADDRESS(2,COLUMN())),OFFSET($BN$2,0,0,ROW()-1,60),ROW()-1,FALSE)) -> 2097.6108 | AN12: =IF(AND($B$31=1,LEN($AN$34)>0),$AN$34/1000,HLOOKUP(INDIRECT(ADDRESS(2,COLUMN())),OFFSET($BN$2,0,0,ROW()-1,60),ROW()-1,FALSE)) -> 2079.8827 | AO12: =IF(AND($B$31=1,LEN($AO$34)>0),$AO$34/1000,HLOOKUP(INDIRECT(ADDRESS(2,COLUMN())),OFFSET($BN$2,0,0,ROW()-1,60),ROW()-1,FALSE)) -> 2060.1064 | AP12: =IF(AND($B$31=1,LEN($AP$34)>0),$AP$34/1000,HLOOKUP(INDIRECT(ADDRESS(2,COLUMN())),OFFSET($BN$2,0,0,ROW()-1,60),ROW()-1,FALSE)) -> 2046.0933 | AQ12: =IF(AND($B$31=1,LEN($AQ$34)>0),$AQ$34/1000,HLOOKUP(INDIRECT(ADDRESS(2,COLUMN())),OFFSET($BN$2,0,0,ROW()-1,60),ROW()-1,FALSE)) -> 2035.5053 | AR12: =IF(AND($B$31=1,LEN($AR$34)>0),$AR$34/1000,HLOOKUP(INDIRECT(ADDRESS(2,COLUMN())),OFFSET($BN$2,0,0,ROW()-1,60),ROW()-1,FALSE)) -> 2024.6596 | AS12: =IF(AND($B$31=1,LEN($AS$34)>0),$AS$34/1000,HLOOKUP(INDIRECT(ADDRESS(2,COLUMN())),OFFSET($BN$2,0,0,ROW()-1,60),ROW()-1,FALSE)) -> 2014.993 | AT12: =IF(AND($B$31=1,LEN($AT$34)>0),$AT$34/1000,HLOOKUP(INDIRECT(ADDRESS(2,COLUMN())),OFFSET($BN$2,0,0,ROW()-1,60),ROW()-1,FALSE)) -> 2006.2547 | AU12: =IF(AND($B$31=1,LEN($AU$34)>0),$AU$34/1000,HLOOKUP(INDIRECT(ADDRESS(2,COLUMN())),OFFSET($BN$2,0,0,ROW()-1,60),ROW()-1,FALSE)) -> 1986.5366 | AV12: =IF(AND($B$31=1,LEN($AV$34)>0),$AV$34/1000,HLOOKUP(INDIRECT(ADDRESS(2,COLUMN())),OFFSET($BN$2,0,0,ROW()-1,60),ROW()-1,FALSE)) -> 1981.4085 | AW12: =IF(AND($B$31=1,LEN($AW$34)>0),$AW$34/1000,HLOOKUP(INDIRECT(ADDRESS(2,COLUMN())),OFFSET($BN$2,0,0,ROW()-1,60),ROW()-1,FALSE)) -> 1969.5667 | AX12: =IF(AND($B$31=1,LEN($AX$34)>0),$AX$34/1000,HLOOKUP(INDIRECT(ADDRESS(2,COLUMN())),OFFSET($BN$2,0,0,ROW()-1,60),ROW()-1,FALSE)) -> 1959.3503 | AY12: =IF(AND($B$31=1,LEN($AY$34)>0),$AY$34/1000,HLOOKUP(INDIRECT(ADDRESS(2,COLUMN())),OFFSET($BN$2,0,0,ROW()-1,60),ROW()-1,FALSE)) -> 1952.1088 | AZ12: =IF(AND($B$31=1,LEN($AZ$34)>0),$AZ$34/1000,HLOOKUP(INDIRECT(ADDRESS(2,COLUMN())),OFFSET($BN$2,0,0,ROW()-1,60),ROW()-1,FALSE)) -> 1946.3309 | BA12: =IF(AND($B$31=1,LEN($BA$34)>0),$BA$34/1000,HLOOKUP(INDIRECT(ADDRESS(2,COLUMN())),OFFSET($BN$2,0,0,ROW()-1,60),ROW()-1,FALSE)) -> 1941.221 | BB12: =IF(AND($B$31=1,LEN($BB$34)>0),$BB$34/1000,HLOOKUP(INDIRECT(ADDRESS(2,COLUMN())),OFFSET($BN$2,0,0,ROW()-1,60),ROW()-1,FALSE)) -> 1931.8702 | BC12: =IF(AND($B$31=1,LEN($BC$34)>0),$BC$34/1000,HLOOKUP(INDIRECT(ADDRESS(2,COLUMN())),OFFSET($BN$2,0,0,ROW()-1,60),ROW()-1,FALSE)) -> 1924.6826 | BD12: =IF(AND($B$31=1,LEN($BD$34)>0),$BD$34/1000,HLOOKUP(INDIRECT(ADDRESS(2,COLUMN())),OFFSET($BN$2,0,0,ROW()-1,60),ROW()-1,FALSE)) -> 1920.0997 | BE12: =IF(AND($B$31=1,LEN($BE$34)>0),$BE$34/1000,HLOOKUP(INDIRECT(ADDRESS(2,COLUMN())),OFFSET($BN$2,0,0,ROW()-1,60),ROW()-1,FALSE)) -> 1922.1627 | BF12: =IF(AND($B$31=1,LEN($BF$34)>0),$BF$34/1000,HLOOKUP(INDIRECT(ADDRESS(2,COLUMN())),OFFSET($BN$2,0,0,ROW()-1,60),ROW()-1,FALSE)) -> 1919.8425 | BG12: =IF(AND($B$31=1,LEN($BG$34)>0),$BG$34/1000,HLOOKUP(INDIRECT(ADDRESS(2,COLUMN())),OFFSET($BN$2,0,0,ROW()-1,60),ROW()-1,FALSE)) -> 1921.5766 | BH12: =IF(AND($B$31=1,LEN($BH$34)>0),$BH$34/1000,HLOOKUP(INDIRECT(ADDRESS(2,COLUMN())),OFFSET($BN$2,0,0,ROW()-1,60),ROW()-1,FALSE)) -> 1915.3692 | BI12: =IF(AND($B$31=1,LEN($BI$34)>0),$BI$34/1000,HLOOKUP(INDIRECT(ADDRESS(2,COLUMN())),OFFSET($BN$2,0,0,ROW()-1,60),ROW()-1,FALSE)) -> 1911.7589 | BJ12: =IF(AND($B$31=1,LEN($BJ$34)>0),$BJ$34/1000,HLOOKUP(INDIRECT(ADDRESS(2,COLUMN())),OFFSET($BN$2,0,0,ROW()-1,60),ROW()-1,FALSE)) -> 1907.5539 | BK12: =IF(AND($B$31=1,LEN($BK$34)>0),$BK$34/1000,HLOOKUP(INDIRECT(ADDRESS(2,COLUMN())),OFFSET($BN$2,0,0,ROW()-1,60),ROW()-1,FALSE)) -> 1899.2257 | BL12: =IF(AND($B$31=1,LEN($BL$34)>0),$BL$34/1000,HLOOKUP(INDIRECT(ADDRESS(2,COLUMN())),OFFSET($BN$2,0,0,ROW()-1,60),ROW()-1,FALSE)) -> 1889.6495 | BM12: =IF(AND($B$31=1,LEN($BM$34)>0),$BM$34/1000,HLOOKUP(INDIRECT(ADDRESS(2,COLUMN())),OFFSET($BN$2,0,0,ROW()-1,60),ROW()-1,FALSE)) -> 1876.8776 | BN12: ="" | BO12: =2888.1282 -> 2888.1282 | BP12: =2858.7927 -> 2858.7927 | BQ12: =2834.7721 -> 2834.7721 | BR12: =2805.52 -> 2805.52 | BS12: =2780.9173 -> 2780.9173 | BT12: =2752.5781 -> 2752.5781 | BU12: =2723.3114 -> 2723.3114 | BV12: =2693.8129 -> 2693.8129 | BW12: =2657.7057 -> 2657.7057 | BX12: =2620.6016 -> 2620.6016 | BY12: =2576.7203 -> 2576.7203 | BZ12: =2517.643 -> 2517.643 | CA12: =2458.7145 -> 2458.7145 | CB12: =2401.025 -> 2401.025 | CC12: =2360.2405 -> 2360.2405 | CD12: =2277.7042 -> 2277.7042 | CE12: =2196.5321 -> 2196.5321 | CF12: =2192.7202 -> 2192.7202 | CG12: =2221.9214 -> 2221.9214 | CH12: =2019.9591 -> 2019.9591 | CI12: =2204.7461 -> 2204.7461 | CJ12: =2273.1355 -> 2273.1355 | CK12: =2262.406 -> 2262.406 | CL12: =2243.8448 -> 2243.8448 | CM12: =2223.8868 -> 2223.8868 | CN12: =2211.9023 -> 2211.9023 | CO12: =2192.1088 -> 2192.1088 | CP12: =2179.0635 -> 2179.0635 | CQ12: =2162.9735 -> 2162.9735 | CR12: =2146.671 -> 2146.671 | CS12: =2127.6025 -> 2127.6025 | CT12: =2115.5038 -> 2115.5038 | CU12: =2097.6108 -> 2097.6108 | CV12: =2079.8827 -> 2079.8827 | CW12: =2060.1064 -> 2060.1064 | CX12: =2046.0933 -> 2046.0933 | CY12: =2035.5053 -> 2035.5053 | CZ12: =2024.6596 -> 2024.6596 | DA12: =2014.993 -> 2014.993 | DB12: =2006.2547 -> 2006.2547 | DC12: =1986.5366 -> 1986.5366 | DD12: =1981.4085 -> 1981.4085 | DE12: =1969.5667 -> 1969.5667 | DF12: =1959.3503 -> 1959.3503 | DG12: =1952.1088 -> 1952.1088 | DH12: =1946.3309 -> 1946.3309 | DI12: =1941.221 -> 1941.221 | DJ12: =1931.8702 -> 1931.8702 | DK12: =1924.6826 -> 1924.6826 | DL12: =1920.0997 -> 1920.0997 | DM12: =1922.1627 -> 1922.1627 | DN12: =1919.8425 -> 1919.8425 | DO12: =1921.5766 -> 1921.5766 | DP12: =1915.3692 -> 1915.3692 | DQ12: =1911.7589 -> 1911.7589 | DR12: =1907.5539 -> 1907.5539 | DS12: =1899.2257 -> 1899.2257 | DT12: =1889.6495 -> 1889.6495 | DU12: =1876.8776 -> 1876.8776
A13: =" Gross Fixed Capital Formation" -> Gross Fixed Capital Formation | B13: ="ENCPEAS Index" -> ENCPEAS Index | E13: ="Expression" -> Expression | F13: =IF(AND($B$31=1,LEN($F$35)>0),$F$35/1000,HLOOKUP(INDIRECT(ADDRESS(2,COLUMN())),OFFSET($BN$2,0,0,ROW()-1,60),ROW()-1,FALSE)) | G13: =IF(AND($B$31=1,LEN($G$35)>0),$G$35/1000,HLOOKUP(INDIRECT(ADDRESS(2,COLUMN())),OFFSET($BN$2,0,0,ROW()-1,60),ROW()-1,FALSE)) -> 836.3054 | H13: =IF(AND($B$31=1,LEN($H$35)>0),$H$35/1000,HLOOKUP(INDIRECT(ADDRESS(2,COLUMN())),OFFSET($BN$2,0,0,ROW()-1,60),ROW()-1,FALSE)) -> 828.5335 | I13: =IF(AND($B$31=1,LEN($I$35)>0),$I$35/1000,HLOOKUP(INDIRECT(ADDRESS(2,COLUMN())),OFFSET($BN$2,0,0,ROW()-1,60),ROW()-1,FALSE)) -> 813.3532 | J13: =IF(AND($B$31=1,LEN($J$35)>0),$J$35/1000,HLOOKUP(INDIRECT(ADDRESS(2,COLUMN())),OFFSET($BN$2,0,0,ROW()-1,60),ROW()-1,FALSE)) -> 780.6301 | K13: =IF(AND($B$31=1,LEN($K$35)>0),$K$35/1000,HLOOKUP(INDIRECT(ADDRESS(2,COLUMN())),OFFSET($BN$2,0,0,ROW()-1,60),ROW()-1,FALSE)) -> 789.9666 | L13: =IF(AND($B$31=1,LEN($L$35)>0),$L$35/1000,HLOOKUP(INDIRECT(ADDRESS(2,COLUMN())),OFFSET($BN$2,0,0,ROW()-1,60),ROW()-1,FALSE)) -> 815.9231 | M13: =IF(AND($B$31=1,LEN($M$35)>0),$M$35/1000,HLOOKUP(INDIRECT(ADDRESS(2,COLUMN())),OFFSET($BN$2,0,0,ROW()-1,60),ROW()-1,FALSE)) -> 806.4788 | N13: =IF(AND($B$31=1,LEN($N$35)>0),$N$35/1000,HLOOKUP(INDIRECT(ADDRESS(2,COLUMN())),OFFSET($BN$2,0,0,ROW()-1,60),ROW()-1,FALSE)) -> 817.1378 | O13: =IF(AND($B$31=1,LEN($O$35)>0),$O$35/1000,HLOOKUP(INDIRECT(ADDRESS(2,COLUMN())),OFFSET($BN$2,0,0,ROW()-1,60),ROW()-1,FALSE)) -> 820.8645 | P13: =IF(AND($B$31=1,LEN($P$35)>0),$P$35/1000,HLOOKUP(INDIRECT(ADDRESS(2,COLUMN())),OFFSET($BN$2,0,0,ROW()-1,60),ROW()-1,FALSE)) -> 819.1068 | Q13: =IF(AND($B$31=1,LEN($Q$35)>0),$Q$35/1000,HLOOKUP(INDIRECT(ADDRESS(2,COLUMN())),OFFSET($BN$2,0,0,ROW()-1,60),ROW()-1,FALSE)) -> 843.8806 | R13: =IF(AND($B$31=1,LEN($R$35)>0),$R$35/1000,HLOOKUP(INDIRECT(ADDRESS(2,COLUMN())),OFFSET($BN$2,0,0,ROW()-1,60),ROW()-1,FALSE)) -> 819.9767 | S13: =IF(AND($B$31=1,LEN($S$35)>0),$S$35/1000,HLOOKUP(INDIRECT(ADDRESS(2,COLUMN())),OFFSET($BN$2,0,0,ROW()-1,60),ROW()-1,FALSE)) -> 781.4184 | T13: =IF(AND($B$31=1,LEN($T$35)>0),$T$35/1000,HLOOKUP(INDIRECT(ADDRESS(2,COLUMN())),OFFSET($BN$2,0,0,ROW()-1,60),ROW()-1,FALSE)) -> 771.3735 | U13: =IF(AND($B$31=1,LEN($U$35)>0),$U$35/1000,HLOOKUP(INDIRECT(ADDRESS(2,COLUMN())),OFFSET($BN$2,0,0,ROW()-1,60),ROW()-1,FALSE)) -> 706.9498 | V13: =IF(AND($B$31=1,LEN($V$35)>0),$V$35/1000,HLOOKUP(INDIRECT(ADDRESS(2,COLUMN())),OFFSET($BN$2,0,0,ROW()-1,60),ROW()-1,FALSE)) -> 692.5553 | W13: =IF(AND($B$31=1,LEN($W$35)>0),$W$35/1000,HLOOKUP(INDIRECT(ADDRESS(2,COLUMN())),OFFSET($BN$2,0,0,ROW()-1,60),ROW()-1,FALSE)) -> 686.5293 | X13: =IF(AND($B$31=1,LEN($X$35)>0),$X$35/1000,HLOOKUP(INDIRECT(ADDRESS(2,COLUMN())),OFFSET($BN$2,0,0,ROW()-1,60),ROW()-1,FALSE)) -> 666.0808 | Y13: =IF(AND($B$31=1,LEN($Y$35)>0),$Y$35/1000,HLOOKUP(INDIRECT(ADDRESS(2,COLUMN())),OFFSET($BN$2,0,0,ROW()-1,60),ROW()-1,FALSE)) -> 608.8569 | Z13: =IF(AND($B$31=1,LEN($Z$35)>0),$Z$35/1000,HLOOKUP(INDIRECT(ADDRESS(2,COLUMN())),OFFSET($BN$2,0,0,ROW()-1,60),ROW()-1,FALSE)) -> 570.3004 | AA13: =IF(AND($B$31=1,LEN($AA$35)>0),$AA$35/1000,HLOOKUP(INDIRECT(ADDRESS(2,COLUMN())),OFFSET($BN$2,0,0,ROW()-1,60),ROW()-1,FALSE)) -> 705.3384 | AB13: =IF(AND($B$31=1,LEN($AB$35)>0),$AB$35/1000,HLOOKUP(INDIRECT(ADDRESS(2,COLUMN())),OFFSET($BN$2,0,0,ROW()-1,60),ROW()-1,FALSE)) -> 720.6733 | AC13: =IF(AND($B$31=1,LEN($AC$35)>0),$AC$35/1000,HLOOKUP(INDIRECT(ADDRESS(2,COLUMN())),OFFSET($BN$2,0,0,ROW()-1,60),ROW()-1,FALSE)) -> 653.7738 | AD13: =IF(AND($B$31=1,LEN($AD$35)>0),$AD$35/1000,HLOOKUP(INDIRECT(ADDRESS(2,COLUMN())),OFFSET($BN$2,0,0,ROW()-1,60),ROW()-1,FALSE)) -> 693.2723 | AE13: =IF(AND($B$31=1,LEN($AE$35)>0),$AE$35/1000,HLOOKUP(INDIRECT(ADDRESS(2,COLUMN())),OFFSET($BN$2,0,0,ROW()-1,60),ROW()-1,FALSE)) -> 650.2235 | AF13: =IF(AND($B$31=1,LEN($AF$35)>0),$AF$35/1000,HLOOKUP(INDIRECT(ADDRESS(2,COLUMN())),OFFSET($BN$2,0,0,ROW()-1,60),ROW()-1,FALSE)) -> 667.7749 | AG13: =IF(AND($B$31=1,LEN($AG$35)>0),$AG$35/1000,HLOOKUP(INDIRECT(ADDRESS(2,COLUMN())),OFFSET($BN$2,0,0,ROW()-1,60),ROW()-1,FALSE)) -> 635.6678 | AH13: =IF(AND($B$31=1,LEN($AH$35)>0),$AH$35/1000,HLOOKUP(INDIRECT(ADDRESS(2,COLUMN())),OFFSET($BN$2,0,0,ROW()-1,60),ROW()-1,FALSE)) -> 621.3755 | AI13: =IF(AND($B$31=1,LEN($AI$35)>0),$AI$35/1000,HLOOKUP(INDIRECT(ADDRESS(2,COLUMN())),OFFSET($BN$2,0,0,ROW()-1,60),ROW()-1,FALSE)) -> 609.0586 | AJ13: =IF(AND($B$31=1,LEN($AJ$35)>0),$AJ$35/1000,HLOOKUP(INDIRECT(ADDRESS(2,COLUMN())),OFFSET($BN$2,0,0,ROW()-1,60),ROW()-1,FALSE)) -> 603.208 | AK13: =IF(AND($B$31=1,LEN($AK$35)>0),$AK$35/1000,HLOOKUP(INDIRECT(ADDRESS(2,COLUMN())),OFFSET($BN$2,0,0,ROW()-1,60),ROW()-1,FALSE)) -> 591.2324 | AL13: =IF(AND($B$31=1,LEN($AL$35)>0),$AL$35/1000,HLOOKUP(INDIRECT(ADDRESS(2,COLUMN())),OFFSET($BN$2,0,0,ROW()-1,60),ROW()-1,FALSE)) -> 618.6726 | AM13: =IF(AND($B$31=1,LEN($AM$35)>0),$AM$35/1000,HLOOKUP(INDIRECT(ADDRESS(2,COLUMN())),OFFSET($BN$2,0,0,ROW()-1,60),ROW()-1,FALSE)) -> 572.9821 | AN13: =IF(AND($B$31=1,LEN($AN$35)>0),$AN$35/1000,HLOOKUP(INDIRECT(ADDRESS(2,COLUMN())),OFFSET($BN$2,0,0,ROW()-1,60),ROW()-1,FALSE)) -> 576.5579 | AO13: =IF(AND($B$31=1,LEN($AO$35)>0),$AO$35/1000,HLOOKUP(INDIRECT(ADDRESS(2,COLUMN())),OFFSET($BN$2,0,0,ROW()-1,60),ROW()-1,FALSE)) -> 559.4096 | AP13: =IF(AND($B$31=1,LEN($AP$35)>0),$AP$35/1000,HLOOKUP(INDIRECT(ADDRESS(2,COLUMN())),OFFSET($BN$2,0,0,ROW()-1,60),ROW()-1,FALSE)) -> 550.2859 | AQ13: =IF(AND($B$31=1,LEN($AQ$35)>0),$AQ$35/1000,HLOOKUP(INDIRECT(ADDRESS(2,COLUMN())),OFFSET($BN$2,0,0,ROW()-1,60),ROW()-1,FALSE)) -> 551.2994 | AR13: =IF(AND($B$31=1,LEN($AR$35)>0),$AR$35/1000,HLOOKUP(INDIRECT(ADDRESS(2,COLUMN())),OFFSET($BN$2,0,0,ROW()-1,60),ROW()-1,FALSE)) -> 549.6557 | AS13: =IF(AND($B$31=1,LEN($AS$35)>0),$AS$35/1000,HLOOKUP(INDIRECT(ADDRESS(2,COLUMN())),OFFSET($BN$2,0,0,ROW()-1,60),ROW()-1,FALSE)) -> 532.2464 | AT13: =IF(AND($B$31=1,LEN($AT$35)>0),$AT$35/1000,HLOOKUP(INDIRECT(ADDRESS(2,COLUMN())),OFFSET($BN$2,0,0,ROW()-1,60),ROW()-1,FALSE)) -> 550.1947 | AU13: =IF(AND($B$31=1,LEN($AU$35)>0),$AU$35/1000,HLOOKUP(INDIRECT(ADDRESS(2,COLUMN())),OFFSET($BN$2,0,0,ROW()-1,60),ROW()-1,FALSE)) -> 514.6238 | AV13: =IF(AND($B$31=1,LEN($AV$35)>0),$AV$35/1000,HLOOKUP(INDIRECT(ADDRESS(2,COLUMN())),OFFSET($BN$2,0,0,ROW()-1,60),ROW()-1,FALSE)) -> 508.7399 | AW13: =IF(AND($B$31=1,LEN($AW$35)>0),$AW$35/1000,HLOOKUP(INDIRECT(ADDRESS(2,COLUMN())),OFFSET($BN$2,0,0,ROW()-1,60),ROW()-1,FALSE)) -> 514.2515 | AX13: =IF(AND($B$31=1,LEN($AX$35)>0),$AX$35/1000,HLOOKUP(INDIRECT(ADDRESS(2,COLUMN())),OFFSET($BN$2,0,0,ROW()-1,60),ROW()-1,FALSE)) -> 511.056 | AY13: =IF(AND($B$31=1,LEN($AY$35)>0),$AY$35/1000,HLOOKUP(INDIRECT(ADDRESS(2,COLUMN())),OFFSET($BN$2,0,0,ROW()-1,60),ROW()-1,FALSE)) -> 509.1821 | AZ13: =IF(AND($B$31=1,LEN($AZ$35)>0),$AZ$35/1000,HLOOKUP(INDIRECT(ADDRESS(2,COLUMN())),OFFSET($BN$2,0,0,ROW()-1,60),ROW()-1,FALSE)) -> 496.0573 | BA13: =IF(AND($B$31=1,LEN($BA$35)>0),$BA$35/1000,HLOOKUP(INDIRECT(ADDRESS(2,COLUMN())),OFFSET($BN$2,0,0,ROW()-1,60),ROW()-1,FALSE)) -> 496.2414 | BB13: =IF(AND($B$31=1,LEN($BB$35)>0),$BB$35/1000,HLOOKUP(INDIRECT(ADDRESS(2,COLUMN())),OFFSET($BN$2,0,0,ROW()-1,60),ROW()-1,FALSE)) -> 489.269 | BC13: =IF(AND($B$31=1,LEN($BC$35)>0),$BC$35/1000,HLOOKUP(INDIRECT(ADDRESS(2,COLUMN())),OFFSET($BN$2,0,0,ROW()-1,60),ROW()-1,FALSE)) -> 478.2403 | BD13: =IF(AND($B$31=1,LEN($BD$35)>0),$BD$35/1000,HLOOKUP(INDIRECT(ADDRESS(2,COLUMN())),OFFSET($BN$2,0,0,ROW()-1,60),ROW()-1,FALSE)) -> 481.7896 | BE13: =IF(AND($B$31=1,LEN($BE$35)>0),$BE$35/1000,HLOOKUP(INDIRECT(ADDRESS(2,COLUMN())),OFFSET($BN$2,0,0,ROW()-1,60),ROW()-1,FALSE)) -> 488.335 | BF13: =IF(AND($B$31=1,LEN($BF$35)>0),$BF$35/1000,HLOOKUP(INDIRECT(ADDRESS(2,COLUMN())),OFFSET($BN$2,0,0,ROW()-1,60),ROW()-1,FALSE)) -> 497.2463 | BG13: =IF(AND($B$31=1,LEN($BG$35)>0),$BG$35/1000,HLOOKUP(INDIRECT(ADDRESS(2,COLUMN())),OFFSET($BN$2,0,0,ROW()-1,60),ROW()-1,FALSE)) -> 506.0857 | BH13: =IF(AND($B$31=1,LEN($BH$35)>0),$BH$35/1000,HLOOKUP(INDIRECT(ADDRESS(2,COLUMN())),OFFSET($BN$2,0,0,ROW()-1,60),ROW()-1,FALSE)) -> 516.2885 | BI13: =IF(AND($B$31=1,LEN($BI$35)>0),$BI$35/1000,HLOOKUP(INDIRECT(ADDRESS(2,COLUMN())),OFFSET($BN$2,0,0,ROW()-1,60),ROW()-1,FALSE)) -> 528.4429 | BJ13: =IF(AND($B$31=1,LEN($BJ$35)>0),$BJ$35/1000,HLOOKUP(INDIRECT(ADDRESS(2,COLUMN())),OFFSET($BN$2,0,0,ROW()-1,60),ROW()-1,FALSE)) -> 531.3475 | BK13: =IF(AND($B$31=1,LEN($BK$35)>0),$BK$35/1000,HLOOKUP(INDIRECT(ADDRESS(2,COLUMN())),OFFSET($BN$2,0,0,ROW()-1,60),ROW()-1,FALSE)) -> 539.9913 | BL13: =IF(AND($B$31=1,LEN($BL$35)>0),$BL$35/1000,HLOOKUP(INDIRECT(ADDRESS(2,COLUMN())),OFFSET($BN$2,0,0,ROW()-1,60),ROW()-1,FALSE)) -> 511.1024 | BM13: =IF(AND($B$31=1,LEN($BM$35)>0),$BM$35/1000,HLOOKUP(INDIRECT(ADDRESS(2,COLUMN())),OFFSET($BN$2,0,0,ROW()-1,60),ROW()-1,FALSE)) -> 503.6381 | BN13: ="" | BO13: =836.3054 -> 836.3054 | BP13: =828.5335 -> 828.5335 | BQ13: =813.3532 -> 813.3532 | BR13: =780.6301 -> 780.6301 | BS13: =789.9666 -> 789.9666 | BT13: =815.9231 -> 815.9231 | BU13: =806.4788 -> 806.4788 | BV13: =817.1378 -> 817.1378 | BW13: =820.8645 -> 820.8645 | BX13: =819.1068 -> 819.1068 | BY13: =843.8806 -> 843.8806 | BZ13: =819.9767 -> 819.9767 | CA13: =781.4184 -> 781.4184 | CB13: =771.3735 -> 771.3735 | CC13: =706.9498 -> 706.9498 | CD13: =692.5553 -> 692.5553 | CE13: =686.5293 -> 686.5293 | CF13: =666.0808 -> 666.0808 | CG13: =608.8569 -> 608.8569 | CH13: =570.3004 -> 570.3004 | CI13: =705.3384 -> 705.3384 | CJ13: =720.6733 -> 720.6733 | CK13: =653.7738 -> 653.7738 | CL13: =693.2723 -> 693.2723 | CM13: =650.2235 -> 650.2235 | CN13: =667.7749 -> 667.7749 | CO13: =635.6678 -> 635.6678 | CP13: =621.3755 -> 621.3755 | CQ13: =609.0586 -> 609.0586 | CR13: =603.208 -> 603.208 | CS13: =591.2324 -> 591.2324 | CT13: =618.6726 -> 618.6726 | CU13: =572.9821 -> 572.9821 | CV13: =576.5579 -> 576.5579 | CW13: =559.4096 -> 559.4096 | CX13: =550.2859 -> 550.2859 | CY13: =551.2994 -> 551.2994 | CZ13: =549.6557 -> 549.6557 | DA13: =532.2464 -> 532.2464 | DB13: =550.1947 -> 550.1947 | DC13: =514.6238 -> 514.6238 | DD13: =508.7399 -> 508.7399 | DE13: =514.2515 -> 514.2515 | DF13: =511.056 -> 511.056 | DG13: =509.1821 -> 509.1821 | DH13: =496.0573 -> 496.0573 | DI13: =496.2414 -> 496.2414 | DJ13: =489.269 -> 489.269 | DK13: =478.2403 -> 478.2403 | DL13: =481.7896 -> 481.7896 | DM13: =488.335 -> 488.335 | DN13: =497.2463 -> 497.2463 | DO13: =506.0857 -> 506.0857 | DP13: =516.2885 -> 516.2885 | DQ13: =528.4429 -> 528.4429 | DR13: =531.3475 -> 531.3475 | DS13: =539.9913 -> 539.9913 | DT13: =511.1024 -> 511.1024 | DU13: =503.6381 -> 503.6381
